Workbook

Sheet Start Here
A1: Payday Super review: s 18C deadlines and the SG charge estimate
A3: 1. On Register, paste one contribution line per row over the example rows, in the eleven canonical columns the command line tool reads and the importer writes. Dates are real Excel dates; amounts are dollars; yes/no columns take yes, no or blank (no).
A4: 2. On Summary, set the as-at date (notional earnings on unpaid lines run to it), an assessment date if the ATO has assessed, and the two confirmations the command line tool asks for: LCR 2026/1 transition allocation and remittance-only review.
A5: 3. Read the calculated columns on Register: pathway, final deadline, verdict (ON_TIME, AT_RISK, LATE, UNPAID, UNKNOWN, SKIPPED), the conservative outer outcomes where the facts cannot decide, days late, final shortfall after s 18D, notional earnings, the uplift range and the experimental SG charge estimate range.
A6: 4. Review Checks: BLOCKED means the register cannot be read or a required confirmation is missing. REVIEW means a line is exposed, a line is undecided, or the file cannot produce ON_TIME and remittance-only review is not confirmed. PASS mirrors the command line tool's exit code 0.
A7: 5. The statutory test is receipt by the fund. A remittance date alone gives AT_RISK, never ON_TIME. Fill fund_received_date from the clearing house or fund before treating a verdict as final.
A8: 6. Experimental review aid. Not a compliance determination. The ATO makes the assessment; choice loading, the maximum contributions base and post-assessment charges are not estimated.
A10: Overall status
A11: ='Review Checks'!B13 -> REVIEW
A13: payday-super-checker workbook, engine 0.1.3. Macro-free. Not advice; see DISCLAIMER.md in the repository.

Sheet Register
A1: employee_id | B1: payment_date | C1: sg_amount | D1: remitted_date | E1: remitted_amount | F1: matched_amount | G1: fund_received_date | H1: first_contribution_to_fund | I1: out_of_cycle | J1: next_standard_payday | K1: defined_benefit | L1: Flag_db | M1: Flag_ooc | N1: Flag_ftf | O1: Row_problem | P1: Guard | Q1: Cap | R1: Due_ooc | S1: Due_ftf | T1: Own_due | U1: Own_pathway | V1: Earliest_prepay | W1: Settled | X1: Remit | Y1: Receipt_credit | Z1: Credit | AA1: Evidence_own | AB1: Confirmed_latest | AC1: Possible_latest | AD1: Final_due | AE1: Pathway | AF1: Possible_item4 | AG1: Past_horizon | AH1: Branch | AI1: Verdict | AJ1: Unassessable_between | AK1: Exposed | AL1: Stale_prepay | AM1: OTRC | AN1: Base_shortfall | AO1: Offset_s18D | AP1: Final_shortfall | AQ1: Lateness_basis | AR1: Outstanding_to | AS1: NEC_end | AT1: Days_late | AU1: NEC | AV1: GIC_estimated | AW1: Shortfall_r | AX1: NEC_r | AY1: Uplift_best | AZ1: Uplift_worst | BA1: SGC_low | BB1: SGC_high | BC1: Transition_row | BD1: Receipt_established | BE1: Assessable | BF1: Duplicate
A2: EMP001 | B2: 46212 | C2: 612 | D2: 46217 | G2: 46219 | H2: no | I2: no | K2: no | L2: =IF(OR(LOWER(TRIM(tblLines[[#This Row],[defined_benefit]]&""))={"1","t","true","y","yes"}),1,IF(OR(LOWER(TRIM(tblLines[[#This Row],[defined_benefit]]&""))={"","0","f","false","n","no"}),0,"")) -> 0 | M2: =IF(OR(LOWER(TRIM(tblLines[[#This Row],[out_of_cycle]]&""))={"1","t","true","y","yes"}),1,IF(OR(LOWER(TRIM(tblLines[[#This Row],[out_of_cycle]]&""))={"","0","f","false","n","no"}),0,"")) -> 0 | N2: =IF(OR(LOWER(TRIM(tblLines[[#This Row],[first_contribution_to_fund]]&""))={"1","t","true","y","yes"}),1,IF(OR(LOWER(TRIM(tblLines[[#This Row],[first_contribution_to_fund]]&""))={"","0","f","false","n","no"}),0,"")) -> 0 | O2: =TRIM(IF(OR(AND(tblLines[[#This Row],[payment_date]]<>"",NOT(ISNUMBER(tblLines[[#This Row],[payment_date]]))),AND(tblLines[[#This Row],[remitted_date]]<>"",NOT(ISNUMBER(tblLines[[#This Row],[remitted_date]]))),AND(tblLines[[#This Row],[fund_received_date]]<>"",NOT(ISNUMBER(tblLines[[#This Row],[fund_received_date]]))),AND(tblLines[[#This Row],[next_standard_payday]]<>"",NOT(ISNUMBER(tblLines[[#This Row],[next_standard_payday]])))),"date ","")&IF(NOT(ISNUMBER(tblLines[[#This Row],[payment_date]])),"payment_date ","")&IF(AND(ISNUMBER(tblLines[[#This Row],[payment_date]]),tblLines[[#This Row],[payment_date]]<DATE(2026,7,1)),"pre-1-Jul-2026 ","")&IF(OR(AND(tblLines[[#This Row],[sg_amount]]<>"",OR(NOT(ISNUMBER(tblLines[[#This Row],[sg_amount]])),tblLines[[#This Row],[sg_amount]]<0)),AND(tblLines[[#This Row],[remitted_amount]]<>"",OR(NOT(ISNUMBER(tblLines[[#This Row],[remitted_amount]])),tblLines[[#This Row],[remitted_amount]]<0)),AND(tblLines[[#This Row],[matched_amount]]<>"",OR(NOT(ISNUMBER(tblLines[[#This Row],[matched_amount]])),tblLines[[#This Row],[matched_amount]]<0))),"amount ","")&IF(NOT(ISNUMBER(tblLines[[#This Row],[sg_amount]])),"sg_amount ","")&IF(OR(tblLines[[#This Row],[Flag_ftf]]="",tblLines[[#This Row],[Flag_ooc]]="",tblLines[[#This Row],[Flag_db]]=""),"yes/no ","")&IF(AND(ISNUMBER(tblLines[[#This Row],[remitted_amount]]),ISNUMBER(tblLines[[#This Row],[sg_amount]]),tblLines[[#This Row],[remitted_amount]]>tblLines[[#This Row],[sg_amount]]),"remitted_amount>sg ","")&IF(AND(ISNUMBER(tblLines[[#This Row],[remitted_amount]]),NOT(ISNUMBER(tblLines[[#This Row],[remitted_date]]))),"remitted_amount-needs-date ","")&IF(AND(ISNUMBER(tblLines[[#This Row],[matched_amount]]),ISNUMBER(tblLines[[#This Row],[sg_amount]]),tblLines[[#This Row],[matched_amount]]>tblLines[[#This Row],[sg_amount]]),"matched_amount>sg ","")&IF(AND(ISNUMBER(tblLines[[#This Row],[matched_amount]]),ISNUMBER(tblLines[[#This Row],[remitted_amount]]),tblLines[[#This Row],[remitted_amount]]>tblLines[[#This Row],[matched_amount]]),"remitted_amount>matched ","")&IF(AND(ISNUMBER(tblLines[[#This Row],[matched_amount]]),ISNUMBER(tblLines[[#This Row],[sg_amount]]),tblLines[[#This Row],[matched_amount]]<tblLines[[#This Row],[sg_amount]],ISNUMBER(tblLines[[#This Row],[remitted_date]]),NOT(ISNUMBER(tblLines[[#This Row],[remitted_amount]]))),"partial-match-needs-remitted_amount ","")&IF(AND(ISNUMBER(tblLines[[#This Row],[fund_received_date]]),ISNUMBER(tblLines[[#This Row],[remitted_date]]),tblLines[[#This Row],[fund_received_date]]<tblLines[[#This Row],[remitted_date]]),"receipt-before-remittance ","")&IF(AND(tblLines[[#This Row],[Flag_ooc]]=1,NOT(ISNUMBER(tblLines[[#This Row],[next_standard_payday]]))),"out_of_cycle-needs-next_standard_payday ","")&IF(AND(tblLines[[#This Row],[Flag_ooc]]=1,ISNUMBER(tblLines[[#This Row],[next_standard_payday]]),ISNUMBER(tblLines[[#This Row],[payment_date]]),tblLines[[#This Row],[next_standard_payday]]<=tblLines[[#This Row],[payment_date]]),"next_standard_payday-not-after-payday ","")) | P2: =IF(OR(_xlfn.ISFORMULA(tblLines[[#This Row],[employee_id]]),_xlfn.ISFORMULA(tblLines[[#This Row],[payment_date]]),_xlfn.ISFORMULA(tblLines[[#This Row],[sg_amount]]),_xlfn.ISFORMULA(tblLines[[#This Row],[remitted_date]]),_xlfn.ISFORMULA(tblLines[[#This Row],[remitted_amount]]),_xlfn.ISFORMULA(tblLines[[#This Row],[matched_amount]]),_xlfn.ISFORMULA(tblLines[[#This Row],[fund_received_date]]),_xlfn.ISFORMULA(tblLines[[#This Row],[first_contribution_to_fund]]),_xlfn.ISFORMULA(tblLines[[#This Row],[out_of_cycle]]),_xlfn.ISFORMULA(tblLines[[#This Row],[next_standard_payday]]),_xlfn.ISFORMULA(tblLines[[#This Row],[defined_benefit]])),1,0) -> 0 | Q2: =IF(ISNUMBER(tblLines[[#This Row],[matched_amount]]),tblLines[[#This Row],[matched_amount]],IF(ISNUMBER(tblLines[[#This Row],[remitted_amount]]),tblLines[[#This Row],[remitted_amount]],tblLines[[#This Row],[sg_amount]])) -> 612 | R2: =IF(AND(tblLines[[#This Row],[Flag_ooc]]=1,ISNUMBER(tblLines[[#This Row],[next_standard_payday]])),WORKDAY.INTL(tblLines[[#This Row],[next_standard_payday]],7,1,tblHolidays[date]),"") | S2: =IF(tblLines[[#This Row],[Flag_ftf]]=1,WORKDAY.INTL(tblLines[[#This Row],[payment_date]],20,1,tblHolidays[date]),"") | T2: =IF(OR(tblLines[[#This Row],[Flag_db]]=1,NOT(ISNUMBER(tblLines[[#This Row],[payment_date]]))),"",IF(OR(tblLines[[#This Row],[Flag_ooc]]=1,tblLines[[#This Row],[Flag_ftf]]=1),MAX(tblLines[[#This Row],[Due_ooc]],tblLines[[#This Row],[Due_ftf]]),WORKDAY.INTL(tblLines[[#This Row],[payment_date]],7,1,tblHolidays[date]))) -> 46223 | U2: =IF(tblLines[[#This Row],[Flag_db]]=1,"SKIP_DB",IF(tblLines[[#This Row],[Flag_ooc]]=1,IF(AND(tblLines[[#This Row],[Flag_ftf]]=1,tblLines[[#This Row],[Due_ftf]]>tblLines[[#This Row],[Due_ooc]]),"EXTENDED_20BD","OUT_OF_CYCLE"),IF(tblLines[[#This Row],[Flag_ftf]]=1,"EXTENDED_20BD","USUAL_7BD"))) -> USUAL_7BD | V2: =IF(ISNUMBER(tblLines[[#This Row],[payment_date]]),EDATE(tblLines[[#This Row],[payment_date]]-1,-12)+1,"") -> 45847 | W2: =IF(AND(ISNUMBER(tblLines[[#This Row],[fund_received_date]]),tblLines[[#This Row],[fund_received_date]]<=Summary!$B$2),tblLines[[#This Row],[fund_received_date]],"") -> 46219 | X2: =IF(AND(ISNUMBER(tblLines[[#This Row],[remitted_date]]),tblLines[[#This Row],[remitted_date]]<=Summary!$B$2),tblLines[[#This Row],[remitted_date]],"") -> 46217 | Y2: =IF(tblLines[[#This Row],[Settled]]<>"",MIN(ROUND(tblLines[[#This Row],[Cap]],2),ROUND(tblLines[[#This Row],[sg_amount]],2)),0) -> 612 | Z2: =IF(ISNUMBER(tblLines[[#This Row],[remitted_amount]]),IF(tblLines[[#This Row],[Remit]]<>"",MIN(ROUND(tblLines[[#This Row],[remitted_amount]],2),ROUND(tblLines[[#This Row],[sg_amount]],2)),0),IF(tblLines[[#This Row],[Remit]]<>"",ROUND(tblLines[[#This Row],[sg_amount]],2),0)) -> 612 | AA2: =IF(OR(tblLines[[#This Row],[Own_due]]="",tblLines[[#This Row],[sg_amount]]<=0,tblLines[[#This Row],[Flag_db]]=1,tblLines[[#This Row],[Cap]]<=0),"impossible",IF(ISNUMBER(tblLines[[#This Row],[fund_received_date]]),IF(tblLines[[#This Row],[fund_received_date]]<tblLines[[#This Row],[Earliest_prepay]],"impossible",IF(tblLines[[#This Row],[fund_received_date]]<=Summary!$B$2,IF(OR(tblLines[[#This Row],[fund_received_date]]<tblLines[[#This Row],[payment_date]],tblLines[[#This Row],[fund_received_date]]<=tblLines[[#This Row],[Own_due]]),"confirmed",IF(tblLines[[#This Row],[fund_received_date]]>tblLines[[#This Row],[Own_due]],"impossible","possible")),IF(tblLines[[#This Row],[fund_received_date]]<=tblLines[[#This Row],[Own_due]],"possible","impossible"))),IF(AND(ISNUMBER(tblLines[[#This Row],[remitted_date]]),tblLines[[#This Row],[remitted_date]]>tblLines[[#This Row],[Own_due]]),"impossible","possible"))) -> confirmed | AB2: =IF(OR(tblLines[[#This Row],[Flag_db]]=1,tblLines[[#This Row],[Own_due]]=""),"",_xlfn.MAXIFS(tblLines[Own_due],tblLines[employee_id],tblLines[[#This Row],[employee_id]],tblLines[payment_date],"<"&tblLines[[#This Row],[payment_date]],tblLines[Evidence_own],"confirmed")) -> 0 | AC2: =IF(OR(tblLines[[#This Row],[Flag_db]]=1,tblLines[[#This Row],[Own_due]]=""),"",_xlfn.MAXIFS(tblLines[Own_due],tblLines[employee_id],tblLines[[#This Row],[employee_id]],tblLines[payment_date],"<"&tblLines[[#This Row],[payment_date]],tblLines[Evidence_own],"<>impossible")) -> 0 | AD2: =IF(tblLines[[#This Row],[Own_due]]="","",IF(AND(ISNUMBER(tblLines[[#This Row],[Confirmed_latest]]),tblLines[[#This Row],[Confirmed_latest]]>tblLines[[#This Row],[Own_due]]),tblLines[[#This Row],[Confirmed_latest]],tblLines[[#This Row],[Own_due]])) -> 46223 | AE2: =IF(tblLines[[#This Row],[Own_due]]="",tblLines[[#This Row],[Own_pathway]],IF(AND(ISNUMBER(tblLines[[#This Row],[Confirmed_latest]]),tblLines[[#This Row],[Confirmed_latest]]>tblLines[[#This Row],[Own_due]]),"ITEM4_ALIGNED",tblLines[[#This Row],[Own_pathway]])) -> USUAL_7BD | AF2: =IF(tblLines[[#This Row],[Final_due]]="","",IF(AND(ISNUMBER(tblLines[[#This Row],[Possible_latest]]),tblLines[[#This Row],[Possible_latest]]>tblLines[[#This Row],[Final_due]]),tblLines[[#This Row],[Possible_latest]],"")) | AG2: =IF(tblLines[[#This Row],[Final_due]]="","",IF((tblLines[[#This Row],[Final_due]]>Summary!$B$6),1,0)) -> 0 | AH2: =IF(tblLines[[#This Row],[Flag_db]]=1,"DB",IF(tblLines[[#This Row],[Final_due]]="","",IF(tblLines[[#This Row],[sg_amount]]<=0,"NIL",IF(tblLines[[#This Row],[Settled]]<>"",IF(tblLines[[#This Row],[Settled]]<tblLines[[#This Row],[payment_date]],IF(tblLines[[#This Row],[Settled]]>=tblLines[[#This Row],[Earliest_prepay]],IF((tblLines[[#This Row],[Receipt_credit]]>=tblLines[[#This Row],[sg_amount]]),"A1",IF(tblLines[[#This Row],[Final_due]]>=Summary!$B$2,"A2",IF(OR((tblLines[[#This Row],[Final_due]]>Summary!$B$6),AND((tblLines[[#This Row],[Possible_item4]]<>""),Summary!$B$2<=tblLines[[#This Row],[Possible_item4]])),"A3","A4"))),IF(tblLines[[#This Row],[Final_due]]>=Summary!$B$2,"S1",IF(OR((tblLines[[#This Row],[Final_due]]>Summary!$B$6),AND((tblLines[[#This Row],[Possible_item4]]<>""),Summary!$B$2<=tblLines[[#This Row],[Possible_item4]])),"S2","S3"))),IF(AND((tblLines[[#This Row],[Possible_item4]]<>""),tblLines[[#This Row],[Final_due]]<tblLines[[#This Row],[Settled]],tblLines[[#This Row],[Settled]]<=tblLines[[#This Row],[Possible_item4]]),IF((tblLines[[#This Row],[Receipt_credit]]>=tblLines[[#This Row],[sg_amount]]),"B1",IF(Summary!$B$2<=tblLines[[#This Row],[Possible_item4]],"B2","B3")),IF(AND((tblLines[[#This Row],[Final_due]]>Summary!$B$6),tblLines[[#This Row],[Settled]]>tblLines[[#This Row],[Final_due]]),IF((tblLines[[#This Row],[Receipt_credit]]>=tblLines[[#This Row],[sg_amount]]),"C1","C2"),IF(tblLines[[#This Row],[Settled]]<=tblLines[[#This Row],[Final_due]],IF((tblLines[[#This Row],[Receipt_credit]]>=tblLines[[#This Row],[sg_amount]]),"D1",IF(OR((tblLines[[#This Row],[Final_due]]>Summary!$B$6),AND((tblLines[[#This Row],[Possible_item4]]<>""),Summary!$B$2<=tblLines[[#This Row],[Possible_item4]])),"D2",IF(tblLines[[#This Row],[Final_due]]<Summary!$B$2,"D3","D4"))),"E")))),IF(AND(tblLines[[#This Row],[Remit]]<>"",tblLines[[#This Row],[sg_amount]]-tblLines[[#This Row],[Credit]]<=0),IF(AND((tblLines[[#This Row],[Possible_item4]]<>""),tblLines[[#This Row],[Final_due]]<tblLines[[#This Row],[Remit]],tblLines[[#This Row],[Remit]]<=tblLines[[#This Row],[Possible_item4]]),"R1",IF(AND((tblLines[[#This Row],[Final_due]]>Summary!$B$6),tblLines[[#This Row],[Remit]]>tblLines[[#This Row],[Final_due]]),"R2",IF(tblLines[[#This Row],[Remit]]<=tblLines[[#This Row],[Final_due]],"R3","R4"))),IF(tblLines[[#This Row],[Final_due]]<Summary!$B$2,IF(OR((tblLines[[#This Row],[Final_due]]>Summary!$B$6),AND((tblLines[[#This Row],[Possible_item4]]<>""),Summary!$B$2<=tblLines[[#This Row],[Possible_item4]])),"N1","N2"),"N3")))))) -> D1 | AI2: =IF(tblLines[[#This Row],[Branch]]="","",INDEX(tblCodes[verdict],MATCH(tblLines[[#This Row],[Branch]],tblCodes[code],0))) -> ON_TIME | AJ2: =IF(tblLines[[#This Row],[Branch]]="","",T(INDEX(tblCodes[unassessable],MATCH(tblLines[[#This Row],[Branch]],tblCodes[code],0)))) | AK2: =IF(tblLines[[#This Row],[Branch]]="",0,INDEX(tblCodes[exposed],MATCH(tblLines[[#This Row],[Branch]],tblCodes[code],0))) -> 0 | AL2: =IF(tblLines[[#This Row],[Branch]]="",0,INDEX(tblCodes[stale],MATCH(tblLines[[#This Row],[Branch]],tblCodes[code],0))) -> 0 | AM2: =IF(tblLines[[#This Row],[Branch]]="",0,INDEX(tblCodes[otrc],MATCH(tblLines[[#This Row],[Branch]],tblCodes[code],0))*tblLines[[#This Row],[Receipt_credit]]) -> 612 | AN2: =IF((tblLines[[#This Row],[Exposed]]=1),MAX(ROUND(tblLines[[#This Row],[sg_amount]],2)-tblLines[[#This Row],[OTRC]],0),"") | AO2: =IF((tblLines[[#This Row],[Exposed]]=1),IF(AND(tblLines[[#This Row],[Settled]]<>"",tblLines[[#This Row],[Stale_prepay]]=0,tblLines[[#This Row],[Settled]]>tblLines[[#This Row],[Final_due]],OR(Summary!$B$3="",tblLines[[#This Row],[Settled]]<Summary!$B$3)),MIN(tblLines[[#This Row],[Receipt_credit]],tblLines[[#This Row],[Base_shortfall]]),0),"") | AP2: =IF((tblLines[[#This Row],[Exposed]]=1),MAX(tblLines[[#This Row],[Base_shortfall]]-tblLines[[#This Row],[Offset_s18D]],0),"") | AQ2: =IF((tblLines[[#This Row],[Exposed]]=1),IF(AND(tblLines[[#This Row],[Settled]]<>"",tblLines[[#This Row],[Stale_prepay]]=0,(tblLines[[#This Row],[Receipt_credit]]>=tblLines[[#This Row],[sg_amount]])),"fund receipt",IF(AND(tblLines[[#This Row],[Settled]]<>"",tblLines[[#This Row],[Stale_prepay]]=0),"as-at date (shortfall remains after part receipt)",IF(AND(OR(tblLines[[#This Row],[Settled]]<>"",tblLines[[#This Row],[Remit]]<>""),tblLines[[#This Row],[Stale_prepay]]=0),"as-at date (no fund receipt recorded)","as-at date (nothing applied to this payday)"))),"") | AR2: =IF((tblLines[[#This Row],[Exposed]]=1),IF(AND(tblLines[[#This Row],[Settled]]<>"",tblLines[[#This Row],[Stale_prepay]]=0,(tblLines[[#This Row],[Receipt_credit]]>=tblLines[[#This Row],[sg_amount]])),tblLines[[#This Row],[Settled]],Summary!$B$2),"") | AS2: =IF((tblLines[[#This Row],[Exposed]]=1),MIN(IF(Summary!$B$3="",DATE(2030,12,31),Summary!$B$3-1),IF(AND(tblLines[[#This Row],[Settled]]<>"",tblLines[[#This Row],[Stale_prepay]]=0,(tblLines[[#This Row],[Receipt_credit]]>=tblLines[[#This Row],[sg_amount]]),tblLines[[#This Row],[Final_shortfall]]=0),tblLines[[#This Row],[Settled]],Summary!$B$2)),"") | AT2: =IF((tblLines[[#This Row],[Exposed]]=1),IF(tblLines[[#This Row],[Past_horizon]]=1,"",MAX(tblLines[[#This Row],[Outstanding_to]]-tblLines[[#This Row],[Final_due]],0)),"") | AU2: =IF((tblLines[[#This Row],[Exposed]]=1),IF(tblLines[[#This Row],[NEC_end]]>tblLines[[#This Row],[Final_due]],tblLines[[#This Row],[Base_shortfall]]*(EXP(SUMPRODUCT((((((tblLines[[#This Row],[NEC_end]]+tblGic[to]-ABS(tblLines[[#This Row],[NEC_end]]-tblGic[to]))/2)-(((tblLines[[#This Row],[Final_due]]+1)+tblGic[from]+ABS((tblLines[[#This Row],[Final_due]]+1)-tblGic[from]))/2)+1)>0)*(((tblLines[[#This Row],[NEC_end]]+tblGic[to]-ABS(tblLines[[#This Row],[NEC_end]]-tblGic[to]))/2)-(((tblLines[[#This Row],[Final_due]]+1)+tblGic[from]+ABS((tblLines[[#This Row],[Final_due]]+1)-tblGic[from]))/2)+1))*LN(1+tblGic[annual_pct]/100/tblGic[divisor])))-1),0),"") | AV2: =IF((tblLines[[#This Row],[Exposed]]=1),IF(tblLines[[#This Row],[NEC_end]]>Summary!$B$7,1,0),"") | AW2: =IF((tblLines[[#This Row],[Exposed]]=1),ROUND(tblLines[[#This Row],[Final_shortfall]],2),"") | AX2: =IF((tblLines[[#This Row],[Exposed]]=1),ROUND(tblLines[[#This Row],[NEC]],2),"") | AY2: =IF((tblLines[[#This Row],[Exposed]]=1),0,"") | AZ2: =IF((tblLines[[#This Row],[Exposed]]=1),ROUND(0.6*(tblLines[[#This Row],[Final_shortfall]]+tblLines[[#This Row],[NEC]]),2),"") | BA2: =IF((tblLines[[#This Row],[Exposed]]=1),tblLines[[#This Row],[Shortfall_r]]+tblLines[[#This Row],[NEC_r]]+tblLines[[#This Row],[Uplift_best]],"") | BB2: =IF((tblLines[[#This Row],[Exposed]]=1),tblLines[[#This Row],[Shortfall_r]]+tblLines[[#This Row],[NEC_r]]+tblLines[[#This Row],[Uplift_worst]],"") | BC2: =IF(AND(tblLines[[#This Row],[Flag_db]]<>1,ISNUMBER(tblLines[[#This Row],[sg_amount]]),tblLines[[#This Row],[sg_amount]]>0,tblLines[[#This Row],[Cap]]>0,OR(ISNUMBER(tblLines[[#This Row],[fund_received_date]]),ISNUMBER(tblLines[[#This Row],[remitted_date]])),IF(ISNUMBER(tblLines[[#This Row],[fund_received_date]]),tblLines[[#This Row],[fund_received_date]],tblLines[[#This Row],[remitted_date]])<=DATE(2026,7,28)),1,0) -> 1 | BD2: =IF(tblLines[[#This Row],[Settled]]<>"",1,0) -> 1 | BE2: =IF(AND(tblLines[[#This Row],[Verdict]]<>"",tblLines[[#This Row],[Verdict]]<>"SKIPPED",ISNUMBER(tblLines[[#This Row],[sg_amount]]),tblLines[[#This Row],[sg_amount]]>0),1,0) -> 1 | BF2: =IF(COUNTIFS(tblLines[employee_id],tblLines[[#This Row],[employee_id]],tblLines[payment_date],tblLines[[#This Row],[payment_date]],tblLines[sg_amount],tblLines[[#This Row],[sg_amount]],tblLines[remitted_date],tblLines[[#This Row],[remitted_date]]&"",tblLines[fund_received_date],tblLines[[#This Row],[fund_received_date]]&"")>1,1,0) -> 0
A3: EMP002 | B3: 46212 | C3: 540 | D3: 46233 | G3: 46238 | H3: no | I3: no | K3: no | L3: =IF(OR(LOWER(TRIM(tblLines[[#This Row],[defined_benefit]]&""))={"1","t","true","y","yes"}),1,IF(OR(LOWER(TRIM(tblLines[[#This Row],[defined_benefit]]&""))={"","0","f","false","n","no"}),0,"")) -> 0 | M3: =IF(OR(LOWER(TRIM(tblLines[[#This Row],[out_of_cycle]]&""))={"1","t","true","y","yes"}),1,IF(OR(LOWER(TRIM(tblLines[[#This Row],[out_of_cycle]]&""))={"","0","f","false","n","no"}),0,"")) -> 0 | N3: =IF(OR(LOWER(TRIM(tblLines[[#This Row],[first_contribution_to_fund]]&""))={"1","t","true","y","yes"}),1,IF(OR(LOWER(TRIM(tblLines[[#This Row],[first_contribution_to_fund]]&""))={"","0","f","false","n","no"}),0,"")) -> 0 | O3: =TRIM(IF(OR(AND(tblLines[[#This Row],[payment_date]]<>"",NOT(ISNUMBER(tblLines[[#This Row],[payment_date]]))),AND(tblLines[[#This Row],[remitted_date]]<>"",NOT(ISNUMBER(tblLines[[#This Row],[remitted_date]]))),AND(tblLines[[#This Row],[fund_received_date]]<>"",NOT(ISNUMBER(tblLines[[#This Row],[fund_received_date]]))),AND(tblLines[[#This Row],[next_standard_payday]]<>"",NOT(ISNUMBER(tblLines[[#This Row],[next_standard_payday]])))),"date ","")&IF(NOT(ISNUMBER(tblLines[[#This Row],[payment_date]])),"payment_date ","")&IF(AND(ISNUMBER(tblLines[[#This Row],[payment_date]]),tblLines[[#This Row],[payment_date]]<DATE(2026,7,1)),"pre-1-Jul-2026 ","")&IF(OR(AND(tblLines[[#This Row],[sg_amount]]<>"",OR(NOT(ISNUMBER(tblLines[[#This Row],[sg_amount]])),tblLines[[#This Row],[sg_amount]]<0)),AND(tblLines[[#This Row],[remitted_amount]]<>"",OR(NOT(ISNUMBER(tblLines[[#This Row],[remitted_amount]])),tblLines[[#This Row],[remitted_amount]]<0)),AND(tblLines[[#This Row],[matched_amount]]<>"",OR(NOT(ISNUMBER(tblLines[[#This Row],[matched_amount]])),tblLines[[#This Row],[matched_amount]]<0))),"amount ","")&IF(NOT(ISNUMBER(tblLines[[#This Row],[sg_amount]])),"sg_amount ","")&IF(OR(tblLines[[#This Row],[Flag_ftf]]="",tblLines[[#This Row],[Flag_ooc]]="",tblLines[[#This Row],[Flag_db]]=""),"yes/no ","")&IF(AND(ISNUMBER(tblLines[[#This Row],[remitted_amount]]),ISNUMBER(tblLines[[#This Row],[sg_amount]]),tblLines[[#This Row],[remitted_amount]]>tblLines[[#This Row],[sg_amount]]),"remitted_amount>sg ","")&IF(AND(ISNUMBER(tblLines[[#This Row],[remitted_amount]]),NOT(ISNUMBER(tblLines[[#This Row],[remitted_date]]))),"remitted_amount-needs-date ","")&IF(AND(ISNUMBER(tblLines[[#This Row],[matched_amount]]),ISNUMBER(tblLines[[#This Row],[sg_amount]]),tblLines[[#This Row],[matched_amount]]>tblLines[[#This Row],[sg_amount]]),"matched_amount>sg ","")&IF(AND(ISNUMBER(tblLines[[#This Row],[matched_amount]]),ISNUMBER(tblLines[[#This Row],[remitted_amount]]),tblLines[[#This Row],[remitted_amount]]>tblLines[[#This Row],[matched_amount]]),"remitted_amount>matched ","")&IF(AND(ISNUMBER(tblLines[[#This Row],[matched_amount]]),ISNUMBER(tblLines[[#This Row],[sg_amount]]),tblLines[[#This Row],[matched_amount]]<tblLines[[#This Row],[sg_amount]],ISNUMBER(tblLines[[#This Row],[remitted_date]]),NOT(ISNUMBER(tblLines[[#This Row],[remitted_amount]]))),"partial-match-needs-remitted_amount ","")&IF(AND(ISNUMBER(tblLines[[#This Row],[fund_received_date]]),ISNUMBER(tblLines[[#This Row],[remitted_date]]),tblLines[[#This Row],[fund_received_date]]<tblLines[[#This Row],[remitted_date]]),"receipt-before-remittance ","")&IF(AND(tblLines[[#This Row],[Flag_ooc]]=1,NOT(ISNUMBER(tblLines[[#This Row],[next_standard_payday]]))),"out_of_cycle-needs-next_standard_payday ","")&IF(AND(tblLines[[#This Row],[Flag_ooc]]=1,ISNUMBER(tblLines[[#This Row],[next_standard_payday]]),ISNUMBER(tblLines[[#This Row],[payment_date]]),tblLines[[#This Row],[next_standard_payday]]<=tblLines[[#This Row],[payment_date]]),"next_standard_payday-not-after-payday ","")) | P3: =IF(OR(_xlfn.ISFORMULA(tblLines[[#This Row],[employee_id]]),_xlfn.ISFORMULA(tblLines[[#This Row],[payment_date]]),_xlfn.ISFORMULA(tblLines[[#This Row],[sg_amount]]),_xlfn.ISFORMULA(tblLines[[#This Row],[remitted_date]]),_xlfn.ISFORMULA(tblLines[[#This Row],[remitted_amount]]),_xlfn.ISFORMULA(tblLines[[#This Row],[matched_amount]]),_xlfn.ISFORMULA(tblLines[[#This Row],[fund_received_date]]),_xlfn.ISFORMULA(tblLines[[#This Row],[first_contribution_to_fund]]),_xlfn.ISFORMULA(tblLines[[#This Row],[out_of_cycle]]),_xlfn.ISFORMULA(tblLines[[#This Row],[next_standard_payday]]),_xlfn.ISFORMULA(tblLines[[#This Row],[defined_benefit]])),1,0) -> 0 | Q3: =IF(ISNUMBER(tblLines[[#This Row],[matched_amount]]),tblLines[[#This Row],[matched_amount]],IF(ISNUMBER(tblLines[[#This Row],[remitted_amount]]),tblLines[[#This Row],[remitted_amount]],tblLines[[#This Row],[sg_amount]])) -> 540 | R3: =IF(AND(tblLines[[#This Row],[Flag_ooc]]=1,ISNUMBER(tblLines[[#This Row],[next_standard_payday]])),WORKDAY.INTL(tblLines[[#This Row],[next_standard_payday]],7,1,tblHolidays[date]),"") | S3: =IF(tblLines[[#This Row],[Flag_ftf]]=1,WORKDAY.INTL(tblLines[[#This Row],[payment_date]],20,1,tblHolidays[date]),"") | T3: =IF(OR(tblLines[[#This Row],[Flag_db]]=1,NOT(ISNUMBER(tblLines[[#This Row],[payment_date]]))),"",IF(OR(tblLines[[#This Row],[Flag_ooc]]=1,tblLines[[#This Row],[Flag_ftf]]=1),MAX(tblLines[[#This Row],[Due_ooc]],tblLines[[#This Row],[Due_ftf]]),WORKDAY.INTL(tblLines[[#This Row],[payment_date]],7,1,tblHolidays[date]))) -> 46223 | U3: =IF(tblLines[[#This Row],[Flag_db]]=1,"SKIP_DB",IF(tblLines[[#This Row],[Flag_ooc]]=1,IF(AND(tblLines[[#This Row],[Flag_ftf]]=1,tblLines[[#This Row],[Due_ftf]]>tblLines[[#This Row],[Due_ooc]]),"EXTENDED_20BD","OUT_OF_CYCLE"),IF(tblLines[[#This Row],[Flag_ftf]]=1,"EXTENDED_20BD","USUAL_7BD"))) -> USUAL_7BD | V3: =IF(ISNUMBER(tblLines[[#This Row],[payment_date]]),EDATE(tblLines[[#This Row],[payment_date]]-1,-12)+1,"") -> 45847 | W3: =IF(AND(ISNUMBER(tblLines[[#This Row],[fund_received_date]]),tblLines[[#This Row],[fund_received_date]]<=Summary!$B$2),tblLines[[#This Row],[fund_received_date]],"") -> 46238 | X3: =IF(AND(ISNUMBER(tblLines[[#This Row],[remitted_date]]),tblLines[[#This Row],[remitted_date]]<=Summary!$B$2),tblLines[[#This Row],[remitted_date]],"") -> 46233 | Y3: =IF(tblLines[[#This Row],[Settled]]<>"",MIN(ROUND(tblLines[[#This Row],[Cap]],2),ROUND(tblLines[[#This Row],[sg_amount]],2)),0) -> 540 | Z3: =IF(ISNUMBER(tblLines[[#This Row],[remitted_amount]]),IF(tblLines[[#This Row],[Remit]]<>"",MIN(ROUND(tblLines[[#This Row],[remitted_amount]],2),ROUND(tblLines[[#This Row],[sg_amount]],2)),0),IF(tblLines[[#This Row],[Remit]]<>"",ROUND(tblLines[[#This Row],[sg_amount]],2),0)) -> 540 | AA3: =IF(OR(tblLines[[#This Row],[Own_due]]="",tblLines[[#This Row],[sg_amount]]<=0,tblLines[[#This Row],[Flag_db]]=1,tblLines[[#This Row],[Cap]]<=0),"impossible",IF(ISNUMBER(tblLines[[#This Row],[fund_received_date]]),IF(tblLines[[#This Row],[fund_received_date]]<tblLines[[#This Row],[Earliest_prepay]],"impossible",IF(tblLines[[#This Row],[fund_received_date]]<=Summary!$B$2,IF(OR(tblLines[[#This Row],[fund_received_date]]<tblLines[[#This Row],[payment_date]],tblLines[[#This Row],[fund_received_date]]<=tblLines[[#This Row],[Own_due]]),"confirmed",IF(tblLines[[#This Row],[fund_received_date]]>tblLines[[#This Row],[Own_due]],"impossible","possible")),IF(tblLines[[#This Row],[fund_received_date]]<=tblLines[[#This Row],[Own_due]],"possible","impossible"))),IF(AND(ISNUMBER(tblLines[[#This Row],[remitted_date]]),tblLines[[#This Row],[remitted_date]]>tblLines[[#This Row],[Own_due]]),"impossible","possible"))) -> impossible | AB3: =IF(OR(tblLines[[#This Row],[Flag_db]]=1,tblLines[[#This Row],[Own_due]]=""),"",_xlfn.MAXIFS(tblLines[Own_due],tblLines[employee_id],tblLines[[#This Row],[employee_id]],tblLines[payment_date],"<"&tblLines[[#This Row],[payment_date]],tblLines[Evidence_own],"confirmed")) -> 0 | AC3: =IF(OR(tblLines[[#This Row],[Flag_db]]=1,tblLines[[#This Row],[Own_due]]=""),"",_xlfn.MAXIFS(tblLines[Own_due],tblLines[employee_id],tblLines[[#This Row],[employee_id]],tblLines[payment_date],"<"&tblLines[[#This Row],[payment_date]],tblLines[Evidence_own],"<>impossible")) -> 0 | AD3: =IF(tblLines[[#This Row],[Own_due]]="","",IF(AND(ISNUMBER(tblLines[[#This Row],[Confirmed_latest]]),tblLines[[#This Row],[Confirmed_latest]]>tblLines[[#This Row],[Own_due]]),tblLines[[#This Row],[Confirmed_latest]],tblLines[[#This Row],[Own_due]])) -> 46223 | AE3: =IF(tblLines[[#This Row],[Own_due]]="",tblLines[[#This Row],[Own_pathway]],IF(AND(ISNUMBER(tblLines[[#This Row],[Confirmed_latest]]),tblLines[[#This Row],[Confirmed_latest]]>tblLines[[#This Row],[Own_due]]),"ITEM4_ALIGNED",tblLines[[#This Row],[Own_pathway]])) -> USUAL_7BD | AF3: =IF(tblLines[[#This Row],[Final_due]]="","",IF(AND(ISNUMBER(tblLines[[#This Row],[Possible_latest]]),tblLines[[#This Row],[Possible_latest]]>tblLines[[#This Row],[Final_due]]),tblLines[[#This Row],[Possible_latest]],"")) | AG3: =IF(tblLines[[#This Row],[Final_due]]="","",IF((tblLines[[#This Row],[Final_due]]>Summary!$B$6),1,0)) -> 0 | AH3: =IF(tblLines[[#This Row],[Flag_db]]=1,"DB",IF(tblLines[[#This Row],[Final_due]]="","",IF(tblLines[[#This Row],[sg_amount]]<=0,"NIL",IF(tblLines[[#This Row],[Settled]]<>"",IF(tblLines[[#This Row],[Settled]]<tblLines[[#This Row],[payment_date]],IF(tblLines[[#This Row],[Settled]]>=tblLines[[#This Row],[Earliest_prepay]],IF((tblLines[[#This Row],[Receipt_credit]]>=tblLines[[#This Row],[sg_amount]]),"A1",IF(tblLines[[#This Row],[Final_due]]>=Summary!$B$2,"A2",IF(OR((tblLines[[#This Row],[Final_due]]>Summary!$B$6),AND((tblLines[[#This Row],[Possible_item4]]<>""),Summary!$B$2<=tblLines[[#This Row],[Possible_item4]])),"A3","A4"))),IF(tblLines[[#This Row],[Final_due]]>=Summary!$B$2,"S1",IF(OR((tblLines[[#This Row],[Final_due]]>Summary!$B$6),AND((tblLines[[#This Row],[Possible_item4]]<>""),Summary!$B$2<=tblLines[[#This Row],[Possible_item4]])),"S2","S3"))),IF(AND((tblLines[[#This Row],[Possible_item4]]<>""),tblLines[[#This Row],[Final_due]]<tblLines[[#This Row],[Settled]],tblLines[[#This Row],[Settled]]<=tblLines[[#This Row],[Possible_item4]]),IF((tblLines[[#This Row],[Receipt_credit]]>=tblLines[[#This Row],[sg_amount]]),"B1",IF(Summary!$B$2<=tblLines[[#This Row],[Possible_item4]],"B2","B3")),IF(AND((tblLines[[#This Row],[Final_due]]>Summary!$B$6),tblLines[[#This Row],[Settled]]>tblLines[[#This Row],[Final_due]]),IF((tblLines[[#This Row],[Receipt_credit]]>=tblLines[[#This Row],[sg_amount]]),"C1","C2"),IF(tblLines[[#This Row],[Settled]]<=tblLines[[#This Row],[Final_due]],IF((tblLines[[#This Row],[Receipt_credit]]>=tblLines[[#This Row],[sg_amount]]),"D1",IF(OR((tblLines[[#This Row],[Final_due]]>Summary!$B$6),AND((tblLines[[#This Row],[Possible_item4]]<>""),Summary!$B$2<=tblLines[[#This Row],[Possible_item4]])),"D2",IF(tblLines[[#This Row],[Final_due]]<Summary!$B$2,"D3","D4"))),"E")))),IF(AND(tblLines[[#This Row],[Remit]]<>"",tblLines[[#This Row],[sg_amount]]-tblLines[[#This Row],[Credit]]<=0),IF(AND((tblLines[[#This Row],[Possible_item4]]<>""),tblLines[[#This Row],[Final_due]]<tblLines[[#This Row],[Remit]],tblLines[[#This Row],[Remit]]<=tblLines[[#This Row],[Possible_item4]]),"R1",IF(AND((tblLines[[#This Row],[Final_due]]>Summary!$B$6),tblLines[[#This Row],[Remit]]>tblLines[[#This Row],[Final_due]]),"R2",IF(tblLines[[#This Row],[Remit]]<=tblLines[[#This Row],[Final_due]],"R3","R4"))),IF(tblLines[[#This Row],[Final_due]]<Summary!$B$2,IF(OR((tblLines[[#This Row],[Final_due]]>Summary!$B$6),AND((tblLines[[#This Row],[Possible_item4]]<>""),Summary!$B$2<=tblLines[[#This Row],[Possible_item4]])),"N1","N2"),"N3")))))) -> E | AI3: =IF(tblLines[[#This Row],[Branch]]="","",INDEX(tblCodes[verdict],MATCH(tblLines[[#This Row],[Branch]],tblCodes[code],0))) -> LATE | AJ3: =IF(tblLines[[#This Row],[Branch]]="","",T(INDEX(tblCodes[unassessable],MATCH(tblLines[[#This Row],[Branch]],tblCodes[code],0)))) | AK3: =IF(tblLines[[#This Row],[Branch]]="",0,INDEX(tblCodes[exposed],MATCH(tblLines[[#This Row],[Branch]],tblCodes[code],0))) -> 1 | AL3: =IF(tblLines[[#This Row],[Branch]]="",0,INDEX(tblCodes[stale],MATCH(tblLines[[#This Row],[Branch]],tblCodes[code],0))) -> 0 | AM3: =IF(tblLines[[#This Row],[Branch]]="",0,INDEX(tblCodes[otrc],MATCH(tblLines[[#This Row],[Branch]],tblCodes[code],0))*tblLines[[#This Row],[Receipt_credit]]) -> 0 | AN3: =IF((tblLines[[#This Row],[Exposed]]=1),MAX(ROUND(tblLines[[#This Row],[sg_amount]],2)-tblLines[[#This Row],[OTRC]],0),"") -> 540 | AO3: =IF((tblLines[[#This Row],[Exposed]]=1),IF(AND(tblLines[[#This Row],[Settled]]<>"",tblLines[[#This Row],[Stale_prepay]]=0,tblLines[[#This Row],[Settled]]>tblLines[[#This Row],[Final_due]],OR(Summary!$B$3="",tblLines[[#This Row],[Settled]]<Summary!$B$3)),MIN(tblLines[[#This Row],[Receipt_credit]],tblLines[[#This Row],[Base_shortfall]]),0),"") -> 540 | AP3: =IF((tblLines[[#This Row],[Exposed]]=1),MAX(tblLines[[#This Row],[Base_shortfall]]-tblLines[[#This Row],[Offset_s18D]],0),"") -> 0 | AQ3: =IF((tblLines[[#This Row],[Exposed]]=1),IF(AND(tblLines[[#This Row],[Settled]]<>"",tblLines[[#This Row],[Stale_prepay]]=0,(tblLines[[#This Row],[Receipt_credit]]>=tblLines[[#This Row],[sg_amount]])),"fund receipt",IF(AND(tblLines[[#This Row],[Settled]]<>"",tblLines[[#This Row],[Stale_prepay]]=0),"as-at date (shortfall remains after part receipt)",IF(AND(OR(tblLines[[#This Row],[Settled]]<>"",tblLines[[#This Row],[Remit]]<>""),tblLines[[#This Row],[Stale_prepay]]=0),"as-at date (no fund receipt recorded)","as-at date (nothing applied to this payday)"))),"") -> fund receipt | AR3: =IF((tblLines[[#This Row],[Exposed]]=1),IF(AND(tblLines[[#This Row],[Settled]]<>"",tblLines[[#This Row],[Stale_prepay]]=0,(tblLines[[#This Row],[Receipt_credit]]>=tblLines[[#This Row],[sg_amount]])),tblLines[[#This Row],[Settled]],Summary!$B$2),"") -> 46238 | AS3: =IF((tblLines[[#This Row],[Exposed]]=1),MIN(IF(Summary!$B$3="",DATE(2030,12,31),Summary!$B$3-1),IF(AND(tblLines[[#This Row],[Settled]]<>"",tblLines[[#This Row],[Stale_prepay]]=0,(tblLines[[#This Row],[Receipt_credit]]>=tblLines[[#This Row],[sg_amount]]),tblLines[[#This Row],[Final_shortfall]]=0),tblLines[[#This Row],[Settled]],Summary!$B$2)),"") -> 46238 | AT3: =IF((tblLines[[#This Row],[Exposed]]=1),IF(tblLines[[#This Row],[Past_horizon]]=1,"",MAX(tblLines[[#This Row],[Outstanding_to]]-tblLines[[#This Row],[Final_due]],0)),"") -> 15 | AU3: =IF((tblLines[[#This Row],[Exposed]]=1),IF(tblLines[[#This Row],[NEC_end]]>tblLines[[#This Row],[Final_due]],tblLines[[#This Row],[Base_shortfall]]*(EXP(SUMPRODUCT((((((tblLines[[#This Row],[NEC_end]]+tblGic[to]-ABS(tblLines[[#This Row],[NEC_end]]-tblGic[to]))/2)-(((tblLines[[#This Row],[Final_due]]+1)+tblGic[from]+ABS((tblLines[[#This Row],[Final_due]]+1)-tblGic[from]))/2)+1)>0)*(((tblLines[[#This Row],[NEC_end]]+tblGic[to]-ABS(tblLines[[#This Row],[NEC_end]]-tblGic[to]))/2)-(((tblLines[[#This Row],[Final_due]]+1)+tblGic[from]+ABS((tblLines[[#This Row],[Final_due]]+1)-tblGic[from]))/2)+1))*LN(1+tblGic[annual_pct]/100/tblGic[divisor])))-1),0),"") -> 2.5420883 | AV3: =IF((tblLines[[#This Row],[Exposed]]=1),IF(tblLines[[#This Row],[NEC_end]]>Summary!$B$7,1,0),"") -> 0 | AW3: =IF((tblLines[[#This Row],[Exposed]]=1),ROUND(tblLines[[#This Row],[Final_shortfall]],2),"") -> 0 | AX3: =IF((tblLines[[#This Row],[Exposed]]=1),ROUND(tblLines[[#This Row],[NEC]],2),"") -> 2.54 | AY3: =IF((tblLines[[#This Row],[Exposed]]=1),0,"") -> 0 | AZ3: =IF((tblLines[[#This Row],[Exposed]]=1),ROUND(0.6*(tblLines[[#This Row],[Final_shortfall]]+tblLines[[#This Row],[NEC]]),2),"") -> 1.53 | BA3: =IF((tblLines[[#This Row],[Exposed]]=1),tblLines[[#This Row],[Shortfall_r]]+tblLines[[#This Row],[NEC_r]]+tblLines[[#This Row],[Uplift_best]],"") -> 2.54 | BB3: =IF((tblLines[[#This Row],[Exposed]]=1),tblLines[[#This Row],[Shortfall_r]]+tblLines[[#This Row],[NEC_r]]+tblLines[[#This Row],[Uplift_worst]],"") -> 4.07 | BC3: =IF(AND(tblLines[[#This Row],[Flag_db]]<>1,ISNUMBER(tblLines[[#This Row],[sg_amount]]),tblLines[[#This Row],[sg_amount]]>0,tblLines[[#This Row],[Cap]]>0,OR(ISNUMBER(tblLines[[#This Row],[fund_received_date]]),ISNUMBER(tblLines[[#This Row],[remitted_date]])),IF(ISNUMBER(tblLines[[#This Row],[fund_received_date]]),tblLines[[#This Row],[fund_received_date]],tblLines[[#This Row],[remitted_date]])<=DATE(2026,7,28)),1,0) -> 0 | BD3: =IF(tblLines[[#This Row],[Settled]]<>"",1,0) -> 1 | BE3: =IF(AND(tblLines[[#This Row],[Verdict]]<>"",tblLines[[#This Row],[Verdict]]<>"SKIPPED",ISNUMBER(tblLines[[#This Row],[sg_amount]]),tblLines[[#This Row],[sg_amount]]>0),1,0) -> 1 | BF3: =IF(COUNTIFS(tblLines[employee_id],tblLines[[#This Row],[employee_id]],tblLines[payment_date],tblLines[[#This Row],[payment_date]],tblLines[sg_amount],tblLines[[#This Row],[sg_amount]],tblLines[remitted_date],tblLines[[#This Row],[remitted_date]]&"",tblLines[fund_received_date],tblLines[[#This Row],[fund_received_date]]&"")>1,1,0) -> 0
A4: EMP003 | B4: 46212 | C4: 318 | D4: 46218 | H4: no | I4: no | K4: no | L4: =IF(OR(LOWER(TRIM(tblLines[[#This Row],[defined_benefit]]&""))={"1","t","true","y","yes"}),1,IF(OR(LOWER(TRIM(tblLines[[#This Row],[defined_benefit]]&""))={"","0","f","false","n","no"}),0,"")) -> 0 | M4: =IF(OR(LOWER(TRIM(tblLines[[#This Row],[out_of_cycle]]&""))={"1","t","true","y","yes"}),1,IF(OR(LOWER(TRIM(tblLines[[#This Row],[out_of_cycle]]&""))={"","0","f","false","n","no"}),0,"")) -> 0 | N4: =IF(OR(LOWER(TRIM(tblLines[[#This Row],[first_contribution_to_fund]]&""))={"1","t","true","y","yes"}),1,IF(OR(LOWER(TRIM(tblLines[[#This Row],[first_contribution_to_fund]]&""))={"","0","f","false","n","no"}),0,"")) -> 0 | O4: =TRIM(IF(OR(AND(tblLines[[#This Row],[payment_date]]<>"",NOT(ISNUMBER(tblLines[[#This Row],[payment_date]]))),AND(tblLines[[#This Row],[remitted_date]]<>"",NOT(ISNUMBER(tblLines[[#This Row],[remitted_date]]))),AND(tblLines[[#This Row],[fund_received_date]]<>"",NOT(ISNUMBER(tblLines[[#This Row],[fund_received_date]]))),AND(tblLines[[#This Row],[next_standard_payday]]<>"",NOT(ISNUMBER(tblLines[[#This Row],[next_standard_payday]])))),"date ","")&IF(NOT(ISNUMBER(tblLines[[#This Row],[payment_date]])),"payment_date ","")&IF(AND(ISNUMBER(tblLines[[#This Row],[payment_date]]),tblLines[[#This Row],[payment_date]]<DATE(2026,7,1)),"pre-1-Jul-2026 ","")&IF(OR(AND(tblLines[[#This Row],[sg_amount]]<>"",OR(NOT(ISNUMBER(tblLines[[#This Row],[sg_amount]])),tblLines[[#This Row],[sg_amount]]<0)),AND(tblLines[[#This Row],[remitted_amount]]<>"",OR(NOT(ISNUMBER(tblLines[[#This Row],[remitted_amount]])),tblLines[[#This Row],[remitted_amount]]<0)),AND(tblLines[[#This Row],[matched_amount]]<>"",OR(NOT(ISNUMBER(tblLines[[#This Row],[matched_amount]])),tblLines[[#This Row],[matched_amount]]<0))),"amount ","")&IF(NOT(ISNUMBER(tblLines[[#This Row],[sg_amount]])),"sg_amount ","")&IF(OR(tblLines[[#This Row],[Flag_ftf]]="",tblLines[[#This Row],[Flag_ooc]]="",tblLines[[#This Row],[Flag_db]]=""),"yes/no ","")&IF(AND(ISNUMBER(tblLines[[#This Row],[remitted_amount]]),ISNUMBER(tblLines[[#This Row],[sg_amount]]),tblLines[[#This Row],[remitted_amount]]>tblLines[[#This Row],[sg_amount]]),"remitted_amount>sg ","")&IF(AND(ISNUMBER(tblLines[[#This Row],[remitted_amount]]),NOT(ISNUMBER(tblLines[[#This Row],[remitted_date]]))),"remitted_amount-needs-date ","")&IF(AND(ISNUMBER(tblLines[[#This Row],[matched_amount]]),ISNUMBER(tblLines[[#This Row],[sg_amount]]),tblLines[[#This Row],[matched_amount]]>tblLines[[#This Row],[sg_amount]]),"matched_amount>sg ","")&IF(AND(ISNUMBER(tblLines[[#This Row],[matched_amount]]),ISNUMBER(tblLines[[#This Row],[remitted_amount]]),tblLines[[#This Row],[remitted_amount]]>tblLines[[#This Row],[matched_amount]]),"remitted_amount>matched ","")&IF(AND(ISNUMBER(tblLines[[#This Row],[matched_amount]]),ISNUMBER(tblLines[[#This Row],[sg_amount]]),tblLines[[#This Row],[matched_amount]]<tblLines[[#This Row],[sg_amount]],ISNUMBER(tblLines[[#This Row],[remitted_date]]),NOT(ISNUMBER(tblLines[[#This Row],[remitted_amount]]))),"partial-match-needs-remitted_amount ","")&IF(AND(ISNUMBER(tblLines[[#This Row],[fund_received_date]]),ISNUMBER(tblLines[[#This Row],[remitted_date]]),tblLines[[#This Row],[fund_received_date]]<tblLines[[#This Row],[remitted_date]]),"receipt-before-remittance ","")&IF(AND(tblLines[[#This Row],[Flag_ooc]]=1,NOT(ISNUMBER(tblLines[[#This Row],[next_standard_payday]]))),"out_of_cycle-needs-next_standard_payday ","")&IF(AND(tblLines[[#This Row],[Flag_ooc]]=1,ISNUMBER(tblLines[[#This Row],[next_standard_payday]]),ISNUMBER(tblLines[[#This Row],[payment_date]]),tblLines[[#This Row],[next_standard_payday]]<=tblLines[[#This Row],[payment_date]]),"next_standard_payday-not-after-payday ","")) | P4: =IF(OR(_xlfn.ISFORMULA(tblLines[[#This Row],[employee_id]]),_xlfn.ISFORMULA(tblLines[[#This Row],[payment_date]]),_xlfn.ISFORMULA(tblLines[[#This Row],[sg_amount]]),_xlfn.ISFORMULA(tblLines[[#This Row],[remitted_date]]),_xlfn.ISFORMULA(tblLines[[#This Row],[remitted_amount]]),_xlfn.ISFORMULA(tblLines[[#This Row],[matched_amount]]),_xlfn.ISFORMULA(tblLines[[#This Row],[fund_received_date]]),_xlfn.ISFORMULA(tblLines[[#This Row],[first_contribution_to_fund]]),_xlfn.ISFORMULA(tblLines[[#This Row],[out_of_cycle]]),_xlfn.ISFORMULA(tblLines[[#This Row],[next_standard_payday]]),_xlfn.ISFORMULA(tblLines[[#This Row],[defined_benefit]])),1,0) -> 0 | Q4: =IF(ISNUMBER(tblLines[[#This Row],[matched_amount]]),tblLines[[#This Row],[matched_amount]],IF(ISNUMBER(tblLines[[#This Row],[remitted_amount]]),tblLines[[#This Row],[remitted_amount]],tblLines[[#This Row],[sg_amount]])) -> 318 | R4: =IF(AND(tblLines[[#This Row],[Flag_ooc]]=1,ISNUMBER(tblLines[[#This Row],[next_standard_payday]])),WORKDAY.INTL(tblLines[[#This Row],[next_standard_payday]],7,1,tblHolidays[date]),"") | S4: =IF(tblLines[[#This Row],[Flag_ftf]]=1,WORKDAY.INTL(tblLines[[#This Row],[payment_date]],20,1,tblHolidays[date]),"") | T4: =IF(OR(tblLines[[#This Row],[Flag_db]]=1,NOT(ISNUMBER(tblLines[[#This Row],[payment_date]]))),"",IF(OR(tblLines[[#This Row],[Flag_ooc]]=1,tblLines[[#This Row],[Flag_ftf]]=1),MAX(tblLines[[#This Row],[Due_ooc]],tblLines[[#This Row],[Due_ftf]]),WORKDAY.INTL(tblLines[[#This Row],[payment_date]],7,1,tblHolidays[date]))) -> 46223 | U4: =IF(tblLines[[#This Row],[Flag_db]]=1,"SKIP_DB",IF(tblLines[[#This Row],[Flag_ooc]]=1,IF(AND(tblLines[[#This Row],[Flag_ftf]]=1,tblLines[[#This Row],[Due_ftf]]>tblLines[[#This Row],[Due_ooc]]),"EXTENDED_20BD","OUT_OF_CYCLE"),IF(tblLines[[#This Row],[Flag_ftf]]=1,"EXTENDED_20BD","USUAL_7BD"))) -> USUAL_7BD | V4: =IF(ISNUMBER(tblLines[[#This Row],[payment_date]]),EDATE(tblLines[[#This Row],[payment_date]]-1,-12)+1,"") -> 45847 | W4: =IF(AND(ISNUMBER(tblLines[[#This Row],[fund_received_date]]),tblLines[[#This Row],[fund_received_date]]<=Summary!$B$2),tblLines[[#This Row],[fund_received_date]],"") | X4: =IF(AND(ISNUMBER(tblLines[[#This Row],[remitted_date]]),tblLines[[#This Row],[remitted_date]]<=Summary!$B$2),tblLines[[#This Row],[remitted_date]],"") -> 46218 | Y4: =IF(tblLines[[#This Row],[Settled]]<>"",MIN(ROUND(tblLines[[#This Row],[Cap]],2),ROUND(tblLines[[#This Row],[sg_amount]],2)),0) -> 0 | Z4: =IF(ISNUMBER(tblLines[[#This Row],[remitted_amount]]),IF(tblLines[[#This Row],[Remit]]<>"",MIN(ROUND(tblLines[[#This Row],[remitted_amount]],2),ROUND(tblLines[[#This Row],[sg_amount]],2)),0),IF(tblLines[[#This Row],[Remit]]<>"",ROUND(tblLines[[#This Row],[sg_amount]],2),0)) -> 318 | AA4: =IF(OR(tblLines[[#This Row],[Own_due]]="",tblLines[[#This Row],[sg_amount]]<=0,tblLines[[#This Row],[Flag_db]]=1,tblLines[[#This Row],[Cap]]<=0),"impossible",IF(ISNUMBER(tblLines[[#This Row],[fund_received_date]]),IF(tblLines[[#This Row],[fund_received_date]]<tblLines[[#This Row],[Earliest_prepay]],"impossible",IF(tblLines[[#This Row],[fund_received_date]]<=Summary!$B$2,IF(OR(tblLines[[#This Row],[fund_received_date]]<tblLines[[#This Row],[payment_date]],tblLines[[#This Row],[fund_received_date]]<=tblLines[[#This Row],[Own_due]]),"confirmed",IF(tblLines[[#This Row],[fund_received_date]]>tblLines[[#This Row],[Own_due]],"impossible","possible")),IF(tblLines[[#This Row],[fund_received_date]]<=tblLines[[#This Row],[Own_due]],"possible","impossible"))),IF(AND(ISNUMBER(tblLines[[#This Row],[remitted_date]]),tblLines[[#This Row],[remitted_date]]>tblLines[[#This Row],[Own_due]]),"impossible","possible"))) -> possible | AB4: =IF(OR(tblLines[[#This Row],[Flag_db]]=1,tblLines[[#This Row],[Own_due]]=""),"",_xlfn.MAXIFS(tblLines[Own_due],tblLines[employee_id],tblLines[[#This Row],[employee_id]],tblLines[payment_date],"<"&tblLines[[#This Row],[payment_date]],tblLines[Evidence_own],"confirmed")) -> 0 | AC4: =IF(OR(tblLines[[#This Row],[Flag_db]]=1,tblLines[[#This Row],[Own_due]]=""),"",_xlfn.MAXIFS(tblLines[Own_due],tblLines[employee_id],tblLines[[#This Row],[employee_id]],tblLines[payment_date],"<"&tblLines[[#This Row],[payment_date]],tblLines[Evidence_own],"<>impossible")) -> 0 | AD4: =IF(tblLines[[#This Row],[Own_due]]="","",IF(AND(ISNUMBER(tblLines[[#This Row],[Confirmed_latest]]),tblLines[[#This Row],[Confirmed_latest]]>tblLines[[#This Row],[Own_due]]),tblLines[[#This Row],[Confirmed_latest]],tblLines[[#This Row],[Own_due]])) -> 46223 | AE4: =IF(tblLines[[#This Row],[Own_due]]="",tblLines[[#This Row],[Own_pathway]],IF(AND(ISNUMBER(tblLines[[#This Row],[Confirmed_latest]]),tblLines[[#This Row],[Confirmed_latest]]>tblLines[[#This Row],[Own_due]]),"ITEM4_ALIGNED",tblLines[[#This Row],[Own_pathway]])) -> USUAL_7BD | AF4: =IF(tblLines[[#This Row],[Final_due]]="","",IF(AND(ISNUMBER(tblLines[[#This Row],[Possible_latest]]),tblLines[[#This Row],[Possible_latest]]>tblLines[[#This Row],[Final_due]]),tblLines[[#This Row],[Possible_latest]],"")) | AG4: =IF(tblLines[[#This Row],[Final_due]]="","",IF((tblLines[[#This Row],[Final_due]]>Summary!$B$6),1,0)) -> 0 | AH4: =IF(tblLines[[#This Row],[Flag_db]]=1,"DB",IF(tblLines[[#This Row],[Final_due]]="","",IF(tblLines[[#This Row],[sg_amount]]<=0,"NIL",IF(tblLines[[#This Row],[Settled]]<>"",IF(tblLines[[#This Row],[Settled]]<tblLines[[#This Row],[payment_date]],IF(tblLines[[#This Row],[Settled]]>=tblLines[[#This Row],[Earliest_prepay]],IF((tblLines[[#This Row],[Receipt_credit]]>=tblLines[[#This Row],[sg_amount]]),"A1",IF(tblLines[[#This Row],[Final_due]]>=Summary!$B$2,"A2",IF(OR((tblLines[[#This Row],[Final_due]]>Summary!$B$6),AND((tblLines[[#This Row],[Possible_item4]]<>""),Summary!$B$2<=tblLines[[#This Row],[Possible_item4]])),"A3","A4"))),IF(tblLines[[#This Row],[Final_due]]>=Summary!$B$2,"S1",IF(OR((tblLines[[#This Row],[Final_due]]>Summary!$B$6),AND((tblLines[[#This Row],[Possible_item4]]<>""),Summary!$B$2<=tblLines[[#This Row],[Possible_item4]])),"S2","S3"))),IF(AND((tblLines[[#This Row],[Possible_item4]]<>""),tblLines[[#This Row],[Final_due]]<tblLines[[#This Row],[Settled]],tblLines[[#This Row],[Settled]]<=tblLines[[#This Row],[Possible_item4]]),IF((tblLines[[#This Row],[Receipt_credit]]>=tblLines[[#This Row],[sg_amount]]),"B1",IF(Summary!$B$2<=tblLines[[#This Row],[Possible_item4]],"B2","B3")),IF(AND((tblLines[[#This Row],[Final_due]]>Summary!$B$6),tblLines[[#This Row],[Settled]]>tblLines[[#This Row],[Final_due]]),IF((tblLines[[#This Row],[Receipt_credit]]>=tblLines[[#This Row],[sg_amount]]),"C1","C2"),IF(tblLines[[#This Row],[Settled]]<=tblLines[[#This Row],[Final_due]],IF((tblLines[[#This Row],[Receipt_credit]]>=tblLines[[#This Row],[sg_amount]]),"D1",IF(OR((tblLines[[#This Row],[Final_due]]>Summary!$B$6),AND((tblLines[[#This Row],[Possible_item4]]<>""),Summary!$B$2<=tblLines[[#This Row],[Possible_item4]])),"D2",IF(tblLines[[#This Row],[Final_due]]<Summary!$B$2,"D3","D4"))),"E")))),IF(AND(tblLines[[#This Row],[Remit]]<>"",tblLines[[#This Row],[sg_amount]]-tblLines[[#This Row],[Credit]]<=0),IF(AND((tblLines[[#This Row],[Possible_item4]]<>""),tblLines[[#This Row],[Final_due]]<tblLines[[#This Row],[Remit]],tblLines[[#This Row],[Remit]]<=tblLines[[#This Row],[Possible_item4]]),"R1",IF(AND((tblLines[[#This Row],[Final_due]]>Summary!$B$6),tblLines[[#This Row],[Remit]]>tblLines[[#This Row],[Final_due]]),"R2",IF(tblLines[[#This Row],[Remit]]<=tblLines[[#This Row],[Final_due]],"R3","R4"))),IF(tblLines[[#This Row],[Final_due]]<Summary!$B$2,IF(OR((tblLines[[#This Row],[Final_due]]>Summary!$B$6),AND((tblLines[[#This Row],[Possible_item4]]<>""),Summary!$B$2<=tblLines[[#This Row],[Possible_item4]])),"N1","N2"),"N3")))))) -> R3 | AI4: =IF(tblLines[[#This Row],[Branch]]="","",INDEX(tblCodes[verdict],MATCH(tblLines[[#This Row],[Branch]],tblCodes[code],0))) -> AT_RISK | AJ4: =IF(tblLines[[#This Row],[Branch]]="","",T(INDEX(tblCodes[unassessable],MATCH(tblLines[[#This Row],[Branch]],tblCodes[code],0)))) | AK4: =IF(tblLines[[#This Row],[Branch]]="",0,INDEX(tblCodes[exposed],MATCH(tblLines[[#This Row],[Branch]],tblCodes[code],0))) -> 0 | AL4: =IF(tblLines[[#This Row],[Branch]]="",0,INDEX(tblCodes[stale],MATCH(tblLines[[#This Row],[Branch]],tblCodes[code],0))) -> 0 | AM4: =IF(tblLines[[#This Row],[Branch]]="",0,INDEX(tblCodes[otrc],MATCH(tblLines[[#This Row],[Branch]],tblCodes[code],0))*tblLines[[#This Row],[Receipt_credit]]) -> 0 | AN4: =IF((tblLines[[#This Row],[Exposed]]=1),MAX(ROUND(tblLines[[#This Row],[sg_amount]],2)-tblLines[[#This Row],[OTRC]],0),"") | AO4: =IF((tblLines[[#This Row],[Exposed]]=1),IF(AND(tblLines[[#This Row],[Settled]]<>"",tblLines[[#This Row],[Stale_prepay]]=0,tblLines[[#This Row],[Settled]]>tblLines[[#This Row],[Final_due]],OR(Summary!$B$3="",tblLines[[#This Row],[Settled]]<Summary!$B$3)),MIN(tblLines[[#This Row],[Receipt_credit]],tblLines[[#This Row],[Base_shortfall]]),0),"") | AP4: =IF((tblLines[[#This Row],[Exposed]]=1),MAX(tblLines[[#This Row],[Base_shortfall]]-tblLines[[#This Row],[Offset_s18D]],0),"") | AQ4: =IF((tblLines[[#This Row],[Exposed]]=1),IF(AND(tblLines[[#This Row],[Settled]]<>"",tblLines[[#This Row],[Stale_prepay]]=0,(tblLines[[#This Row],[Receipt_credit]]>=tblLines[[#This Row],[sg_amount]])),"fund receipt",IF(AND(tblLines[[#This Row],[Settled]]<>"",tblLines[[#This Row],[Stale_prepay]]=0),"as-at date (shortfall remains after part receipt)",IF(AND(OR(tblLines[[#This Row],[Settled]]<>"",tblLines[[#This Row],[Remit]]<>""),tblLines[[#This Row],[Stale_prepay]]=0),"as-at date (no fund receipt recorded)","as-at date (nothing applied to this payday)"))),"") | AR4: =IF((tblLines[[#This Row],[Exposed]]=1),IF(AND(tblLines[[#This Row],[Settled]]<>"",tblLines[[#This Row],[Stale_prepay]]=0,(tblLines[[#This Row],[Receipt_credit]]>=tblLines[[#This Row],[sg_amount]])),tblLines[[#This Row],[Settled]],Summary!$B$2),"") | AS4: =IF((tblLines[[#This Row],[Exposed]]=1),MIN(IF(Summary!$B$3="",DATE(2030,12,31),Summary!$B$3-1),IF(AND(tblLines[[#This Row],[Settled]]<>"",tblLines[[#This Row],[Stale_prepay]]=0,(tblLines[[#This Row],[Receipt_credit]]>=tblLines[[#This Row],[sg_amount]]),tblLines[[#This Row],[Final_shortfall]]=0),tblLines[[#This Row],[Settled]],Summary!$B$2)),"") | AT4: =IF((tblLines[[#This Row],[Exposed]]=1),IF(tblLines[[#This Row],[Past_horizon]]=1,"",MAX(tblLines[[#This Row],[Outstanding_to]]-tblLines[[#This Row],[Final_due]],0)),"") | AU4: =IF((tblLines[[#This Row],[Exposed]]=1),IF(tblLines[[#This Row],[NEC_end]]>tblLines[[#This Row],[Final_due]],tblLines[[#This Row],[Base_shortfall]]*(EXP(SUMPRODUCT((((((tblLines[[#This Row],[NEC_end]]+tblGic[to]-ABS(tblLines[[#This Row],[NEC_end]]-tblGic[to]))/2)-(((tblLines[[#This Row],[Final_due]]+1)+tblGic[from]+ABS((tblLines[[#This Row],[Final_due]]+1)-tblGic[from]))/2)+1)>0)*(((tblLines[[#This Row],[NEC_end]]+tblGic[to]-ABS(tblLines[[#This Row],[NEC_end]]-tblGic[to]))/2)-(((tblLines[[#This Row],[Final_due]]+1)+tblGic[from]+ABS((tblLines[[#This Row],[Final_due]]+1)-tblGic[from]))/2)+1))*LN(1+tblGic[annual_pct]/100/tblGic[divisor])))-1),0),"") | AV4: =IF((tblLines[[#This Row],[Exposed]]=1),IF(tblLines[[#This Row],[NEC_end]]>Summary!$B$7,1,0),"") | AW4: =IF((tblLines[[#This Row],[Exposed]]=1),ROUND(tblLines[[#This Row],[Final_shortfall]],2),"") | AX4: =IF((tblLines[[#This Row],[Exposed]]=1),ROUND(tblLines[[#This Row],[NEC]],2),"") | AY4: =IF((tblLines[[#This Row],[Exposed]]=1),0,"") | AZ4: =IF((tblLines[[#This Row],[Exposed]]=1),ROUND(0.6*(tblLines[[#This Row],[Final_shortfall]]+tblLines[[#This Row],[NEC]]),2),"") | BA4: =IF((tblLines[[#This Row],[Exposed]]=1),tblLines[[#This Row],[Shortfall_r]]+tblLines[[#This Row],[NEC_r]]+tblLines[[#This Row],[Uplift_best]],"") | BB4: =IF((tblLines[[#This Row],[Exposed]]=1),tblLines[[#This Row],[Shortfall_r]]+tblLines[[#This Row],[NEC_r]]+tblLines[[#This Row],[Uplift_worst]],"") | BC4: =IF(AND(tblLines[[#This Row],[Flag_db]]<>1,ISNUMBER(tblLines[[#This Row],[sg_amount]]),tblLines[[#This Row],[sg_amount]]>0,tblLines[[#This Row],[Cap]]>0,OR(ISNUMBER(tblLines[[#This Row],[fund_received_date]]),ISNUMBER(tblLines[[#This Row],[remitted_date]])),IF(ISNUMBER(tblLines[[#This Row],[fund_received_date]]),tblLines[[#This Row],[fund_received_date]],tblLines[[#This Row],[remitted_date]])<=DATE(2026,7,28)),1,0) -> 1 | BD4: =IF(tblLines[[#This Row],[Settled]]<>"",1,0) -> 0 | BE4: =IF(AND(tblLines[[#This Row],[Verdict]]<>"",tblLines[[#This Row],[Verdict]]<>"SKIPPED",ISNUMBER(tblLines[[#This Row],[sg_amount]]),tblLines[[#This Row],[sg_amount]]>0),1,0) -> 1 | BF4: =IF(COUNTIFS(tblLines[employee_id],tblLines[[#This Row],[employee_id]],tblLines[payment_date],tblLines[[#This Row],[payment_date]],tblLines[sg_amount],tblLines[[#This Row],[sg_amount]],tblLines[remitted_date],tblLines[[#This Row],[remitted_date]]&"",tblLines[fund_received_date],tblLines[[#This Row],[fund_received_date]]&"")>1,1,0) -> 0
A5: EMP004 | B5: 46212 | C5: 780 | H5: no | I5: no | K5: no | L5: =IF(OR(LOWER(TRIM(tblLines[[#This Row],[defined_benefit]]&""))={"1","t","true","y","yes"}),1,IF(OR(LOWER(TRIM(tblLines[[#This Row],[defined_benefit]]&""))={"","0","f","false","n","no"}),0,"")) -> 0 | M5: =IF(OR(LOWER(TRIM(tblLines[[#This Row],[out_of_cycle]]&""))={"1","t","true","y","yes"}),1,IF(OR(LOWER(TRIM(tblLines[[#This Row],[out_of_cycle]]&""))={"","0","f","false","n","no"}),0,"")) -> 0 | N5: =IF(OR(LOWER(TRIM(tblLines[[#This Row],[first_contribution_to_fund]]&""))={"1","t","true","y","yes"}),1,IF(OR(LOWER(TRIM(tblLines[[#This Row],[first_contribution_to_fund]]&""))={"","0","f","false","n","no"}),0,"")) -> 0 | O5: =TRIM(IF(OR(AND(tblLines[[#This Row],[payment_date]]<>"",NOT(ISNUMBER(tblLines[[#This Row],[payment_date]]))),AND(tblLines[[#This Row],[remitted_date]]<>"",NOT(ISNUMBER(tblLines[[#This Row],[remitted_date]]))),AND(tblLines[[#This Row],[fund_received_date]]<>"",NOT(ISNUMBER(tblLines[[#This Row],[fund_received_date]]))),AND(tblLines[[#This Row],[next_standard_payday]]<>"",NOT(ISNUMBER(tblLines[[#This Row],[next_standard_payday]])))),"date ","")&IF(NOT(ISNUMBER(tblLines[[#This Row],[payment_date]])),"payment_date ","")&IF(AND(ISNUMBER(tblLines[[#This Row],[payment_date]]),tblLines[[#This Row],[payment_date]]<DATE(2026,7,1)),"pre-1-Jul-2026 ","")&IF(OR(AND(tblLines[[#This Row],[sg_amount]]<>"",OR(NOT(ISNUMBER(tblLines[[#This Row],[sg_amount]])),tblLines[[#This Row],[sg_amount]]<0)),AND(tblLines[[#This Row],[remitted_amount]]<>"",OR(NOT(ISNUMBER(tblLines[[#This Row],[remitted_amount]])),tblLines[[#This Row],[remitted_amount]]<0)),AND(tblLines[[#This Row],[matched_amount]]<>"",OR(NOT(ISNUMBER(tblLines[[#This Row],[matched_amount]])),tblLines[[#This Row],[matched_amount]]<0))),"amount ","")&IF(NOT(ISNUMBER(tblLines[[#This Row],[sg_amount]])),"sg_amount ","")&IF(OR(tblLines[[#This Row],[Flag_ftf]]="",tblLines[[#This Row],[Flag_ooc]]="",tblLines[[#This Row],[Flag_db]]=""),"yes/no ","")&IF(AND(ISNUMBER(tblLines[[#This Row],[remitted_amount]]),ISNUMBER(tblLines[[#This Row],[sg_amount]]),tblLines[[#This Row],[remitted_amount]]>tblLines[[#This Row],[sg_amount]]),"remitted_amount>sg ","")&IF(AND(ISNUMBER(tblLines[[#This Row],[remitted_amount]]),NOT(ISNUMBER(tblLines[[#This Row],[remitted_date]]))),"remitted_amount-needs-date ","")&IF(AND(ISNUMBER(tblLines[[#This Row],[matched_amount]]),ISNUMBER(tblLines[[#This Row],[sg_amount]]),tblLines[[#This Row],[matched_amount]]>tblLines[[#This Row],[sg_amount]]),"matched_amount>sg ","")&IF(AND(ISNUMBER(tblLines[[#This Row],[matched_amount]]),ISNUMBER(tblLines[[#This Row],[remitted_amount]]),tblLines[[#This Row],[remitted_amount]]>tblLines[[#This Row],[matched_amount]]),"remitted_amount>matched ","")&IF(AND(ISNUMBER(tblLines[[#This Row],[matched_amount]]),ISNUMBER(tblLines[[#This Row],[sg_amount]]),tblLines[[#This Row],[matched_amount]]<tblLines[[#This Row],[sg_amount]],ISNUMBER(tblLines[[#This Row],[remitted_date]]),NOT(ISNUMBER(tblLines[[#This Row],[remitted_amount]]))),"partial-match-needs-remitted_amount ","")&IF(AND(ISNUMBER(tblLines[[#This Row],[fund_received_date]]),ISNUMBER(tblLines[[#This Row],[remitted_date]]),tblLines[[#This Row],[fund_received_date]]<tblLines[[#This Row],[remitted_date]]),"receipt-before-remittance ","")&IF(AND(tblLines[[#This Row],[Flag_ooc]]=1,NOT(ISNUMBER(tblLines[[#This Row],[next_standard_payday]]))),"out_of_cycle-needs-next_standard_payday ","")&IF(AND(tblLines[[#This Row],[Flag_ooc]]=1,ISNUMBER(tblLines[[#This Row],[next_standard_payday]]),ISNUMBER(tblLines[[#This Row],[payment_date]]),tblLines[[#This Row],[next_standard_payday]]<=tblLines[[#This Row],[payment_date]]),"next_standard_payday-not-after-payday ","")) | P5: =IF(OR(_xlfn.ISFORMULA(tblLines[[#This Row],[employee_id]]),_xlfn.ISFORMULA(tblLines[[#This Row],[payment_date]]),_xlfn.ISFORMULA(tblLines[[#This Row],[sg_amount]]),_xlfn.ISFORMULA(tblLines[[#This Row],[remitted_date]]),_xlfn.ISFORMULA(tblLines[[#This Row],[remitted_amount]]),_xlfn.ISFORMULA(tblLines[[#This Row],[matched_amount]]),_xlfn.ISFORMULA(tblLines[[#This Row],[fund_received_date]]),_xlfn.ISFORMULA(tblLines[[#This Row],[first_contribution_to_fund]]),_xlfn.ISFORMULA(tblLines[[#This Row],[out_of_cycle]]),_xlfn.ISFORMULA(tblLines[[#This Row],[next_standard_payday]]),_xlfn.ISFORMULA(tblLines[[#This Row],[defined_benefit]])),1,0) -> 0 | Q5: =IF(ISNUMBER(tblLines[[#This Row],[matched_amount]]),tblLines[[#This Row],[matched_amount]],IF(ISNUMBER(tblLines[[#This Row],[remitted_amount]]),tblLines[[#This Row],[remitted_amount]],tblLines[[#This Row],[sg_amount]])) -> 780 | R5: =IF(AND(tblLines[[#This Row],[Flag_ooc]]=1,ISNUMBER(tblLines[[#This Row],[next_standard_payday]])),WORKDAY.INTL(tblLines[[#This Row],[next_standard_payday]],7,1,tblHolidays[date]),"") | S5: =IF(tblLines[[#This Row],[Flag_ftf]]=1,WORKDAY.INTL(tblLines[[#This Row],[payment_date]],20,1,tblHolidays[date]),"") | T5: =IF(OR(tblLines[[#This Row],[Flag_db]]=1,NOT(ISNUMBER(tblLines[[#This Row],[payment_date]]))),"",IF(OR(tblLines[[#This Row],[Flag_ooc]]=1,tblLines[[#This Row],[Flag_ftf]]=1),MAX(tblLines[[#This Row],[Due_ooc]],tblLines[[#This Row],[Due_ftf]]),WORKDAY.INTL(tblLines[[#This Row],[payment_date]],7,1,tblHolidays[date]))) -> 46223 | U5: =IF(tblLines[[#This Row],[Flag_db]]=1,"SKIP_DB",IF(tblLines[[#This Row],[Flag_ooc]]=1,IF(AND(tblLines[[#This Row],[Flag_ftf]]=1,tblLines[[#This Row],[Due_ftf]]>tblLines[[#This Row],[Due_ooc]]),"EXTENDED_20BD","OUT_OF_CYCLE"),IF(tblLines[[#This Row],[Flag_ftf]]=1,"EXTENDED_20BD","USUAL_7BD"))) -> USUAL_7BD | V5: =IF(ISNUMBER(tblLines[[#This Row],[payment_date]]),EDATE(tblLines[[#This Row],[payment_date]]-1,-12)+1,"") -> 45847 | W5: =IF(AND(ISNUMBER(tblLines[[#This Row],[fund_received_date]]),tblLines[[#This Row],[fund_received_date]]<=Summary!$B$2),tblLines[[#This Row],[fund_received_date]],"") | X5: =IF(AND(ISNUMBER(tblLines[[#This Row],[remitted_date]]),tblLines[[#This Row],[remitted_date]]<=Summary!$B$2),tblLines[[#This Row],[remitted_date]],"") | Y5: =IF(tblLines[[#This Row],[Settled]]<>"",MIN(ROUND(tblLines[[#This Row],[Cap]],2),ROUND(tblLines[[#This Row],[sg_amount]],2)),0) -> 0 | Z5: =IF(ISNUMBER(tblLines[[#This Row],[remitted_amount]]),IF(tblLines[[#This Row],[Remit]]<>"",MIN(ROUND(tblLines[[#This Row],[remitted_amount]],2),ROUND(tblLines[[#This Row],[sg_amount]],2)),0),IF(tblLines[[#This Row],[Remit]]<>"",ROUND(tblLines[[#This Row],[sg_amount]],2),0)) -> 0 | AA5: =IF(OR(tblLines[[#This Row],[Own_due]]="",tblLines[[#This Row],[sg_amount]]<=0,tblLines[[#This Row],[Flag_db]]=1,tblLines[[#This Row],[Cap]]<=0),"impossible",IF(ISNUMBER(tblLines[[#This Row],[fund_received_date]]),IF(tblLines[[#This Row],[fund_received_date]]<tblLines[[#This Row],[Earliest_prepay]],"impossible",IF(tblLines[[#This Row],[fund_received_date]]<=Summary!$B$2,IF(OR(tblLines[[#This Row],[fund_received_date]]<tblLines[[#This Row],[payment_date]],tblLines[[#This Row],[fund_received_date]]<=tblLines[[#This Row],[Own_due]]),"confirmed",IF(tblLines[[#This Row],[fund_received_date]]>tblLines[[#This Row],[Own_due]],"impossible","possible")),IF(tblLines[[#This Row],[fund_received_date]]<=tblLines[[#This Row],[Own_due]],"possible","impossible"))),IF(AND(ISNUMBER(tblLines[[#This Row],[remitted_date]]),tblLines[[#This Row],[remitted_date]]>tblLines[[#This Row],[Own_due]]),"impossible","possible"))) -> possible | AB5: =IF(OR(tblLines[[#This Row],[Flag_db]]=1,tblLines[[#This Row],[Own_due]]=""),"",_xlfn.MAXIFS(tblLines[Own_due],tblLines[employee_id],tblLines[[#This Row],[employee_id]],tblLines[payment_date],"<"&tblLines[[#This Row],[payment_date]],tblLines[Evidence_own],"confirmed")) -> 0 | AC5: =IF(OR(tblLines[[#This Row],[Flag_db]]=1,tblLines[[#This Row],[Own_due]]=""),"",_xlfn.MAXIFS(tblLines[Own_due],tblLines[employee_id],tblLines[[#This Row],[employee_id]],tblLines[payment_date],"<"&tblLines[[#This Row],[payment_date]],tblLines[Evidence_own],"<>impossible")) -> 0 | AD5: =IF(tblLines[[#This Row],[Own_due]]="","",IF(AND(ISNUMBER(tblLines[[#This Row],[Confirmed_latest]]),tblLines[[#This Row],[Confirmed_latest]]>tblLines[[#This Row],[Own_due]]),tblLines[[#This Row],[Confirmed_latest]],tblLines[[#This Row],[Own_due]])) -> 46223 | AE5: =IF(tblLines[[#This Row],[Own_due]]="",tblLines[[#This Row],[Own_pathway]],IF(AND(ISNUMBER(tblLines[[#This Row],[Confirmed_latest]]),tblLines[[#This Row],[Confirmed_latest]]>tblLines[[#This Row],[Own_due]]),"ITEM4_ALIGNED",tblLines[[#This Row],[Own_pathway]])) -> USUAL_7BD | AF5: =IF(tblLines[[#This Row],[Final_due]]="","",IF(AND(ISNUMBER(tblLines[[#This Row],[Possible_latest]]),tblLines[[#This Row],[Possible_latest]]>tblLines[[#This Row],[Final_due]]),tblLines[[#This Row],[Possible_latest]],"")) | AG5: =IF(tblLines[[#This Row],[Final_due]]="","",IF((tblLines[[#This Row],[Final_due]]>Summary!$B$6),1,0)) -> 0 | AH5: =IF(tblLines[[#This Row],[Flag_db]]=1,"DB",IF(tblLines[[#This Row],[Final_due]]="","",IF(tblLines[[#This Row],[sg_amount]]<=0,"NIL",IF(tblLines[[#This Row],[Settled]]<>"",IF(tblLines[[#This Row],[Settled]]<tblLines[[#This Row],[payment_date]],IF(tblLines[[#This Row],[Settled]]>=tblLines[[#This Row],[Earliest_prepay]],IF((tblLines[[#This Row],[Receipt_credit]]>=tblLines[[#This Row],[sg_amount]]),"A1",IF(tblLines[[#This Row],[Final_due]]>=Summary!$B$2,"A2",IF(OR((tblLines[[#This Row],[Final_due]]>Summary!$B$6),AND((tblLines[[#This Row],[Possible_item4]]<>""),Summary!$B$2<=tblLines[[#This Row],[Possible_item4]])),"A3","A4"))),IF(tblLines[[#This Row],[Final_due]]>=Summary!$B$2,"S1",IF(OR((tblLines[[#This Row],[Final_due]]>Summary!$B$6),AND((tblLines[[#This Row],[Possible_item4]]<>""),Summary!$B$2<=tblLines[[#This Row],[Possible_item4]])),"S2","S3"))),IF(AND((tblLines[[#This Row],[Possible_item4]]<>""),tblLines[[#This Row],[Final_due]]<tblLines[[#This Row],[Settled]],tblLines[[#This Row],[Settled]]<=tblLines[[#This Row],[Possible_item4]]),IF((tblLines[[#This Row],[Receipt_credit]]>=tblLines[[#This Row],[sg_amount]]),"B1",IF(Summary!$B$2<=tblLines[[#This Row],[Possible_item4]],"B2","B3")),IF(AND((tblLines[[#This Row],[Final_due]]>Summary!$B$6),tblLines[[#This Row],[Settled]]>tblLines[[#This Row],[Final_due]]),IF((tblLines[[#This Row],[Receipt_credit]]>=tblLines[[#This Row],[sg_amount]]),"C1","C2"),IF(tblLines[[#This Row],[Settled]]<=tblLines[[#This Row],[Final_due]],IF((tblLines[[#This Row],[Receipt_credit]]>=tblLines[[#This Row],[sg_amount]]),"D1",IF(OR((tblLines[[#This Row],[Final_due]]>Summary!$B$6),AND((tblLines[[#This Row],[Possible_item4]]<>""),Summary!$B$2<=tblLines[[#This Row],[Possible_item4]])),"D2",IF(tblLines[[#This Row],[Final_due]]<Summary!$B$2,"D3","D4"))),"E")))),IF(AND(tblLines[[#This Row],[Remit]]<>"",tblLines[[#This Row],[sg_amount]]-tblLines[[#This Row],[Credit]]<=0),IF(AND((tblLines[[#This Row],[Possible_item4]]<>""),tblLines[[#This Row],[Final_due]]<tblLines[[#This Row],[Remit]],tblLines[[#This Row],[Remit]]<=tblLines[[#This Row],[Possible_item4]]),"R1",IF(AND((tblLines[[#This Row],[Final_due]]>Summary!$B$6),tblLines[[#This Row],[Remit]]>tblLines[[#This Row],[Final_due]]),"R2",IF(tblLines[[#This Row],[Remit]]<=tblLines[[#This Row],[Final_due]],"R3","R4"))),IF(tblLines[[#This Row],[Final_due]]<Summary!$B$2,IF(OR((tblLines[[#This Row],[Final_due]]>Summary!$B$6),AND((tblLines[[#This Row],[Possible_item4]]<>""),Summary!$B$2<=tblLines[[#This Row],[Possible_item4]])),"N1","N2"),"N3")))))) -> N2 | AI5: =IF(tblLines[[#This Row],[Branch]]="","",INDEX(tblCodes[verdict],MATCH(tblLines[[#This Row],[Branch]],tblCodes[code],0))) -> UNPAID | AJ5: =IF(tblLines[[#This Row],[Branch]]="","",T(INDEX(tblCodes[unassessable],MATCH(tblLines[[#This Row],[Branch]],tblCodes[code],0)))) | AK5: =IF(tblLines[[#This Row],[Branch]]="",0,INDEX(tblCodes[exposed],MATCH(tblLines[[#This Row],[Branch]],tblCodes[code],0))) -> 1 | AL5: =IF(tblLines[[#This Row],[Branch]]="",0,INDEX(tblCodes[stale],MATCH(tblLines[[#This Row],[Branch]],tblCodes[code],0))) -> 0 | AM5: =IF(tblLines[[#This Row],[Branch]]="",0,INDEX(tblCodes[otrc],MATCH(tblLines[[#This Row],[Branch]],tblCodes[code],0))*tblLines[[#This Row],[Receipt_credit]]) -> 0 | AN5: =IF((tblLines[[#This Row],[Exposed]]=1),MAX(ROUND(tblLines[[#This Row],[sg_amount]],2)-tblLines[[#This Row],[OTRC]],0),"") -> 780 | AO5: =IF((tblLines[[#This Row],[Exposed]]=1),IF(AND(tblLines[[#This Row],[Settled]]<>"",tblLines[[#This Row],[Stale_prepay]]=0,tblLines[[#This Row],[Settled]]>tblLines[[#This Row],[Final_due]],OR(Summary!$B$3="",tblLines[[#This Row],[Settled]]<Summary!$B$3)),MIN(tblLines[[#This Row],[Receipt_credit]],tblLines[[#This Row],[Base_shortfall]]),0),"") -> 0 | AP5: =IF((tblLines[[#This Row],[Exposed]]=1),MAX(tblLines[[#This Row],[Base_shortfall]]-tblLines[[#This Row],[Offset_s18D]],0),"") -> 780 | AQ5: =IF((tblLines[[#This Row],[Exposed]]=1),IF(AND(tblLines[[#This Row],[Settled]]<>"",tblLines[[#This Row],[Stale_prepay]]=0,(tblLines[[#This Row],[Receipt_credit]]>=tblLines[[#This Row],[sg_amount]])),"fund receipt",IF(AND(tblLines[[#This Row],[Settled]]<>"",tblLines[[#This Row],[Stale_prepay]]=0),"as-at date (shortfall remains after part receipt)",IF(AND(OR(tblLines[[#This Row],[Settled]]<>"",tblLines[[#This Row],[Remit]]<>""),tblLines[[#This Row],[Stale_prepay]]=0),"as-at date (no fund receipt recorded)","as-at date (nothing applied to this payday)"))),"") -> as-at date (nothing applied to this payday) | AR5: =IF((tblLines[[#This Row],[Exposed]]=1),IF(AND(tblLines[[#This Row],[Settled]]<>"",tblLines[[#This Row],[Stale_prepay]]=0,(tblLines[[#This Row],[Receipt_credit]]>=tblLines[[#This Row],[sg_amount]])),tblLines[[#This Row],[Settled]],Summary!$B$2),"") -> 46244 | AS5: =IF((tblLines[[#This Row],[Exposed]]=1),MIN(IF(Summary!$B$3="",DATE(2030,12,31),Summary!$B$3-1),IF(AND(tblLines[[#This Row],[Settled]]<>"",tblLines[[#This Row],[Stale_prepay]]=0,(tblLines[[#This Row],[Receipt_credit]]>=tblLines[[#This Row],[sg_amount]]),tblLines[[#This Row],[Final_shortfall]]=0),tblLines[[#This Row],[Settled]],Summary!$B$2)),"") -> 46244 | AT5: =IF((tblLines[[#This Row],[Exposed]]=1),IF(tblLines[[#This Row],[Past_horizon]]=1,"",MAX(tblLines[[#This Row],[Outstanding_to]]-tblLines[[#This Row],[Final_due]],0)),"") -> 21 | AU5: =IF((tblLines[[#This Row],[Exposed]]=1),IF(tblLines[[#This Row],[NEC_end]]>tblLines[[#This Row],[Final_due]],tblLines[[#This Row],[Base_shortfall]]*(EXP(SUMPRODUCT((((((tblLines[[#This Row],[NEC_end]]+tblGic[to]-ABS(tblLines[[#This Row],[NEC_end]]-tblGic[to]))/2)-(((tblLines[[#This Row],[Final_due]]+1)+tblGic[from]+ABS((tblLines[[#This Row],[Final_due]]+1)-tblGic[from]))/2)+1)>0)*(((tblLines[[#This Row],[NEC_end]]+tblGic[to]-ABS(tblLines[[#This Row],[NEC_end]]-tblGic[to]))/2)-(((tblLines[[#This Row],[Final_due]]+1)+tblGic[from]+ABS((tblLines[[#This Row],[Final_due]]+1)-tblGic[from]))/2)+1))*LN(1+tblGic[annual_pct]/100/tblGic[divisor])))-1),0),"") -> 5.1455029 | AV5: =IF((tblLines[[#This Row],[Exposed]]=1),IF(tblLines[[#This Row],[NEC_end]]>Summary!$B$7,1,0),"") -> 0 | AW5: =IF((tblLines[[#This Row],[Exposed]]=1),ROUND(tblLines[[#This Row],[Final_shortfall]],2),"") -> 780 | AX5: =IF((tblLines[[#This Row],[Exposed]]=1),ROUND(tblLines[[#This Row],[NEC]],2),"") -> 5.15 | AY5: =IF((tblLines[[#This Row],[Exposed]]=1),0,"") -> 0 | AZ5: =IF((tblLines[[#This Row],[Exposed]]=1),ROUND(0.6*(tblLines[[#This Row],[Final_shortfall]]+tblLines[[#This Row],[NEC]]),2),"") -> 471.09 | BA5: =IF((tblLines[[#This Row],[Exposed]]=1),tblLines[[#This Row],[Shortfall_r]]+tblLines[[#This Row],[NEC_r]]+tblLines[[#This Row],[Uplift_best]],"") -> 785.15 | BB5: =IF((tblLines[[#This Row],[Exposed]]=1),tblLines[[#This Row],[Shortfall_r]]+tblLines[[#This Row],[NEC_r]]+tblLines[[#This Row],[Uplift_worst]],"") -> 1256.24 | BC5: =IF(AND(tblLines[[#This Row],[Flag_db]]<>1,ISNUMBER(tblLines[[#This Row],[sg_amount]]),tblLines[[#This Row],[sg_amount]]>0,tblLines[[#This Row],[Cap]]>0,OR(ISNUMBER(tblLines[[#This Row],[fund_received_date]]),ISNUMBER(tblLines[[#This Row],[remitted_date]])),IF(ISNUMBER(tblLines[[#This Row],[fund_received_date]]),tblLines[[#This Row],[fund_received_date]],tblLines[[#This Row],[remitted_date]])<=DATE(2026,7,28)),1,0) -> 0 | BD5: =IF(tblLines[[#This Row],[Settled]]<>"",1,0) -> 0 | BE5: =IF(AND(tblLines[[#This Row],[Verdict]]<>"",tblLines[[#This Row],[Verdict]]<>"SKIPPED",ISNUMBER(tblLines[[#This Row],[sg_amount]]),tblLines[[#This Row],[sg_amount]]>0),1,0) -> 1 | BF5: =IF(COUNTIFS(tblLines[employee_id],tblLines[[#This Row],[employee_id]],tblLines[payment_date],tblLines[[#This Row],[payment_date]],tblLines[sg_amount],tblLines[[#This Row],[sg_amount]],tblLines[remitted_date],tblLines[[#This Row],[remitted_date]]&"",tblLines[fund_received_date],tblLines[[#This Row],[fund_received_date]]&"")>1,1,0) -> 0
A6: EMP005 | B6: 46212 | C6: 450 | D6: 46237 | G6: 46239 | H6: yes | I6: no | K6: no | L6: =IF(OR(LOWER(TRIM(tblLines[[#This Row],[defined_benefit]]&""))={"1","t","true","y","yes"}),1,IF(OR(LOWER(TRIM(tblLines[[#This Row],[defined_benefit]]&""))={"","0","f","false","n","no"}),0,"")) -> 0 | M6: =IF(OR(LOWER(TRIM(tblLines[[#This Row],[out_of_cycle]]&""))={"1","t","true","y","yes"}),1,IF(OR(LOWER(TRIM(tblLines[[#This Row],[out_of_cycle]]&""))={"","0","f","false","n","no"}),0,"")) -> 0 | N6: =IF(OR(LOWER(TRIM(tblLines[[#This Row],[first_contribution_to_fund]]&""))={"1","t","true","y","yes"}),1,IF(OR(LOWER(TRIM(tblLines[[#This Row],[first_contribution_to_fund]]&""))={"","0","f","false","n","no"}),0,"")) -> 1 | O6: =TRIM(IF(OR(AND(tblLines[[#This Row],[payment_date]]<>"",NOT(ISNUMBER(tblLines[[#This Row],[payment_date]]))),AND(tblLines[[#This Row],[remitted_date]]<>"",NOT(ISNUMBER(tblLines[[#This Row],[remitted_date]]))),AND(tblLines[[#This Row],[fund_received_date]]<>"",NOT(ISNUMBER(tblLines[[#This Row],[fund_received_date]]))),AND(tblLines[[#This Row],[next_standard_payday]]<>"",NOT(ISNUMBER(tblLines[[#This Row],[next_standard_payday]])))),"date ","")&IF(NOT(ISNUMBER(tblLines[[#This Row],[payment_date]])),"payment_date ","")&IF(AND(ISNUMBER(tblLines[[#This Row],[payment_date]]),tblLines[[#This Row],[payment_date]]<DATE(2026,7,1)),"pre-1-Jul-2026 ","")&IF(OR(AND(tblLines[[#This Row],[sg_amount]]<>"",OR(NOT(ISNUMBER(tblLines[[#This Row],[sg_amount]])),tblLines[[#This Row],[sg_amount]]<0)),AND(tblLines[[#This Row],[remitted_amount]]<>"",OR(NOT(ISNUMBER(tblLines[[#This Row],[remitted_amount]])),tblLines[[#This Row],[remitted_amount]]<0)),AND(tblLines[[#This Row],[matched_amount]]<>"",OR(NOT(ISNUMBER(tblLines[[#This Row],[matched_amount]])),tblLines[[#This Row],[matched_amount]]<0))),"amount ","")&IF(NOT(ISNUMBER(tblLines[[#This Row],[sg_amount]])),"sg_amount ","")&IF(OR(tblLines[[#This Row],[Flag_ftf]]="",tblLines[[#This Row],[Flag_ooc]]="",tblLines[[#This Row],[Flag_db]]=""),"yes/no ","")&IF(AND(ISNUMBER(tblLines[[#This Row],[remitted_amount]]),ISNUMBER(tblLines[[#This Row],[sg_amount]]),tblLines[[#This Row],[remitted_amount]]>tblLines[[#This Row],[sg_amount]]),"remitted_amount>sg ","")&IF(AND(ISNUMBER(tblLines[[#This Row],[remitted_amount]]),NOT(ISNUMBER(tblLines[[#This Row],[remitted_date]]))),"remitted_amount-needs-date ","")&IF(AND(ISNUMBER(tblLines[[#This Row],[matched_amount]]),ISNUMBER(tblLines[[#This Row],[sg_amount]]),tblLines[[#This Row],[matched_amount]]>tblLines[[#This Row],[sg_amount]]),"matched_amount>sg ","")&IF(AND(ISNUMBER(tblLines[[#This Row],[matched_amount]]),ISNUMBER(tblLines[[#This Row],[remitted_amount]]),tblLines[[#This Row],[remitted_amount]]>tblLines[[#This Row],[matched_amount]]),"remitted_amount>matched ","")&IF(AND(ISNUMBER(tblLines[[#This Row],[matched_amount]]),ISNUMBER(tblLines[[#This Row],[sg_amount]]),tblLines[[#This Row],[matched_amount]]<tblLines[[#This Row],[sg_amount]],ISNUMBER(tblLines[[#This Row],[remitted_date]]),NOT(ISNUMBER(tblLines[[#This Row],[remitted_amount]]))),"partial-match-needs-remitted_amount ","")&IF(AND(ISNUMBER(tblLines[[#This Row],[fund_received_date]]),ISNUMBER(tblLines[[#This Row],[remitted_date]]),tblLines[[#This Row],[fund_received_date]]<tblLines[[#This Row],[remitted_date]]),"receipt-before-remittance ","")&IF(AND(tblLines[[#This Row],[Flag_ooc]]=1,NOT(ISNUMBER(tblLines[[#This Row],[next_standard_payday]]))),"out_of_cycle-needs-next_standard_payday ","")&IF(AND(tblLines[[#This Row],[Flag_ooc]]=1,ISNUMBER(tblLines[[#This Row],[next_standard_payday]]),ISNUMBER(tblLines[[#This Row],[payment_date]]),tblLines[[#This Row],[next_standard_payday]]<=tblLines[[#This Row],[payment_date]]),"next_standard_payday-not-after-payday ","")) | P6: =IF(OR(_xlfn.ISFORMULA(tblLines[[#This Row],[employee_id]]),_xlfn.ISFORMULA(tblLines[[#This Row],[payment_date]]),_xlfn.ISFORMULA(tblLines[[#This Row],[sg_amount]]),_xlfn.ISFORMULA(tblLines[[#This Row],[remitted_date]]),_xlfn.ISFORMULA(tblLines[[#This Row],[remitted_amount]]),_xlfn.ISFORMULA(tblLines[[#This Row],[matched_amount]]),_xlfn.ISFORMULA(tblLines[[#This Row],[fund_received_date]]),_xlfn.ISFORMULA(tblLines[[#This Row],[first_contribution_to_fund]]),_xlfn.ISFORMULA(tblLines[[#This Row],[out_of_cycle]]),_xlfn.ISFORMULA(tblLines[[#This Row],[next_standard_payday]]),_xlfn.ISFORMULA(tblLines[[#This Row],[defined_benefit]])),1,0) -> 0 | Q6: =IF(ISNUMBER(tblLines[[#This Row],[matched_amount]]),tblLines[[#This Row],[matched_amount]],IF(ISNUMBER(tblLines[[#This Row],[remitted_amount]]),tblLines[[#This Row],[remitted_amount]],tblLines[[#This Row],[sg_amount]])) -> 450 | R6: =IF(AND(tblLines[[#This Row],[Flag_ooc]]=1,ISNUMBER(tblLines[[#This Row],[next_standard_payday]])),WORKDAY.INTL(tblLines[[#This Row],[next_standard_payday]],7,1,tblHolidays[date]),"") | S6: =IF(tblLines[[#This Row],[Flag_ftf]]=1,WORKDAY.INTL(tblLines[[#This Row],[payment_date]],20,1,tblHolidays[date]),"") -> 46241 | T6: =IF(OR(tblLines[[#This Row],[Flag_db]]=1,NOT(ISNUMBER(tblLines[[#This Row],[payment_date]]))),"",IF(OR(tblLines[[#This Row],[Flag_ooc]]=1,tblLines[[#This Row],[Flag_ftf]]=1),MAX(tblLines[[#This Row],[Due_ooc]],tblLines[[#This Row],[Due_ftf]]),WORKDAY.INTL(tblLines[[#This Row],[payment_date]],7,1,tblHolidays[date]))) -> 46241 | U6: =IF(tblLines[[#This Row],[Flag_db]]=1,"SKIP_DB",IF(tblLines[[#This Row],[Flag_ooc]]=1,IF(AND(tblLines[[#This Row],[Flag_ftf]]=1,tblLines[[#This Row],[Due_ftf]]>tblLines[[#This Row],[Due_ooc]]),"EXTENDED_20BD","OUT_OF_CYCLE"),IF(tblLines[[#This Row],[Flag_ftf]]=1,"EXTENDED_20BD","USUAL_7BD"))) -> EXTENDED_20BD | V6: =IF(ISNUMBER(tblLines[[#This Row],[payment_date]]),EDATE(tblLines[[#This Row],[payment_date]]-1,-12)+1,"") -> 45847 | W6: =IF(AND(ISNUMBER(tblLines[[#This Row],[fund_received_date]]),tblLines[[#This Row],[fund_received_date]]<=Summary!$B$2),tblLines[[#This Row],[fund_received_date]],"") -> 46239 | X6: =IF(AND(ISNUMBER(tblLines[[#This Row],[remitted_date]]),tblLines[[#This Row],[remitted_date]]<=Summary!$B$2),tblLines[[#This Row],[remitted_date]],"") -> 46237 | Y6: =IF(tblLines[[#This Row],[Settled]]<>"",MIN(ROUND(tblLines[[#This Row],[Cap]],2),ROUND(tblLines[[#This Row],[sg_amount]],2)),0) -> 450 | Z6: =IF(ISNUMBER(tblLines[[#This Row],[remitted_amount]]),IF(tblLines[[#This Row],[Remit]]<>"",MIN(ROUND(tblLines[[#This Row],[remitted_amount]],2),ROUND(tblLines[[#This Row],[sg_amount]],2)),0),IF(tblLines[[#This Row],[Remit]]<>"",ROUND(tblLines[[#This Row],[sg_amount]],2),0)) -> 450 | AA6: =IF(OR(tblLines[[#This Row],[Own_due]]="",tblLines[[#This Row],[sg_amount]]<=0,tblLines[[#This Row],[Flag_db]]=1,tblLines[[#This Row],[Cap]]<=0),"impossible",IF(ISNUMBER(tblLines[[#This Row],[fund_received_date]]),IF(tblLines[[#This Row],[fund_received_date]]<tblLines[[#This Row],[Earliest_prepay]],"impossible",IF(tblLines[[#This Row],[fund_received_date]]<=Summary!$B$2,IF(OR(tblLines[[#This Row],[fund_received_date]]<tblLines[[#This Row],[payment_date]],tblLines[[#This Row],[fund_received_date]]<=tblLines[[#This Row],[Own_due]]),"confirmed",IF(tblLines[[#This Row],[fund_received_date]]>tblLines[[#This Row],[Own_due]],"impossible","possible")),IF(tblLines[[#This Row],[fund_received_date]]<=tblLines[[#This Row],[Own_due]],"possible","impossible"))),IF(AND(ISNUMBER(tblLines[[#This Row],[remitted_date]]),tblLines[[#This Row],[remitted_date]]>tblLines[[#This Row],[Own_due]]),"impossible","possible"))) -> confirmed | AB6: =IF(OR(tblLines[[#This Row],[Flag_db]]=1,tblLines[[#This Row],[Own_due]]=""),"",_xlfn.MAXIFS(tblLines[Own_due],tblLines[employee_id],tblLines[[#This Row],[employee_id]],tblLines[payment_date],"<"&tblLines[[#This Row],[payment_date]],tblLines[Evidence_own],"confirmed")) -> 0 | AC6: =IF(OR(tblLines[[#This Row],[Flag_db]]=1,tblLines[[#This Row],[Own_due]]=""),"",_xlfn.MAXIFS(tblLines[Own_due],tblLines[employee_id],tblLines[[#This Row],[employee_id]],tblLines[payment_date],"<"&tblLines[[#This Row],[payment_date]],tblLines[Evidence_own],"<>impossible")) -> 0 | AD6: =IF(tblLines[[#This Row],[Own_due]]="","",IF(AND(ISNUMBER(tblLines[[#This Row],[Confirmed_latest]]),tblLines[[#This Row],[Confirmed_latest]]>tblLines[[#This Row],[Own_due]]),tblLines[[#This Row],[Confirmed_latest]],tblLines[[#This Row],[Own_due]])) -> 46241 | AE6: =IF(tblLines[[#This Row],[Own_due]]="",tblLines[[#This Row],[Own_pathway]],IF(AND(ISNUMBER(tblLines[[#This Row],[Confirmed_latest]]),tblLines[[#This Row],[Confirmed_latest]]>tblLines[[#This Row],[Own_due]]),"ITEM4_ALIGNED",tblLines[[#This Row],[Own_pathway]])) -> EXTENDED_20BD | AF6: =IF(tblLines[[#This Row],[Final_due]]="","",IF(AND(ISNUMBER(tblLines[[#This Row],[Possible_latest]]),tblLines[[#This Row],[Possible_latest]]>tblLines[[#This Row],[Final_due]]),tblLines[[#This Row],[Possible_latest]],"")) | AG6: =IF(tblLines[[#This Row],[Final_due]]="","",IF((tblLines[[#This Row],[Final_due]]>Summary!$B$6),1,0)) -> 0 | AH6: =IF(tblLines[[#This Row],[Flag_db]]=1,"DB",IF(tblLines[[#This Row],[Final_due]]="","",IF(tblLines[[#This Row],[sg_amount]]<=0,"NIL",IF(tblLines[[#This Row],[Settled]]<>"",IF(tblLines[[#This Row],[Settled]]<tblLines[[#This Row],[payment_date]],IF(tblLines[[#This Row],[Settled]]>=tblLines[[#This Row],[Earliest_prepay]],IF((tblLines[[#This Row],[Receipt_credit]]>=tblLines[[#This Row],[sg_amount]]),"A1",IF(tblLines[[#This Row],[Final_due]]>=Summary!$B$2,"A2",IF(OR((tblLines[[#This Row],[Final_due]]>Summary!$B$6),AND((tblLines[[#This Row],[Possible_item4]]<>""),Summary!$B$2<=tblLines[[#This Row],[Possible_item4]])),"A3","A4"))),IF(tblLines[[#This Row],[Final_due]]>=Summary!$B$2,"S1",IF(OR((tblLines[[#This Row],[Final_due]]>Summary!$B$6),AND((tblLines[[#This Row],[Possible_item4]]<>""),Summary!$B$2<=tblLines[[#This Row],[Possible_item4]])),"S2","S3"))),IF(AND((tblLines[[#This Row],[Possible_item4]]<>""),tblLines[[#This Row],[Final_due]]<tblLines[[#This Row],[Settled]],tblLines[[#This Row],[Settled]]<=tblLines[[#This Row],[Possible_item4]]),IF((tblLines[[#This Row],[Receipt_credit]]>=tblLines[[#This Row],[sg_amount]]),"B1",IF(Summary!$B$2<=tblLines[[#This Row],[Possible_item4]],"B2","B3")),IF(AND((tblLines[[#This Row],[Final_due]]>Summary!$B$6),tblLines[[#This Row],[Settled]]>tblLines[[#This Row],[Final_due]]),IF((tblLines[[#This Row],[Receipt_credit]]>=tblLines[[#This Row],[sg_amount]]),"C1","C2"),IF(tblLines[[#This Row],[Settled]]<=tblLines[[#This Row],[Final_due]],IF((tblLines[[#This Row],[Receipt_credit]]>=tblLines[[#This Row],[sg_amount]]),"D1",IF(OR((tblLines[[#This Row],[Final_due]]>Summary!$B$6),AND((tblLines[[#This Row],[Possible_item4]]<>""),Summary!$B$2<=tblLines[[#This Row],[Possible_item4]])),"D2",IF(tblLines[[#This Row],[Final_due]]<Summary!$B$2,"D3","D4"))),"E")))),IF(AND(tblLines[[#This Row],[Remit]]<>"",tblLines[[#This Row],[sg_amount]]-tblLines[[#This Row],[Credit]]<=0),IF(AND((tblLines[[#This Row],[Possible_item4]]<>""),tblLines[[#This Row],[Final_due]]<tblLines[[#This Row],[Remit]],tblLines[[#This Row],[Remit]]<=tblLines[[#This Row],[Possible_item4]]),"R1",IF(AND((tblLines[[#This Row],[Final_due]]>Summary!$B$6),tblLines[[#This Row],[Remit]]>tblLines[[#This Row],[Final_due]]),"R2",IF(tblLines[[#This Row],[Remit]]<=tblLines[[#This Row],[Final_due]],"R3","R4"))),IF(tblLines[[#This Row],[Final_due]]<Summary!$B$2,IF(OR((tblLines[[#This Row],[Final_due]]>Summary!$B$6),AND((tblLines[[#This Row],[Possible_item4]]<>""),Summary!$B$2<=tblLines[[#This Row],[Possible_item4]])),"N1","N2"),"N3")))))) -> D1 | AI6: =IF(tblLines[[#This Row],[Branch]]="","",INDEX(tblCodes[verdict],MATCH(tblLines[[#This Row],[Branch]],tblCodes[code],0))) -> ON_TIME | AJ6: =IF(tblLines[[#This Row],[Branch]]="","",T(INDEX(tblCodes[unassessable],MATCH(tblLines[[#This Row],[Branch]],tblCodes[code],0)))) | AK6: =IF(tblLines[[#This Row],[Branch]]="",0,INDEX(tblCodes[exposed],MATCH(tblLines[[#This Row],[Branch]],tblCodes[code],0))) -> 0 | AL6: =IF(tblLines[[#This Row],[Branch]]="",0,INDEX(tblCodes[stale],MATCH(tblLines[[#This Row],[Branch]],tblCodes[code],0))) -> 0 | AM6: =IF(tblLines[[#This Row],[Branch]]="",0,INDEX(tblCodes[otrc],MATCH(tblLines[[#This Row],[Branch]],tblCodes[code],0))*tblLines[[#This Row],[Receipt_credit]]) -> 450 | AN6: =IF((tblLines[[#This Row],[Exposed]]=1),MAX(ROUND(tblLines[[#This Row],[sg_amount]],2)-tblLines[[#This Row],[OTRC]],0),"") | AO6: =IF((tblLines[[#This Row],[Exposed]]=1),IF(AND(tblLines[[#This Row],[Settled]]<>"",tblLines[[#This Row],[Stale_prepay]]=0,tblLines[[#This Row],[Settled]]>tblLines[[#This Row],[Final_due]],OR(Summary!$B$3="",tblLines[[#This Row],[Settled]]<Summary!$B$3)),MIN(tblLines[[#This Row],[Receipt_credit]],tblLines[[#This Row],[Base_shortfall]]),0),"") | AP6: =IF((tblLines[[#This Row],[Exposed]]=1),MAX(tblLines[[#This Row],[Base_shortfall]]-tblLines[[#This Row],[Offset_s18D]],0),"") | AQ6: =IF((tblLines[[#This Row],[Exposed]]=1),IF(AND(tblLines[[#This Row],[Settled]]<>"",tblLines[[#This Row],[Stale_prepay]]=0,(tblLines[[#This Row],[Receipt_credit]]>=tblLines[[#This Row],[sg_amount]])),"fund receipt",IF(AND(tblLines[[#This Row],[Settled]]<>"",tblLines[[#This Row],[Stale_prepay]]=0),"as-at date (shortfall remains after part receipt)",IF(AND(OR(tblLines[[#This Row],[Settled]]<>"",tblLines[[#This Row],[Remit]]<>""),tblLines[[#This Row],[Stale_prepay]]=0),"as-at date (no fund receipt recorded)","as-at date (nothing applied to this payday)"))),"") | AR6: =IF((tblLines[[#This Row],[Exposed]]=1),IF(AND(tblLines[[#This Row],[Settled]]<>"",tblLines[[#This Row],[Stale_prepay]]=0,(tblLines[[#This Row],[Receipt_credit]]>=tblLines[[#This Row],[sg_amount]])),tblLines[[#This Row],[Settled]],Summary!$B$2),"") | AS6: =IF((tblLines[[#This Row],[Exposed]]=1),MIN(IF(Summary!$B$3="",DATE(2030,12,31),Summary!$B$3-1),IF(AND(tblLines[[#This Row],[Settled]]<>"",tblLines[[#This Row],[Stale_prepay]]=0,(tblLines[[#This Row],[Receipt_credit]]>=tblLines[[#This Row],[sg_amount]]),tblLines[[#This Row],[Final_shortfall]]=0),tblLines[[#This Row],[Settled]],Summary!$B$2)),"") | AT6: =IF((tblLines[[#This Row],[Exposed]]=1),IF(tblLines[[#This Row],[Past_horizon]]=1,"",MAX(tblLines[[#This Row],[Outstanding_to]]-tblLines[[#This Row],[Final_due]],0)),"") | AU6: =IF((tblLines[[#This Row],[Exposed]]=1),IF(tblLines[[#This Row],[NEC_end]]>tblLines[[#This Row],[Final_due]],tblLines[[#This Row],[Base_shortfall]]*(EXP(SUMPRODUCT((((((tblLines[[#This Row],[NEC_end]]+tblGic[to]-ABS(tblLines[[#This Row],[NEC_end]]-tblGic[to]))/2)-(((tblLines[[#This Row],[Final_due]]+1)+tblGic[from]+ABS((tblLines[[#This Row],[Final_due]]+1)-tblGic[from]))/2)+1)>0)*(((tblLines[[#This Row],[NEC_end]]+tblGic[to]-ABS(tblLines[[#This Row],[NEC_end]]-tblGic[to]))/2)-(((tblLines[[#This Row],[Final_due]]+1)+tblGic[from]+ABS((tblLines[[#This Row],[Final_due]]+1)-tblGic[from]))/2)+1))*LN(1+tblGic[annual_pct]/100/tblGic[divisor])))-1),0),"") | AV6: =IF((tblLines[[#This Row],[Exposed]]=1),IF(tblLines[[#This Row],[NEC_end]]>Summary!$B$7,1,0),"") | AW6: =IF((tblLines[[#This Row],[Exposed]]=1),ROUND(tblLines[[#This Row],[Final_shortfall]],2),"") | AX6: =IF((tblLines[[#This Row],[Exposed]]=1),ROUND(tblLines[[#This Row],[NEC]],2),"") | AY6: =IF((tblLines[[#This Row],[Exposed]]=1),0,"") | AZ6: =IF((tblLines[[#This Row],[Exposed]]=1),ROUND(0.6*(tblLines[[#This Row],[Final_shortfall]]+tblLines[[#This Row],[NEC]]),2),"") | BA6: =IF((tblLines[[#This Row],[Exposed]]=1),tblLines[[#This Row],[Shortfall_r]]+tblLines[[#This Row],[NEC_r]]+tblLines[[#This Row],[Uplift_best]],"") | BB6: =IF((tblLines[[#This Row],[Exposed]]=1),tblLines[[#This Row],[Shortfall_r]]+tblLines[[#This Row],[NEC_r]]+tblLines[[#This Row],[Uplift_worst]],"") | BC6: =IF(AND(tblLines[[#This Row],[Flag_db]]<>1,ISNUMBER(tblLines[[#This Row],[sg_amount]]),tblLines[[#This Row],[sg_amount]]>0,tblLines[[#This Row],[Cap]]>0,OR(ISNUMBER(tblLines[[#This Row],[fund_received_date]]),ISNUMBER(tblLines[[#This Row],[remitted_date]])),IF(ISNUMBER(tblLines[[#This Row],[fund_received_date]]),tblLines[[#This Row],[fund_received_date]],tblLines[[#This Row],[remitted_date]])<=DATE(2026,7,28)),1,0) -> 0 | BD6: =IF(tblLines[[#This Row],[Settled]]<>"",1,0) -> 1 | BE6: =IF(AND(tblLines[[#This Row],[Verdict]]<>"",tblLines[[#This Row],[Verdict]]<>"SKIPPED",ISNUMBER(tblLines[[#This Row],[sg_amount]]),tblLines[[#This Row],[sg_amount]]>0),1,0) -> 1 | BF6: =IF(COUNTIFS(tblLines[employee_id],tblLines[[#This Row],[employee_id]],tblLines[payment_date],tblLines[[#This Row],[payment_date]],tblLines[sg_amount],tblLines[[#This Row],[sg_amount]],tblLines[remitted_date],tblLines[[#This Row],[remitted_date]]&"",tblLines[fund_received_date],tblLines[[#This Row],[fund_received_date]]&"")>1,1,0) -> 0
A7: EMP006 | B7: 46218 | C7: 120 | D7: 46233 | G7: 46234 | H7: no | I7: yes | J7: 46226 | K7: no | L7: =IF(OR(LOWER(TRIM(tblLines[[#This Row],[defined_benefit]]&""))={"1","t","true","y","yes"}),1,IF(OR(LOWER(TRIM(tblLines[[#This Row],[defined_benefit]]&""))={"","0","f","false","n","no"}),0,"")) -> 0 | M7: =IF(OR(LOWER(TRIM(tblLines[[#This Row],[out_of_cycle]]&""))={"1","t","true","y","yes"}),1,IF(OR(LOWER(TRIM(tblLines[[#This Row],[out_of_cycle]]&""))={"","0","f","false","n","no"}),0,"")) -> 1 | N7: =IF(OR(LOWER(TRIM(tblLines[[#This Row],[first_contribution_to_fund]]&""))={"1","t","true","y","yes"}),1,IF(OR(LOWER(TRIM(tblLines[[#This Row],[first_contribution_to_fund]]&""))={"","0","f","false","n","no"}),0,"")) -> 0 | O7: =TRIM(IF(OR(AND(tblLines[[#This Row],[payment_date]]<>"",NOT(ISNUMBER(tblLines[[#This Row],[payment_date]]))),AND(tblLines[[#This Row],[remitted_date]]<>"",NOT(ISNUMBER(tblLines[[#This Row],[remitted_date]]))),AND(tblLines[[#This Row],[fund_received_date]]<>"",NOT(ISNUMBER(tblLines[[#This Row],[fund_received_date]]))),AND(tblLines[[#This Row],[next_standard_payday]]<>"",NOT(ISNUMBER(tblLines[[#This Row],[next_standard_payday]])))),"date ","")&IF(NOT(ISNUMBER(tblLines[[#This Row],[payment_date]])),"payment_date ","")&IF(AND(ISNUMBER(tblLines[[#This Row],[payment_date]]),tblLines[[#This Row],[payment_date]]<DATE(2026,7,1)),"pre-1-Jul-2026 ","")&IF(OR(AND(tblLines[[#This Row],[sg_amount]]<>"",OR(NOT(ISNUMBER(tblLines[[#This Row],[sg_amount]])),tblLines[[#This Row],[sg_amount]]<0)),AND(tblLines[[#This Row],[remitted_amount]]<>"",OR(NOT(ISNUMBER(tblLines[[#This Row],[remitted_amount]])),tblLines[[#This Row],[remitted_amount]]<0)),AND(tblLines[[#This Row],[matched_amount]]<>"",OR(NOT(ISNUMBER(tblLines[[#This Row],[matched_amount]])),tblLines[[#This Row],[matched_amount]]<0))),"amount ","")&IF(NOT(ISNUMBER(tblLines[[#This Row],[sg_amount]])),"sg_amount ","")&IF(OR(tblLines[[#This Row],[Flag_ftf]]="",tblLines[[#This Row],[Flag_ooc]]="",tblLines[[#This Row],[Flag_db]]=""),"yes/no ","")&IF(AND(ISNUMBER(tblLines[[#This Row],[remitted_amount]]),ISNUMBER(tblLines[[#This Row],[sg_amount]]),tblLines[[#This Row],[remitted_amount]]>tblLines[[#This Row],[sg_amount]]),"remitted_amount>sg ","")&IF(AND(ISNUMBER(tblLines[[#This Row],[remitted_amount]]),NOT(ISNUMBER(tblLines[[#This Row],[remitted_date]]))),"remitted_amount-needs-date ","")&IF(AND(ISNUMBER(tblLines[[#This Row],[matched_amount]]),ISNUMBER(tblLines[[#This Row],[sg_amount]]),tblLines[[#This Row],[matched_amount]]>tblLines[[#This Row],[sg_amount]]),"matched_amount>sg ","")&IF(AND(ISNUMBER(tblLines[[#This Row],[matched_amount]]),ISNUMBER(tblLines[[#This Row],[remitted_amount]]),tblLines[[#This Row],[remitted_amount]]>tblLines[[#This Row],[matched_amount]]),"remitted_amount>matched ","")&IF(AND(ISNUMBER(tblLines[[#This Row],[matched_amount]]),ISNUMBER(tblLines[[#This Row],[sg_amount]]),tblLines[[#This Row],[matched_amount]]<tblLines[[#This Row],[sg_amount]],ISNUMBER(tblLines[[#This Row],[remitted_date]]),NOT(ISNUMBER(tblLines[[#This Row],[remitted_amount]]))),"partial-match-needs-remitted_amount ","")&IF(AND(ISNUMBER(tblLines[[#This Row],[fund_received_date]]),ISNUMBER(tblLines[[#This Row],[remitted_date]]),tblLines[[#This Row],[fund_received_date]]<tblLines[[#This Row],[remitted_date]]),"receipt-before-remittance ","")&IF(AND(tblLines[[#This Row],[Flag_ooc]]=1,NOT(ISNUMBER(tblLines[[#This Row],[next_standard_payday]]))),"out_of_cycle-needs-next_standard_payday ","")&IF(AND(tblLines[[#This Row],[Flag_ooc]]=1,ISNUMBER(tblLines[[#This Row],[next_standard_payday]]),ISNUMBER(tblLines[[#This Row],[payment_date]]),tblLines[[#This Row],[next_standard_payday]]<=tblLines[[#This Row],[payment_date]]),"next_standard_payday-not-after-payday ","")) | P7: =IF(OR(_xlfn.ISFORMULA(tblLines[[#This Row],[employee_id]]),_xlfn.ISFORMULA(tblLines[[#This Row],[payment_date]]),_xlfn.ISFORMULA(tblLines[[#This Row],[sg_amount]]),_xlfn.ISFORMULA(tblLines[[#This Row],[remitted_date]]),_xlfn.ISFORMULA(tblLines[[#This Row],[remitted_amount]]),_xlfn.ISFORMULA(tblLines[[#This Row],[matched_amount]]),_xlfn.ISFORMULA(tblLines[[#This Row],[fund_received_date]]),_xlfn.ISFORMULA(tblLines[[#This Row],[first_contribution_to_fund]]),_xlfn.ISFORMULA(tblLines[[#This Row],[out_of_cycle]]),_xlfn.ISFORMULA(tblLines[[#This Row],[next_standard_payday]]),_xlfn.ISFORMULA(tblLines[[#This Row],[defined_benefit]])),1,0) -> 0 | Q7: =IF(ISNUMBER(tblLines[[#This Row],[matched_amount]]),tblLines[[#This Row],[matched_amount]],IF(ISNUMBER(tblLines[[#This Row],[remitted_amount]]),tblLines[[#This Row],[remitted_amount]],tblLines[[#This Row],[sg_amount]])) -> 120 | R7: =IF(AND(tblLines[[#This Row],[Flag_ooc]]=1,ISNUMBER(tblLines[[#This Row],[next_standard_payday]])),WORKDAY.INTL(tblLines[[#This Row],[next_standard_payday]],7,1,tblHolidays[date]),"") -> 46238 | S7: =IF(tblLines[[#This Row],[Flag_ftf]]=1,WORKDAY.INTL(tblLines[[#This Row],[payment_date]],20,1,tblHolidays[date]),"") | T7: =IF(OR(tblLines[[#This Row],[Flag_db]]=1,NOT(ISNUMBER(tblLines[[#This Row],[payment_date]]))),"",IF(OR(tblLines[[#This Row],[Flag_ooc]]=1,tblLines[[#This Row],[Flag_ftf]]=1),MAX(tblLines[[#This Row],[Due_ooc]],tblLines[[#This Row],[Due_ftf]]),WORKDAY.INTL(tblLines[[#This Row],[payment_date]],7,1,tblHolidays[date]))) -> 46238 | U7: =IF(tblLines[[#This Row],[Flag_db]]=1,"SKIP_DB",IF(tblLines[[#This Row],[Flag_ooc]]=1,IF(AND(tblLines[[#This Row],[Flag_ftf]]=1,tblLines[[#This Row],[Due_ftf]]>tblLines[[#This Row],[Due_ooc]]),"EXTENDED_20BD","OUT_OF_CYCLE"),IF(tblLines[[#This Row],[Flag_ftf]]=1,"EXTENDED_20BD","USUAL_7BD"))) -> OUT_OF_CYCLE | V7: =IF(ISNUMBER(tblLines[[#This Row],[payment_date]]),EDATE(tblLines[[#This Row],[payment_date]]-1,-12)+1,"") -> 45853 | W7: =IF(AND(ISNUMBER(tblLines[[#This Row],[fund_received_date]]),tblLines[[#This Row],[fund_received_date]]<=Summary!$B$2),tblLines[[#This Row],[fund_received_date]],"") -> 46234 | X7: =IF(AND(ISNUMBER(tblLines[[#This Row],[remitted_date]]),tblLines[[#This Row],[remitted_date]]<=Summary!$B$2),tblLines[[#This Row],[remitted_date]],"") -> 46233 | Y7: =IF(tblLines[[#This Row],[Settled]]<>"",MIN(ROUND(tblLines[[#This Row],[Cap]],2),ROUND(tblLines[[#This Row],[sg_amount]],2)),0) -> 120 | Z7: =IF(ISNUMBER(tblLines[[#This Row],[remitted_amount]]),IF(tblLines[[#This Row],[Remit]]<>"",MIN(ROUND(tblLines[[#This Row],[remitted_amount]],2),ROUND(tblLines[[#This Row],[sg_amount]],2)),0),IF(tblLines[[#This Row],[Remit]]<>"",ROUND(tblLines[[#This Row],[sg_amount]],2),0)) -> 120 | AA7: =IF(OR(tblLines[[#This Row],[Own_due]]="",tblLines[[#This Row],[sg_amount]]<=0,tblLines[[#This Row],[Flag_db]]=1,tblLines[[#This Row],[Cap]]<=0),"impossible",IF(ISNUMBER(tblLines[[#This Row],[fund_received_date]]),IF(tblLines[[#This Row],[fund_received_date]]<tblLines[[#This Row],[Earliest_prepay]],"impossible",IF(tblLines[[#This Row],[fund_received_date]]<=Summary!$B$2,IF(OR(tblLines[[#This Row],[fund_received_date]]<tblLines[[#This Row],[payment_date]],tblLines[[#This Row],[fund_received_date]]<=tblLines[[#This Row],[Own_due]]),"confirmed",IF(tblLines[[#This Row],[fund_received_date]]>tblLines[[#This Row],[Own_due]],"impossible","possible")),IF(tblLines[[#This Row],[fund_received_date]]<=tblLines[[#This Row],[Own_due]],"possible","impossible"))),IF(AND(ISNUMBER(tblLines[[#This Row],[remitted_date]]),tblLines[[#This Row],[remitted_date]]>tblLines[[#This Row],[Own_due]]),"impossible","possible"))) -> confirmed | AB7: =IF(OR(tblLines[[#This Row],[Flag_db]]=1,tblLines[[#This Row],[Own_due]]=""),"",_xlfn.MAXIFS(tblLines[Own_due],tblLines[employee_id],tblLines[[#This Row],[employee_id]],tblLines[payment_date],"<"&tblLines[[#This Row],[payment_date]],tblLines[Evidence_own],"confirmed")) -> 0 | AC7: =IF(OR(tblLines[[#This Row],[Flag_db]]=1,tblLines[[#This Row],[Own_due]]=""),"",_xlfn.MAXIFS(tblLines[Own_due],tblLines[employee_id],tblLines[[#This Row],[employee_id]],tblLines[payment_date],"<"&tblLines[[#This Row],[payment_date]],tblLines[Evidence_own],"<>impossible")) -> 0 | AD7: =IF(tblLines[[#This Row],[Own_due]]="","",IF(AND(ISNUMBER(tblLines[[#This Row],[Confirmed_latest]]),tblLines[[#This Row],[Confirmed_latest]]>tblLines[[#This Row],[Own_due]]),tblLines[[#This Row],[Confirmed_latest]],tblLines[[#This Row],[Own_due]])) -> 46238 | AE7: =IF(tblLines[[#This Row],[Own_due]]="",tblLines[[#This Row],[Own_pathway]],IF(AND(ISNUMBER(tblLines[[#This Row],[Confirmed_latest]]),tblLines[[#This Row],[Confirmed_latest]]>tblLines[[#This Row],[Own_due]]),"ITEM4_ALIGNED",tblLines[[#This Row],[Own_pathway]])) -> OUT_OF_CYCLE | AF7: =IF(tblLines[[#This Row],[Final_due]]="","",IF(AND(ISNUMBER(tblLines[[#This Row],[Possible_latest]]),tblLines[[#This Row],[Possible_latest]]>tblLines[[#This Row],[Final_due]]),tblLines[[#This Row],[Possible_latest]],"")) | AG7: =IF(tblLines[[#This Row],[Final_due]]="","",IF((tblLines[[#This Row],[Final_due]]>Summary!$B$6),1,0)) -> 0 | AH7: =IF(tblLines[[#This Row],[Flag_db]]=1,"DB",IF(tblLines[[#This Row],[Final_due]]="","",IF(tblLines[[#This Row],[sg_amount]]<=0,"NIL",IF(tblLines[[#This Row],[Settled]]<>"",IF(tblLines[[#This Row],[Settled]]<tblLines[[#This Row],[payment_date]],IF(tblLines[[#This Row],[Settled]]>=tblLines[[#This Row],[Earliest_prepay]],IF((tblLines[[#This Row],[Receipt_credit]]>=tblLines[[#This Row],[sg_amount]]),"A1",IF(tblLines[[#This Row],[Final_due]]>=Summary!$B$2,"A2",IF(OR((tblLines[[#This Row],[Final_due]]>Summary!$B$6),AND((tblLines[[#This Row],[Possible_item4]]<>""),Summary!$B$2<=tblLines[[#This Row],[Possible_item4]])),"A3","A4"))),IF(tblLines[[#This Row],[Final_due]]>=Summary!$B$2,"S1",IF(OR((tblLines[[#This Row],[Final_due]]>Summary!$B$6),AND((tblLines[[#This Row],[Possible_item4]]<>""),Summary!$B$2<=tblLines[[#This Row],[Possible_item4]])),"S2","S3"))),IF(AND((tblLines[[#This Row],[Possible_item4]]<>""),tblLines[[#This Row],[Final_due]]<tblLines[[#This Row],[Settled]],tblLines[[#This Row],[Settled]]<=tblLines[[#This Row],[Possible_item4]]),IF((tblLines[[#This Row],[Receipt_credit]]>=tblLines[[#This Row],[sg_amount]]),"B1",IF(Summary!$B$2<=tblLines[[#This Row],[Possible_item4]],"B2","B3")),IF(AND((tblLines[[#This Row],[Final_due]]>Summary!$B$6),tblLines[[#This Row],[Settled]]>tblLines[[#This Row],[Final_due]]),IF((tblLines[[#This Row],[Receipt_credit]]>=tblLines[[#This Row],[sg_amount]]),"C1","C2"),IF(tblLines[[#This Row],[Settled]]<=tblLines[[#This Row],[Final_due]],IF((tblLines[[#This Row],[Receipt_credit]]>=tblLines[[#This Row],[sg_amount]]),"D1",IF(OR((tblLines[[#This Row],[Final_due]]>Summary!$B$6),AND((tblLines[[#This Row],[Possible_item4]]<>""),Summary!$B$2<=tblLines[[#This Row],[Possible_item4]])),"D2",IF(tblLines[[#This Row],[Final_due]]<Summary!$B$2,"D3","D4"))),"E")))),IF(AND(tblLines[[#This Row],[Remit]]<>"",tblLines[[#This Row],[sg_amount]]-tblLines[[#This Row],[Credit]]<=0),IF(AND((tblLines[[#This Row],[Possible_item4]]<>""),tblLines[[#This Row],[Final_due]]<tblLines[[#This Row],[Remit]],tblLines[[#This Row],[Remit]]<=tblLines[[#This Row],[Possible_item4]]),"R1",IF(AND((tblLines[[#This Row],[Final_due]]>Summary!$B$6),tblLines[[#This Row],[Remit]]>tblLines[[#This Row],[Final_due]]),"R2",IF(tblLines[[#This Row],[Remit]]<=tblLines[[#This Row],[Final_due]],"R3","R4"))),IF(tblLines[[#This Row],[Final_due]]<Summary!$B$2,IF(OR((tblLines[[#This Row],[Final_due]]>Summary!$B$6),AND((tblLines[[#This Row],[Possible_item4]]<>""),Summary!$B$2<=tblLines[[#This Row],[Possible_item4]])),"N1","N2"),"N3")))))) -> D1 | AI7: =IF(tblLines[[#This Row],[Branch]]="","",INDEX(tblCodes[verdict],MATCH(tblLines[[#This Row],[Branch]],tblCodes[code],0))) -> ON_TIME | AJ7: =IF(tblLines[[#This Row],[Branch]]="","",T(INDEX(tblCodes[unassessable],MATCH(tblLines[[#This Row],[Branch]],tblCodes[code],0)))) | AK7: =IF(tblLines[[#This Row],[Branch]]="",0,INDEX(tblCodes[exposed],MATCH(tblLines[[#This Row],[Branch]],tblCodes[code],0))) -> 0 | AL7: =IF(tblLines[[#This Row],[Branch]]="",0,INDEX(tblCodes[stale],MATCH(tblLines[[#This Row],[Branch]],tblCodes[code],0))) -> 0 | AM7: =IF(tblLines[[#This Row],[Branch]]="",0,INDEX(tblCodes[otrc],MATCH(tblLines[[#This Row],[Branch]],tblCodes[code],0))*tblLines[[#This Row],[Receipt_credit]]) -> 120 | AN7: =IF((tblLines[[#This Row],[Exposed]]=1),MAX(ROUND(tblLines[[#This Row],[sg_amount]],2)-tblLines[[#This Row],[OTRC]],0),"") | AO7: =IF((tblLines[[#This Row],[Exposed]]=1),IF(AND(tblLines[[#This Row],[Settled]]<>"",tblLines[[#This Row],[Stale_prepay]]=0,tblLines[[#This Row],[Settled]]>tblLines[[#This Row],[Final_due]],OR(Summary!$B$3="",tblLines[[#This Row],[Settled]]<Summary!$B$3)),MIN(tblLines[[#This Row],[Receipt_credit]],tblLines[[#This Row],[Base_shortfall]]),0),"") | AP7: =IF((tblLines[[#This Row],[Exposed]]=1),MAX(tblLines[[#This Row],[Base_shortfall]]-tblLines[[#This Row],[Offset_s18D]],0),"") | AQ7: =IF((tblLines[[#This Row],[Exposed]]=1),IF(AND(tblLines[[#This Row],[Settled]]<>"",tblLines[[#This Row],[Stale_prepay]]=0,(tblLines[[#This Row],[Receipt_credit]]>=tblLines[[#This Row],[sg_amount]])),"fund receipt",IF(AND(tblLines[[#This Row],[Settled]]<>"",tblLines[[#This Row],[Stale_prepay]]=0),"as-at date (shortfall remains after part receipt)",IF(AND(OR(tblLines[[#This Row],[Settled]]<>"",tblLines[[#This Row],[Remit]]<>""),tblLines[[#This Row],[Stale_prepay]]=0),"as-at date (no fund receipt recorded)","as-at date (nothing applied to this payday)"))),"") | AR7: =IF((tblLines[[#This Row],[Exposed]]=1),IF(AND(tblLines[[#This Row],[Settled]]<>"",tblLines[[#This Row],[Stale_prepay]]=0,(tblLines[[#This Row],[Receipt_credit]]>=tblLines[[#This Row],[sg_amount]])),tblLines[[#This Row],[Settled]],Summary!$B$2),"") | AS7: =IF((tblLines[[#This Row],[Exposed]]=1),MIN(IF(Summary!$B$3="",DATE(2030,12,31),Summary!$B$3-1),IF(AND(tblLines[[#This Row],[Settled]]<>"",tblLines[[#This Row],[Stale_prepay]]=0,(tblLines[[#This Row],[Receipt_credit]]>=tblLines[[#This Row],[sg_amount]]),tblLines[[#This Row],[Final_shortfall]]=0),tblLines[[#This Row],[Settled]],Summary!$B$2)),"") | AT7: =IF((tblLines[[#This Row],[Exposed]]=1),IF(tblLines[[#This Row],[Past_horizon]]=1,"",MAX(tblLines[[#This Row],[Outstanding_to]]-tblLines[[#This Row],[Final_due]],0)),"") | AU7: =IF((tblLines[[#This Row],[Exposed]]=1),IF(tblLines[[#This Row],[NEC_end]]>tblLines[[#This Row],[Final_due]],tblLines[[#This Row],[Base_shortfall]]*(EXP(SUMPRODUCT((((((tblLines[[#This Row],[NEC_end]]+tblGic[to]-ABS(tblLines[[#This Row],[NEC_end]]-tblGic[to]))/2)-(((tblLines[[#This Row],[Final_due]]+1)+tblGic[from]+ABS((tblLines[[#This Row],[Final_due]]+1)-tblGic[from]))/2)+1)>0)*(((tblLines[[#This Row],[NEC_end]]+tblGic[to]-ABS(tblLines[[#This Row],[NEC_end]]-tblGic[to]))/2)-(((tblLines[[#This Row],[Final_due]]+1)+tblGic[from]+ABS((tblLines[[#This Row],[Final_due]]+1)-tblGic[from]))/2)+1))*LN(1+tblGic[annual_pct]/100/tblGic[divisor])))-1),0),"") | AV7: =IF((tblLines[[#This Row],[Exposed]]=1),IF(tblLines[[#This Row],[NEC_end]]>Summary!$B$7,1,0),"") | AW7: =IF((tblLines[[#This Row],[Exposed]]=1),ROUND(tblLines[[#This Row],[Final_shortfall]],2),"") | AX7: =IF((tblLines[[#This Row],[Exposed]]=1),ROUND(tblLines[[#This Row],[NEC]],2),"") | AY7: =IF((tblLines[[#This Row],[Exposed]]=1),0,"") | AZ7: =IF((tblLines[[#This Row],[Exposed]]=1),ROUND(0.6*(tblLines[[#This Row],[Final_shortfall]]+tblLines[[#This Row],[NEC]]),2),"") | BA7: =IF((tblLines[[#This Row],[Exposed]]=1),tblLines[[#This Row],[Shortfall_r]]+tblLines[[#This Row],[NEC_r]]+tblLines[[#This Row],[Uplift_best]],"") | BB7: =IF((tblLines[[#This Row],[Exposed]]=1),tblLines[[#This Row],[Shortfall_r]]+tblLines[[#This Row],[NEC_r]]+tblLines[[#This Row],[Uplift_worst]],"") | BC7: =IF(AND(tblLines[[#This Row],[Flag_db]]<>1,ISNUMBER(tblLines[[#This Row],[sg_amount]]),tblLines[[#This Row],[sg_amount]]>0,tblLines[[#This Row],[Cap]]>0,OR(ISNUMBER(tblLines[[#This Row],[fund_received_date]]),ISNUMBER(tblLines[[#This Row],[remitted_date]])),IF(ISNUMBER(tblLines[[#This Row],[fund_received_date]]),tblLines[[#This Row],[fund_received_date]],tblLines[[#This Row],[remitted_date]])<=DATE(2026,7,28)),1,0) -> 0 | BD7: =IF(tblLines[[#This Row],[Settled]]<>"",1,0) -> 1 | BE7: =IF(AND(tblLines[[#This Row],[Verdict]]<>"",tblLines[[#This Row],[Verdict]]<>"SKIPPED",ISNUMBER(tblLines[[#This Row],[sg_amount]]),tblLines[[#This Row],[sg_amount]]>0),1,0) -> 1 | BF7: =IF(COUNTIFS(tblLines[employee_id],tblLines[[#This Row],[employee_id]],tblLines[payment_date],tblLines[[#This Row],[payment_date]],tblLines[sg_amount],tblLines[[#This Row],[sg_amount]],tblLines[remitted_date],tblLines[[#This Row],[remitted_date]]&"",tblLines[fund_received_date],tblLines[[#This Row],[fund_received_date]]&"")>1,1,0) -> 0
A8: EMP007 | B8: 46212 | C8: 900 | D8: 46216 | G8: 46216 | H8: no | I8: no | K8: yes | L8: =IF(OR(LOWER(TRIM(tblLines[[#This Row],[defined_benefit]]&""))={"1","t","true","y","yes"}),1,IF(OR(LOWER(TRIM(tblLines[[#This Row],[defined_benefit]]&""))={"","0","f","false","n","no"}),0,"")) -> 1 | M8: =IF(OR(LOWER(TRIM(tblLines[[#This Row],[out_of_cycle]]&""))={"1","t","true","y","yes"}),1,IF(OR(LOWER(TRIM(tblLines[[#This Row],[out_of_cycle]]&""))={"","0","f","false","n","no"}),0,"")) -> 0 | N8: =IF(OR(LOWER(TRIM(tblLines[[#This Row],[first_contribution_to_fund]]&""))={"1","t","true","y","yes"}),1,IF(OR(LOWER(TRIM(tblLines[[#This Row],[first_contribution_to_fund]]&""))={"","0","f","false","n","no"}),0,"")) -> 0 | O8: =TRIM(IF(OR(AND(tblLines[[#This Row],[payment_date]]<>"",NOT(ISNUMBER(tblLines[[#This Row],[payment_date]]))),AND(tblLines[[#This Row],[remitted_date]]<>"",NOT(ISNUMBER(tblLines[[#This Row],[remitted_date]]))),AND(tblLines[[#This Row],[fund_received_date]]<>"",NOT(ISNUMBER(tblLines[[#This Row],[fund_received_date]]))),AND(tblLines[[#This Row],[next_standard_payday]]<>"",NOT(ISNUMBER(tblLines[[#This Row],[next_standard_payday]])))),"date ","")&IF(NOT(ISNUMBER(tblLines[[#This Row],[payment_date]])),"payment_date ","")&IF(AND(ISNUMBER(tblLines[[#This Row],[payment_date]]),tblLines[[#This Row],[payment_date]]<DATE(2026,7,1)),"pre-1-Jul-2026 ","")&IF(OR(AND(tblLines[[#This Row],[sg_amount]]<>"",OR(NOT(ISNUMBER(tblLines[[#This Row],[sg_amount]])),tblLines[[#This Row],[sg_amount]]<0)),AND(tblLines[[#This Row],[remitted_amount]]<>"",OR(NOT(ISNUMBER(tblLines[[#This Row],[remitted_amount]])),tblLines[[#This Row],[remitted_amount]]<0)),AND(tblLines[[#This Row],[matched_amount]]<>"",OR(NOT(ISNUMBER(tblLines[[#This Row],[matched_amount]])),tblLines[[#This Row],[matched_amount]]<0))),"amount ","")&IF(NOT(ISNUMBER(tblLines[[#This Row],[sg_amount]])),"sg_amount ","")&IF(OR(tblLines[[#This Row],[Flag_ftf]]="",tblLines[[#This Row],[Flag_ooc]]="",tblLines[[#This Row],[Flag_db]]=""),"yes/no ","")&IF(AND(ISNUMBER(tblLines[[#This Row],[remitted_amount]]),ISNUMBER(tblLines[[#This Row],[sg_amount]]),tblLines[[#This Row],[remitted_amount]]>tblLines[[#This Row],[sg_amount]]),"remitted_amount>sg ","")&IF(AND(ISNUMBER(tblLines[[#This Row],[remitted_amount]]),NOT(ISNUMBER(tblLines[[#This Row],[remitted_date]]))),"remitted_amount-needs-date ","")&IF(AND(ISNUMBER(tblLines[[#This Row],[matched_amount]]),ISNUMBER(tblLines[[#This Row],[sg_amount]]),tblLines[[#This Row],[matched_amount]]>tblLines[[#This Row],[sg_amount]]),"matched_amount>sg ","")&IF(AND(ISNUMBER(tblLines[[#This Row],[matched_amount]]),ISNUMBER(tblLines[[#This Row],[remitted_amount]]),tblLines[[#This Row],[remitted_amount]]>tblLines[[#This Row],[matched_amount]]),"remitted_amount>matched ","")&IF(AND(ISNUMBER(tblLines[[#This Row],[matched_amount]]),ISNUMBER(tblLines[[#This Row],[sg_amount]]),tblLines[[#This Row],[matched_amount]]<tblLines[[#This Row],[sg_amount]],ISNUMBER(tblLines[[#This Row],[remitted_date]]),NOT(ISNUMBER(tblLines[[#This Row],[remitted_amount]]))),"partial-match-needs-remitted_amount ","")&IF(AND(ISNUMBER(tblLines[[#This Row],[fund_received_date]]),ISNUMBER(tblLines[[#This Row],[remitted_date]]),tblLines[[#This Row],[fund_received_date]]<tblLines[[#This Row],[remitted_date]]),"receipt-before-remittance ","")&IF(AND(tblLines[[#This Row],[Flag_ooc]]=1,NOT(ISNUMBER(tblLines[[#This Row],[next_standard_payday]]))),"out_of_cycle-needs-next_standard_payday ","")&IF(AND(tblLines[[#This Row],[Flag_ooc]]=1,ISNUMBER(tblLines[[#This Row],[next_standard_payday]]),ISNUMBER(tblLines[[#This Row],[payment_date]]),tblLines[[#This Row],[next_standard_payday]]<=tblLines[[#This Row],[payment_date]]),"next_standard_payday-not-after-payday ","")) | P8: =IF(OR(_xlfn.ISFORMULA(tblLines[[#This Row],[employee_id]]),_xlfn.ISFORMULA(tblLines[[#This Row],[payment_date]]),_xlfn.ISFORMULA(tblLines[[#This Row],[sg_amount]]),_xlfn.ISFORMULA(tblLines[[#This Row],[remitted_date]]),_xlfn.ISFORMULA(tblLines[[#This Row],[remitted_amount]]),_xlfn.ISFORMULA(tblLines[[#This Row],[matched_amount]]),_xlfn.ISFORMULA(tblLines[[#This Row],[fund_received_date]]),_xlfn.ISFORMULA(tblLines[[#This Row],[first_contribution_to_fund]]),_xlfn.ISFORMULA(tblLines[[#This Row],[out_of_cycle]]),_xlfn.ISFORMULA(tblLines[[#This Row],[next_standard_payday]]),_xlfn.ISFORMULA(tblLines[[#This Row],[defined_benefit]])),1,0) -> 0 | Q8: =IF(ISNUMBER(tblLines[[#This Row],[matched_amount]]),tblLines[[#This Row],[matched_amount]],IF(ISNUMBER(tblLines[[#This Row],[remitted_amount]]),tblLines[[#This Row],[remitted_amount]],tblLines[[#This Row],[sg_amount]])) -> 900 | R8: =IF(AND(tblLines[[#This Row],[Flag_ooc]]=1,ISNUMBER(tblLines[[#This Row],[next_standard_payday]])),WORKDAY.INTL(tblLines[[#This Row],[next_standard_payday]],7,1,tblHolidays[date]),"") | S8: =IF(tblLines[[#This Row],[Flag_ftf]]=1,WORKDAY.INTL(tblLines[[#This Row],[payment_date]],20,1,tblHolidays[date]),"") | T8: =IF(OR(tblLines[[#This Row],[Flag_db]]=1,NOT(ISNUMBER(tblLines[[#This Row],[payment_date]]))),"",IF(OR(tblLines[[#This Row],[Flag_ooc]]=1,tblLines[[#This Row],[Flag_ftf]]=1),MAX(tblLines[[#This Row],[Due_ooc]],tblLines[[#This Row],[Due_ftf]]),WORKDAY.INTL(tblLines[[#This Row],[payment_date]],7,1,tblHolidays[date]))) | U8: =IF(tblLines[[#This Row],[Flag_db]]=1,"SKIP_DB",IF(tblLines[[#This Row],[Flag_ooc]]=1,IF(AND(tblLines[[#This Row],[Flag_ftf]]=1,tblLines[[#This Row],[Due_ftf]]>tblLines[[#This Row],[Due_ooc]]),"EXTENDED_20BD","OUT_OF_CYCLE"),IF(tblLines[[#This Row],[Flag_ftf]]=1,"EXTENDED_20BD","USUAL_7BD"))) -> SKIP_DB | V8: =IF(ISNUMBER(tblLines[[#This Row],[payment_date]]),EDATE(tblLines[[#This Row],[payment_date]]-1,-12)+1,"") -> 45847 | W8: =IF(AND(ISNUMBER(tblLines[[#This Row],[fund_received_date]]),tblLines[[#This Row],[fund_received_date]]<=Summary!$B$2),tblLines[[#This Row],[fund_received_date]],"") -> 46216 | X8: =IF(AND(ISNUMBER(tblLines[[#This Row],[remitted_date]]),tblLines[[#This Row],[remitted_date]]<=Summary!$B$2),tblLines[[#This Row],[remitted_date]],"") -> 46216 | Y8: =IF(tblLines[[#This Row],[Settled]]<>"",MIN(ROUND(tblLines[[#This Row],[Cap]],2),ROUND(tblLines[[#This Row],[sg_amount]],2)),0) -> 900 | Z8: =IF(ISNUMBER(tblLines[[#This Row],[remitted_amount]]),IF(tblLines[[#This Row],[Remit]]<>"",MIN(ROUND(tblLines[[#This Row],[remitted_amount]],2),ROUND(tblLines[[#This Row],[sg_amount]],2)),0),IF(tblLines[[#This Row],[Remit]]<>"",ROUND(tblLines[[#This Row],[sg_amount]],2),0)) -> 900 | AA8: =IF(OR(tblLines[[#This Row],[Own_due]]="",tblLines[[#This Row],[sg_amount]]<=0,tblLines[[#This Row],[Flag_db]]=1,tblLines[[#This Row],[Cap]]<=0),"impossible",IF(ISNUMBER(tblLines[[#This Row],[fund_received_date]]),IF(tblLines[[#This Row],[fund_received_date]]<tblLines[[#This Row],[Earliest_prepay]],"impossible",IF(tblLines[[#This Row],[fund_received_date]]<=Summary!$B$2,IF(OR(tblLines[[#This Row],[fund_received_date]]<tblLines[[#This Row],[payment_date]],tblLines[[#This Row],[fund_received_date]]<=tblLines[[#This Row],[Own_due]]),"confirmed",IF(tblLines[[#This Row],[fund_received_date]]>tblLines[[#This Row],[Own_due]],"impossible","possible")),IF(tblLines[[#This Row],[fund_received_date]]<=tblLines[[#This Row],[Own_due]],"possible","impossible"))),IF(AND(ISNUMBER(tblLines[[#This Row],[remitted_date]]),tblLines[[#This Row],[remitted_date]]>tblLines[[#This Row],[Own_due]]),"impossible","possible"))) -> impossible | AB8: =IF(OR(tblLines[[#This Row],[Flag_db]]=1,tblLines[[#This Row],[Own_due]]=""),"",_xlfn.MAXIFS(tblLines[Own_due],tblLines[employee_id],tblLines[[#This Row],[employee_id]],tblLines[payment_date],"<"&tblLines[[#This Row],[payment_date]],tblLines[Evidence_own],"confirmed")) | AC8: =IF(OR(tblLines[[#This Row],[Flag_db]]=1,tblLines[[#This Row],[Own_due]]=""),"",_xlfn.MAXIFS(tblLines[Own_due],tblLines[employee_id],tblLines[[#This Row],[employee_id]],tblLines[payment_date],"<"&tblLines[[#This Row],[payment_date]],tblLines[Evidence_own],"<>impossible")) | AD8: =IF(tblLines[[#This Row],[Own_due]]="","",IF(AND(ISNUMBER(tblLines[[#This Row],[Confirmed_latest]]),tblLines[[#This Row],[Confirmed_latest]]>tblLines[[#This Row],[Own_due]]),tblLines[[#This Row],[Confirmed_latest]],tblLines[[#This Row],[Own_due]])) | AE8: =IF(tblLines[[#This Row],[Own_due]]="",tblLines[[#This Row],[Own_pathway]],IF(AND(ISNUMBER(tblLines[[#This Row],[Confirmed_latest]]),tblLines[[#This Row],[Confirmed_latest]]>tblLines[[#This Row],[Own_due]]),"ITEM4_ALIGNED",tblLines[[#This Row],[Own_pathway]])) -> SKIP_DB | AF8: =IF(tblLines[[#This Row],[Final_due]]="","",IF(AND(ISNUMBER(tblLines[[#This Row],[Possible_latest]]),tblLines[[#This Row],[Possible_latest]]>tblLines[[#This Row],[Final_due]]),tblLines[[#This Row],[Possible_latest]],"")) | AG8: =IF(tblLines[[#This Row],[Final_due]]="","",IF((tblLines[[#This Row],[Final_due]]>Summary!$B$6),1,0)) | AH8: =IF(tblLines[[#This Row],[Flag_db]]=1,"DB",IF(tblLines[[#This Row],[Final_due]]="","",IF(tblLines[[#This Row],[sg_amount]]<=0,"NIL",IF(tblLines[[#This Row],[Settled]]<>"",IF(tblLines[[#This Row],[Settled]]<tblLines[[#This Row],[payment_date]],IF(tblLines[[#This Row],[Settled]]>=tblLines[[#This Row],[Earliest_prepay]],IF((tblLines[[#This Row],[Receipt_credit]]>=tblLines[[#This Row],[sg_amount]]),"A1",IF(tblLines[[#This Row],[Final_due]]>=Summary!$B$2,"A2",IF(OR((tblLines[[#This Row],[Final_due]]>Summary!$B$6),AND((tblLines[[#This Row],[Possible_item4]]<>""),Summary!$B$2<=tblLines[[#This Row],[Possible_item4]])),"A3","A4"))),IF(tblLines[[#This Row],[Final_due]]>=Summary!$B$2,"S1",IF(OR((tblLines[[#This Row],[Final_due]]>Summary!$B$6),AND((tblLines[[#This Row],[Possible_item4]]<>""),Summary!$B$2<=tblLines[[#This Row],[Possible_item4]])),"S2","S3"))),IF(AND((tblLines[[#This Row],[Possible_item4]]<>""),tblLines[[#This Row],[Final_due]]<tblLines[[#This Row],[Settled]],tblLines[[#This Row],[Settled]]<=tblLines[[#This Row],[Possible_item4]]),IF((tblLines[[#This Row],[Receipt_credit]]>=tblLines[[#This Row],[sg_amount]]),"B1",IF(Summary!$B$2<=tblLines[[#This Row],[Possible_item4]],"B2","B3")),IF(AND((tblLines[[#This Row],[Final_due]]>Summary!$B$6),tblLines[[#This Row],[Settled]]>tblLines[[#This Row],[Final_due]]),IF((tblLines[[#This Row],[Receipt_credit]]>=tblLines[[#This Row],[sg_amount]]),"C1","C2"),IF(tblLines[[#This Row],[Settled]]<=tblLines[[#This Row],[Final_due]],IF((tblLines[[#This Row],[Receipt_credit]]>=tblLines[[#This Row],[sg_amount]]),"D1",IF(OR((tblLines[[#This Row],[Final_due]]>Summary!$B$6),AND((tblLines[[#This Row],[Possible_item4]]<>""),Summary!$B$2<=tblLines[[#This Row],[Possible_item4]])),"D2",IF(tblLines[[#This Row],[Final_due]]<Summary!$B$2,"D3","D4"))),"E")))),IF(AND(tblLines[[#This Row],[Remit]]<>"",tblLines[[#This Row],[sg_amount]]-tblLines[[#This Row],[Credit]]<=0),IF(AND((tblLines[[#This Row],[Possible_item4]]<>""),tblLines[[#This Row],[Final_due]]<tblLines[[#This Row],[Remit]],tblLines[[#This Row],[Remit]]<=tblLines[[#This Row],[Possible_item4]]),"R1",IF(AND((tblLines[[#This Row],[Final_due]]>Summary!$B$6),tblLines[[#This Row],[Remit]]>tblLines[[#This Row],[Final_due]]),"R2",IF(tblLines[[#This Row],[Remit]]<=tblLines[[#This Row],[Final_due]],"R3","R4"))),IF(tblLines[[#This Row],[Final_due]]<Summary!$B$2,IF(OR((tblLines[[#This Row],[Final_due]]>Summary!$B$6),AND((tblLines[[#This Row],[Possible_item4]]<>""),Summary!$B$2<=tblLines[[#This Row],[Possible_item4]])),"N1","N2"),"N3")))))) -> DB | AI8: =IF(tblLines[[#This Row],[Branch]]="","",INDEX(tblCodes[verdict],MATCH(tblLines[[#This Row],[Branch]],tblCodes[code],0))) -> SKIPPED | AJ8: =IF(tblLines[[#This Row],[Branch]]="","",T(INDEX(tblCodes[unassessable],MATCH(tblLines[[#This Row],[Branch]],tblCodes[code],0)))) | AK8: =IF(tblLines[[#This Row],[Branch]]="",0,INDEX(tblCodes[exposed],MATCH(tblLines[[#This Row],[Branch]],tblCodes[code],0))) -> 0 | AL8: =IF(tblLines[[#This Row],[Branch]]="",0,INDEX(tblCodes[stale],MATCH(tblLines[[#This Row],[Branch]],tblCodes[code],0))) -> 0 | AM8: =IF(tblLines[[#This Row],[Branch]]="",0,INDEX(tblCodes[otrc],MATCH(tblLines[[#This Row],[Branch]],tblCodes[code],0))*tblLines[[#This Row],[Receipt_credit]]) -> 0 | AN8: =IF((tblLines[[#This Row],[Exposed]]=1),MAX(ROUND(tblLines[[#This Row],[sg_amount]],2)-tblLines[[#This Row],[OTRC]],0),"") | AO8: =IF((tblLines[[#This Row],[Exposed]]=1),IF(AND(tblLines[[#This Row],[Settled]]<>"",tblLines[[#This Row],[Stale_prepay]]=0,tblLines[[#This Row],[Settled]]>tblLines[[#This Row],[Final_due]],OR(Summary!$B$3="",tblLines[[#This Row],[Settled]]<Summary!$B$3)),MIN(tblLines[[#This Row],[Receipt_credit]],tblLines[[#This Row],[Base_shortfall]]),0),"") | AP8: =IF((tblLines[[#This Row],[Exposed]]=1),MAX(tblLines[[#This Row],[Base_shortfall]]-tblLines[[#This Row],[Offset_s18D]],0),"") | AQ8: =IF((tblLines[[#This Row],[Exposed]]=1),IF(AND(tblLines[[#This Row],[Settled]]<>"",tblLines[[#This Row],[Stale_prepay]]=0,(tblLines[[#This Row],[Receipt_credit]]>=tblLines[[#This Row],[sg_amount]])),"fund receipt",IF(AND(tblLines[[#This Row],[Settled]]<>"",tblLines[[#This Row],[Stale_prepay]]=0),"as-at date (shortfall remains after part receipt)",IF(AND(OR(tblLines[[#This Row],[Settled]]<>"",tblLines[[#This Row],[Remit]]<>""),tblLines[[#This Row],[Stale_prepay]]=0),"as-at date (no fund receipt recorded)","as-at date (nothing applied to this payday)"))),"") | AR8: =IF((tblLines[[#This Row],[Exposed]]=1),IF(AND(tblLines[[#This Row],[Settled]]<>"",tblLines[[#This Row],[Stale_prepay]]=0,(tblLines[[#This Row],[Receipt_credit]]>=tblLines[[#This Row],[sg_amount]])),tblLines[[#This Row],[Settled]],Summary!$B$2),"") | AS8: =IF((tblLines[[#This Row],[Exposed]]=1),MIN(IF(Summary!$B$3="",DATE(2030,12,31),Summary!$B$3-1),IF(AND(tblLines[[#This Row],[Settled]]<>"",tblLines[[#This Row],[Stale_prepay]]=0,(tblLines[[#This Row],[Receipt_credit]]>=tblLines[[#This Row],[sg_amount]]),tblLines[[#This Row],[Final_shortfall]]=0),tblLines[[#This Row],[Settled]],Summary!$B$2)),"") | AT8: =IF((tblLines[[#This Row],[Exposed]]=1),IF(tblLines[[#This Row],[Past_horizon]]=1,"",MAX(tblLines[[#This Row],[Outstanding_to]]-tblLines[[#This Row],[Final_due]],0)),"") | AU8: =IF((tblLines[[#This Row],[Exposed]]=1),IF(tblLines[[#This Row],[NEC_end]]>tblLines[[#This Row],[Final_due]],tblLines[[#This Row],[Base_shortfall]]*(EXP(SUMPRODUCT((((((tblLines[[#This Row],[NEC_end]]+tblGic[to]-ABS(tblLines[[#This Row],[NEC_end]]-tblGic[to]))/2)-(((tblLines[[#This Row],[Final_due]]+1)+tblGic[from]+ABS((tblLines[[#This Row],[Final_due]]+1)-tblGic[from]))/2)+1)>0)*(((tblLines[[#This Row],[NEC_end]]+tblGic[to]-ABS(tblLines[[#This Row],[NEC_end]]-tblGic[to]))/2)-(((tblLines[[#This Row],[Final_due]]+1)+tblGic[from]+ABS((tblLines[[#This Row],[Final_due]]+1)-tblGic[from]))/2)+1))*LN(1+tblGic[annual_pct]/100/tblGic[divisor])))-1),0),"") | AV8: =IF((tblLines[[#This Row],[Exposed]]=1),IF(tblLines[[#This Row],[NEC_end]]>Summary!$B$7,1,0),"") | AW8: =IF((tblLines[[#This Row],[Exposed]]=1),ROUND(tblLines[[#This Row],[Final_shortfall]],2),"") | AX8: =IF((tblLines[[#This Row],[Exposed]]=1),ROUND(tblLines[[#This Row],[NEC]],2),"") | AY8: =IF((tblLines[[#This Row],[Exposed]]=1),0,"") | AZ8: =IF((tblLines[[#This Row],[Exposed]]=1),ROUND(0.6*(tblLines[[#This Row],[Final_shortfall]]+tblLines[[#This Row],[NEC]]),2),"") | BA8: =IF((tblLines[[#This Row],[Exposed]]=1),tblLines[[#This Row],[Shortfall_r]]+tblLines[[#This Row],[NEC_r]]+tblLines[[#This Row],[Uplift_best]],"") | BB8: =IF((tblLines[[#This Row],[Exposed]]=1),tblLines[[#This Row],[Shortfall_r]]+tblLines[[#This Row],[NEC_r]]+tblLines[[#This Row],[Uplift_worst]],"") | BC8: =IF(AND(tblLines[[#This Row],[Flag_db]]<>1,ISNUMBER(tblLines[[#This Row],[sg_amount]]),tblLines[[#This Row],[sg_amount]]>0,tblLines[[#This Row],[Cap]]>0,OR(ISNUMBER(tblLines[[#This Row],[fund_received_date]]),ISNUMBER(tblLines[[#This Row],[remitted_date]])),IF(ISNUMBER(tblLines[[#This Row],[fund_received_date]]),tblLines[[#This Row],[fund_received_date]],tblLines[[#This Row],[remitted_date]])<=DATE(2026,7,28)),1,0) -> 0 | BD8: =IF(tblLines[[#This Row],[Settled]]<>"",1,0) -> 1 | BE8: =IF(AND(tblLines[[#This Row],[Verdict]]<>"",tblLines[[#This Row],[Verdict]]<>"SKIPPED",ISNUMBER(tblLines[[#This Row],[sg_amount]]),tblLines[[#This Row],[sg_amount]]>0),1,0) -> 0 | BF8: =IF(COUNTIFS(tblLines[employee_id],tblLines[[#This Row],[employee_id]],tblLines[payment_date],tblLines[[#This Row],[payment_date]],tblLines[sg_amount],tblLines[[#This Row],[sg_amount]],tblLines[remitted_date],tblLines[[#This Row],[remitted_date]]&"",tblLines[fund_received_date],tblLines[[#This Row],[fund_received_date]]&"")>1,1,0) -> 0
A9: EMP001 | B9: 46226 | C9: 612 | D9: 46239 | G9: 46240 | H9: no | I9: no | K9: no | L9: =IF(OR(LOWER(TRIM(tblLines[[#This Row],[defined_benefit]]&""))={"1","t","true","y","yes"}),1,IF(OR(LOWER(TRIM(tblLines[[#This Row],[defined_benefit]]&""))={"","0","f","false","n","no"}),0,"")) -> 0 | M9: =IF(OR(LOWER(TRIM(tblLines[[#This Row],[out_of_cycle]]&""))={"1","t","true","y","yes"}),1,IF(OR(LOWER(TRIM(tblLines[[#This Row],[out_of_cycle]]&""))={"","0","f","false","n","no"}),0,"")) -> 0 | N9: =IF(OR(LOWER(TRIM(tblLines[[#This Row],[first_contribution_to_fund]]&""))={"1","t","true","y","yes"}),1,IF(OR(LOWER(TRIM(tblLines[[#This Row],[first_contribution_to_fund]]&""))={"","0","f","false","n","no"}),0,"")) -> 0 | O9: =TRIM(IF(OR(AND(tblLines[[#This Row],[payment_date]]<>"",NOT(ISNUMBER(tblLines[[#This Row],[payment_date]]))),AND(tblLines[[#This Row],[remitted_date]]<>"",NOT(ISNUMBER(tblLines[[#This Row],[remitted_date]]))),AND(tblLines[[#This Row],[fund_received_date]]<>"",NOT(ISNUMBER(tblLines[[#This Row],[fund_received_date]]))),AND(tblLines[[#This Row],[next_standard_payday]]<>"",NOT(ISNUMBER(tblLines[[#This Row],[next_standard_payday]])))),"date ","")&IF(NOT(ISNUMBER(tblLines[[#This Row],[payment_date]])),"payment_date ","")&IF(AND(ISNUMBER(tblLines[[#This Row],[payment_date]]),tblLines[[#This Row],[payment_date]]<DATE(2026,7,1)),"pre-1-Jul-2026 ","")&IF(OR(AND(tblLines[[#This Row],[sg_amount]]<>"",OR(NOT(ISNUMBER(tblLines[[#This Row],[sg_amount]])),tblLines[[#This Row],[sg_amount]]<0)),AND(tblLines[[#This Row],[remitted_amount]]<>"",OR(NOT(ISNUMBER(tblLines[[#This Row],[remitted_amount]])),tblLines[[#This Row],[remitted_amount]]<0)),AND(tblLines[[#This Row],[matched_amount]]<>"",OR(NOT(ISNUMBER(tblLines[[#This Row],[matched_amount]])),tblLines[[#This Row],[matched_amount]]<0))),"amount ","")&IF(NOT(ISNUMBER(tblLines[[#This Row],[sg_amount]])),"sg_amount ","")&IF(OR(tblLines[[#This Row],[Flag_ftf]]="",tblLines[[#This Row],[Flag_ooc]]="",tblLines[[#This Row],[Flag_db]]=""),"yes/no ","")&IF(AND(ISNUMBER(tblLines[[#This Row],[remitted_amount]]),ISNUMBER(tblLines[[#This Row],[sg_amount]]),tblLines[[#This Row],[remitted_amount]]>tblLines[[#This Row],[sg_amount]]),"remitted_amount>sg ","")&IF(AND(ISNUMBER(tblLines[[#This Row],[remitted_amount]]),NOT(ISNUMBER(tblLines[[#This Row],[remitted_date]]))),"remitted_amount-needs-date ","")&IF(AND(ISNUMBER(tblLines[[#This Row],[matched_amount]]),ISNUMBER(tblLines[[#This Row],[sg_amount]]),tblLines[[#This Row],[matched_amount]]>tblLines[[#This Row],[sg_amount]]),"matched_amount>sg ","")&IF(AND(ISNUMBER(tblLines[[#This Row],[matched_amount]]),ISNUMBER(tblLines[[#This Row],[remitted_amount]]),tblLines[[#This Row],[remitted_amount]]>tblLines[[#This Row],[matched_amount]]),"remitted_amount>matched ","")&IF(AND(ISNUMBER(tblLines[[#This Row],[matched_amount]]),ISNUMBER(tblLines[[#This Row],[sg_amount]]),tblLines[[#This Row],[matched_amount]]<tblLines[[#This Row],[sg_amount]],ISNUMBER(tblLines[[#This Row],[remitted_date]]),NOT(ISNUMBER(tblLines[[#This Row],[remitted_amount]]))),"partial-match-needs-remitted_amount ","")&IF(AND(ISNUMBER(tblLines[[#This Row],[fund_received_date]]),ISNUMBER(tblLines[[#This Row],[remitted_date]]),tblLines[[#This Row],[fund_received_date]]<tblLines[[#This Row],[remitted_date]]),"receipt-before-remittance ","")&IF(AND(tblLines[[#This Row],[Flag_ooc]]=1,NOT(ISNUMBER(tblLines[[#This Row],[next_standard_payday]]))),"out_of_cycle-needs-next_standard_payday ","")&IF(AND(tblLines[[#This Row],[Flag_ooc]]=1,ISNUMBER(tblLines[[#This Row],[next_standard_payday]]),ISNUMBER(tblLines[[#This Row],[payment_date]]),tblLines[[#This Row],[next_standard_payday]]<=tblLines[[#This Row],[payment_date]]),"next_standard_payday-not-after-payday ","")) | P9: =IF(OR(_xlfn.ISFORMULA(tblLines[[#This Row],[employee_id]]),_xlfn.ISFORMULA(tblLines[[#This Row],[payment_date]]),_xlfn.ISFORMULA(tblLines[[#This Row],[sg_amount]]),_xlfn.ISFORMULA(tblLines[[#This Row],[remitted_date]]),_xlfn.ISFORMULA(tblLines[[#This Row],[remitted_amount]]),_xlfn.ISFORMULA(tblLines[[#This Row],[matched_amount]]),_xlfn.ISFORMULA(tblLines[[#This Row],[fund_received_date]]),_xlfn.ISFORMULA(tblLines[[#This Row],[first_contribution_to_fund]]),_xlfn.ISFORMULA(tblLines[[#This Row],[out_of_cycle]]),_xlfn.ISFORMULA(tblLines[[#This Row],[next_standard_payday]]),_xlfn.ISFORMULA(tblLines[[#This Row],[defined_benefit]])),1,0) -> 0 | Q9: =IF(ISNUMBER(tblLines[[#This Row],[matched_amount]]),tblLines[[#This Row],[matched_amount]],IF(ISNUMBER(tblLines[[#This Row],[remitted_amount]]),tblLines[[#This Row],[remitted_amount]],tblLines[[#This Row],[sg_amount]])) -> 612 | R9: =IF(AND(tblLines[[#This Row],[Flag_ooc]]=1,ISNUMBER(tblLines[[#This Row],[next_standard_payday]])),WORKDAY.INTL(tblLines[[#This Row],[next_standard_payday]],7,1,tblHolidays[date]),"") | S9: =IF(tblLines[[#This Row],[Flag_ftf]]=1,WORKDAY.INTL(tblLines[[#This Row],[payment_date]],20,1,tblHolidays[date]),"") | T9: =IF(OR(tblLines[[#This Row],[Flag_db]]=1,NOT(ISNUMBER(tblLines[[#This Row],[payment_date]]))),"",IF(OR(tblLines[[#This Row],[Flag_ooc]]=1,tblLines[[#This Row],[Flag_ftf]]=1),MAX(tblLines[[#This Row],[Due_ooc]],tblLines[[#This Row],[Due_ftf]]),WORKDAY.INTL(tblLines[[#This Row],[payment_date]],7,1,tblHolidays[date]))) -> 46238 | U9: =IF(tblLines[[#This Row],[Flag_db]]=1,"SKIP_DB",IF(tblLines[[#This Row],[Flag_ooc]]=1,IF(AND(tblLines[[#This Row],[Flag_ftf]]=1,tblLines[[#This Row],[Due_ftf]]>tblLines[[#This Row],[Due_ooc]]),"EXTENDED_20BD","OUT_OF_CYCLE"),IF(tblLines[[#This Row],[Flag_ftf]]=1,"EXTENDED_20BD","USUAL_7BD"))) -> USUAL_7BD | V9: =IF(ISNUMBER(tblLines[[#This Row],[payment_date]]),EDATE(tblLines[[#This Row],[payment_date]]-1,-12)+1,"") -> 45861 | W9: =IF(AND(ISNUMBER(tblLines[[#This Row],[fund_received_date]]),tblLines[[#This Row],[fund_received_date]]<=Summary!$B$2),tblLines[[#This Row],[fund_received_date]],"") -> 46240 | X9: =IF(AND(ISNUMBER(tblLines[[#This Row],[remitted_date]]),tblLines[[#This Row],[remitted_date]]<=Summary!$B$2),tblLines[[#This Row],[remitted_date]],"") -> 46239 | Y9: =IF(tblLines[[#This Row],[Settled]]<>"",MIN(ROUND(tblLines[[#This Row],[Cap]],2),ROUND(tblLines[[#This Row],[sg_amount]],2)),0) -> 612 | Z9: =IF(ISNUMBER(tblLines[[#This Row],[remitted_amount]]),IF(tblLines[[#This Row],[Remit]]<>"",MIN(ROUND(tblLines[[#This Row],[remitted_amount]],2),ROUND(tblLines[[#This Row],[sg_amount]],2)),0),IF(tblLines[[#This Row],[Remit]]<>"",ROUND(tblLines[[#This Row],[sg_amount]],2),0)) -> 612 | AA9: =IF(OR(tblLines[[#This Row],[Own_due]]="",tblLines[[#This Row],[sg_amount]]<=0,tblLines[[#This Row],[Flag_db]]=1,tblLines[[#This Row],[Cap]]<=0),"impossible",IF(ISNUMBER(tblLines[[#This Row],[fund_received_date]]),IF(tblLines[[#This Row],[fund_received_date]]<tblLines[[#This Row],[Earliest_prepay]],"impossible",IF(tblLines[[#This Row],[fund_received_date]]<=Summary!$B$2,IF(OR(tblLines[[#This Row],[fund_received_date]]<tblLines[[#This Row],[payment_date]],tblLines[[#This Row],[fund_received_date]]<=tblLines[[#This Row],[Own_due]]),"confirmed",IF(tblLines[[#This Row],[fund_received_date]]>tblLines[[#This Row],[Own_due]],"impossible","possible")),IF(tblLines[[#This Row],[fund_received_date]]<=tblLines[[#This Row],[Own_due]],"possible","impossible"))),IF(AND(ISNUMBER(tblLines[[#This Row],[remitted_date]]),tblLines[[#This Row],[remitted_date]]>tblLines[[#This Row],[Own_due]]),"impossible","possible"))) -> impossible | AB9: =IF(OR(tblLines[[#This Row],[Flag_db]]=1,tblLines[[#This Row],[Own_due]]=""),"",_xlfn.MAXIFS(tblLines[Own_due],tblLines[employee_id],tblLines[[#This Row],[employee_id]],tblLines[payment_date],"<"&tblLines[[#This Row],[payment_date]],tblLines[Evidence_own],"confirmed")) -> 46223 | AC9: =IF(OR(tblLines[[#This Row],[Flag_db]]=1,tblLines[[#This Row],[Own_due]]=""),"",_xlfn.MAXIFS(tblLines[Own_due],tblLines[employee_id],tblLines[[#This Row],[employee_id]],tblLines[payment_date],"<"&tblLines[[#This Row],[payment_date]],tblLines[Evidence_own],"<>impossible")) -> 46223 | AD9: =IF(tblLines[[#This Row],[Own_due]]="","",IF(AND(ISNUMBER(tblLines[[#This Row],[Confirmed_latest]]),tblLines[[#This Row],[Confirmed_latest]]>tblLines[[#This Row],[Own_due]]),tblLines[[#This Row],[Confirmed_latest]],tblLines[[#This Row],[Own_due]])) -> 46238 | AE9: =IF(tblLines[[#This Row],[Own_due]]="",tblLines[[#This Row],[Own_pathway]],IF(AND(ISNUMBER(tblLines[[#This Row],[Confirmed_latest]]),tblLines[[#This Row],[Confirmed_latest]]>tblLines[[#This Row],[Own_due]]),"ITEM4_ALIGNED",tblLines[[#This Row],[Own_pathway]])) -> USUAL_7BD | AF9: =IF(tblLines[[#This Row],[Final_due]]="","",IF(AND(ISNUMBER(tblLines[[#This Row],[Possible_latest]]),tblLines[[#This Row],[Possible_latest]]>tblLines[[#This Row],[Final_due]]),tblLines[[#This Row],[Possible_latest]],"")) | AG9: =IF(tblLines[[#This Row],[Final_due]]="","",IF((tblLines[[#This Row],[Final_due]]>Summary!$B$6),1,0)) -> 0 | AH9: =IF(tblLines[[#This Row],[Flag_db]]=1,"DB",IF(tblLines[[#This Row],[Final_due]]="","",IF(tblLines[[#This Row],[sg_amount]]<=0,"NIL",IF(tblLines[[#This Row],[Settled]]<>"",IF(tblLines[[#This Row],[Settled]]<tblLines[[#This Row],[payment_date]],IF(tblLines[[#This Row],[Settled]]>=tblLines[[#This Row],[Earliest_prepay]],IF((tblLines[[#This Row],[Receipt_credit]]>=tblLines[[#This Row],[sg_amount]]),"A1",IF(tblLines[[#This Row],[Final_due]]>=Summary!$B$2,"A2",IF(OR((tblLines[[#This Row],[Final_due]]>Summary!$B$6),AND((tblLines[[#This Row],[Possible_item4]]<>""),Summary!$B$2<=tblLines[[#This Row],[Possible_item4]])),"A3","A4"))),IF(tblLines[[#This Row],[Final_due]]>=Summary!$B$2,"S1",IF(OR((tblLines[[#This Row],[Final_due]]>Summary!$B$6),AND((tblLines[[#This Row],[Possible_item4]]<>""),Summary!$B$2<=tblLines[[#This Row],[Possible_item4]])),"S2","S3"))),IF(AND((tblLines[[#This Row],[Possible_item4]]<>""),tblLines[[#This Row],[Final_due]]<tblLines[[#This Row],[Settled]],tblLines[[#This Row],[Settled]]<=tblLines[[#This Row],[Possible_item4]]),IF((tblLines[[#This Row],[Receipt_credit]]>=tblLines[[#This Row],[sg_amount]]),"B1",IF(Summary!$B$2<=tblLines[[#This Row],[Possible_item4]],"B2","B3")),IF(AND((tblLines[[#This Row],[Final_due]]>Summary!$B$6),tblLines[[#This Row],[Settled]]>tblLines[[#This Row],[Final_due]]),IF((tblLines[[#This Row],[Receipt_credit]]>=tblLines[[#This Row],[sg_amount]]),"C1","C2"),IF(tblLines[[#This Row],[Settled]]<=tblLines[[#This Row],[Final_due]],IF((tblLines[[#This Row],[Receipt_credit]]>=tblLines[[#This Row],[sg_amount]]),"D1",IF(OR((tblLines[[#This Row],[Final_due]]>Summary!$B$6),AND((tblLines[[#This Row],[Possible_item4]]<>""),Summary!$B$2<=tblLines[[#This Row],[Possible_item4]])),"D2",IF(tblLines[[#This Row],[Final_due]]<Summary!$B$2,"D3","D4"))),"E")))),IF(AND(tblLines[[#This Row],[Remit]]<>"",tblLines[[#This Row],[sg_amount]]-tblLines[[#This Row],[Credit]]<=0),IF(AND((tblLines[[#This Row],[Possible_item4]]<>""),tblLines[[#This Row],[Final_due]]<tblLines[[#This Row],[Remit]],tblLines[[#This Row],[Remit]]<=tblLines[[#This Row],[Possible_item4]]),"R1",IF(AND((tblLines[[#This Row],[Final_due]]>Summary!$B$6),tblLines[[#This Row],[Remit]]>tblLines[[#This Row],[Final_due]]),"R2",IF(tblLines[[#This Row],[Remit]]<=tblLines[[#This Row],[Final_due]],"R3","R4"))),IF(tblLines[[#This Row],[Final_due]]<Summary!$B$2,IF(OR((tblLines[[#This Row],[Final_due]]>Summary!$B$6),AND((tblLines[[#This Row],[Possible_item4]]<>""),Summary!$B$2<=tblLines[[#This Row],[Possible_item4]])),"N1","N2"),"N3")))))) -> E | AI9: =IF(tblLines[[#This Row],[Branch]]="","",INDEX(tblCodes[verdict],MATCH(tblLines[[#This Row],[Branch]],tblCodes[code],0))) -> LATE | AJ9: =IF(tblLines[[#This Row],[Branch]]="","",T(INDEX(tblCodes[unassessable],MATCH(tblLines[[#This Row],[Branch]],tblCodes[code],0)))) | AK9: =IF(tblLines[[#This Row],[Branch]]="",0,INDEX(tblCodes[exposed],MATCH(tblLines[[#This Row],[Branch]],tblCodes[code],0))) -> 1 | AL9: =IF(tblLines[[#This Row],[Branch]]="",0,INDEX(tblCodes[stale],MATCH(tblLines[[#This Row],[Branch]],tblCodes[code],0))) -> 0 | AM9: =IF(tblLines[[#This Row],[Branch]]="",0,INDEX(tblCodes[otrc],MATCH(tblLines[[#This Row],[Branch]],tblCodes[code],0))*tblLines[[#This Row],[Receipt_credit]]) -> 0 | AN9: =IF((tblLines[[#This Row],[Exposed]]=1),MAX(ROUND(tblLines[[#This Row],[sg_amount]],2)-tblLines[[#This Row],[OTRC]],0),"") -> 612 | AO9: =IF((tblLines[[#This Row],[Exposed]]=1),IF(AND(tblLines[[#This Row],[Settled]]<>"",tblLines[[#This Row],[Stale_prepay]]=0,tblLines[[#This Row],[Settled]]>tblLines[[#This Row],[Final_due]],OR(Summary!$B$3="",tblLines[[#This Row],[Settled]]<Summary!$B$3)),MIN(tblLines[[#This Row],[Receipt_credit]],tblLines[[#This Row],[Base_shortfall]]),0),"") -> 612 | AP9: =IF((tblLines[[#This Row],[Exposed]]=1),MAX(tblLines[[#This Row],[Base_shortfall]]-tblLines[[#This Row],[Offset_s18D]],0),"") -> 0 | AQ9: =IF((tblLines[[#This Row],[Exposed]]=1),IF(AND(tblLines[[#This Row],[Settled]]<>"",tblLines[[#This Row],[Stale_prepay]]=0,(tblLines[[#This Row],[Receipt_credit]]>=tblLines[[#This Row],[sg_amount]])),"fund receipt",IF(AND(tblLines[[#This Row],[Settled]]<>"",tblLines[[#This Row],[Stale_prepay]]=0),"as-at date (shortfall remains after part receipt)",IF(AND(OR(tblLines[[#This Row],[Settled]]<>"",tblLines[[#This Row],[Remit]]<>""),tblLines[[#This Row],[Stale_prepay]]=0),"as-at date (no fund receipt recorded)","as-at date (nothing applied to this payday)"))),"") -> fund receipt | AR9: =IF((tblLines[[#This Row],[Exposed]]=1),IF(AND(tblLines[[#This Row],[Settled]]<>"",tblLines[[#This Row],[Stale_prepay]]=0,(tblLines[[#This Row],[Receipt_credit]]>=tblLines[[#This Row],[sg_amount]])),tblLines[[#This Row],[Settled]],Summary!$B$2),"") -> 46240 | AS9: =IF((tblLines[[#This Row],[Exposed]]=1),MIN(IF(Summary!$B$3="",DATE(2030,12,31),Summary!$B$3-1),IF(AND(tblLines[[#This Row],[Settled]]<>"",tblLines[[#This Row],[Stale_prepay]]=0,(tblLines[[#This Row],[Receipt_credit]]>=tblLines[[#This Row],[sg_amount]]),tblLines[[#This Row],[Final_shortfall]]=0),tblLines[[#This Row],[Settled]],Summary!$B$2)),"") -> 46240 | AT9: =IF((tblLines[[#This Row],[Exposed]]=1),IF(tblLines[[#This Row],[Past_horizon]]=1,"",MAX(tblLines[[#This Row],[Outstanding_to]]-tblLines[[#This Row],[Final_due]],0)),"") -> 2 | AU9: =IF((tblLines[[#This Row],[Exposed]]=1),IF(tblLines[[#This Row],[NEC_end]]>tblLines[[#This Row],[Final_due]],tblLines[[#This Row],[Base_shortfall]]*(EXP(SUMPRODUCT((((((tblLines[[#This Row],[NEC_end]]+tblGic[to]-ABS(tblLines[[#This Row],[NEC_end]]-tblGic[to]))/2)-(((tblLines[[#This Row],[Final_due]]+1)+tblGic[from]+ABS((tblLines[[#This Row],[Final_due]]+1)-tblGic[from]))/2)+1)>0)*(((tblLines[[#This Row],[NEC_end]]+tblGic[to]-ABS(tblLines[[#This Row],[NEC_end]]-tblGic[to]))/2)-(((tblLines[[#This Row],[Final_due]]+1)+tblGic[from]+ABS((tblLines[[#This Row],[Final_due]]+1)-tblGic[from]))/2)+1))*LN(1+tblGic[annual_pct]/100/tblGic[divisor])))-1),0),"") -> 0.38335645 | AV9: =IF((tblLines[[#This Row],[Exposed]]=1),IF(tblLines[[#This Row],[NEC_end]]>Summary!$B$7,1,0),"") -> 0 | AW9: =IF((tblLines[[#This Row],[Exposed]]=1),ROUND(tblLines[[#This Row],[Final_shortfall]],2),"") -> 0 | AX9: =IF((tblLines[[#This Row],[Exposed]]=1),ROUND(tblLines[[#This Row],[NEC]],2),"") -> 0.38 | AY9: =IF((tblLines[[#This Row],[Exposed]]=1),0,"") -> 0 | AZ9: =IF((tblLines[[#This Row],[Exposed]]=1),ROUND(0.6*(tblLines[[#This Row],[Final_shortfall]]+tblLines[[#This Row],[NEC]]),2),"") -> 0.23 | BA9: =IF((tblLines[[#This Row],[Exposed]]=1),tblLines[[#This Row],[Shortfall_r]]+tblLines[[#This Row],[NEC_r]]+tblLines[[#This Row],[Uplift_best]],"") -> 0.38 | BB9: =IF((tblLines[[#This Row],[Exposed]]=1),tblLines[[#This Row],[Shortfall_r]]+tblLines[[#This Row],[NEC_r]]+tblLines[[#This Row],[Uplift_worst]],"") -> 0.61 | BC9: =IF(AND(tblLines[[#This Row],[Flag_db]]<>1,ISNUMBER(tblLines[[#This Row],[sg_amount]]),tblLines[[#This Row],[sg_amount]]>0,tblLines[[#This Row],[Cap]]>0,OR(ISNUMBER(tblLines[[#This Row],[fund_received_date]]),ISNUMBER(tblLines[[#This Row],[remitted_date]])),IF(ISNUMBER(tblLines[[#This Row],[fund_received_date]]),tblLines[[#This Row],[fund_received_date]],tblLines[[#This Row],[remitted_date]])<=DATE(2026,7,28)),1,0) -> 0 | BD9: =IF(tblLines[[#This Row],[Settled]]<>"",1,0) -> 1 | BE9: =IF(AND(tblLines[[#This Row],[Verdict]]<>"",tblLines[[#This Row],[Verdict]]<>"SKIPPED",ISNUMBER(tblLines[[#This Row],[sg_amount]]),tblLines[[#This Row],[sg_amount]]>0),1,0) -> 1 | BF9: =IF(COUNTIFS(tblLines[employee_id],tblLines[[#This Row],[employee_id]],tblLines[payment_date],tblLines[[#This Row],[payment_date]],tblLines[sg_amount],tblLines[[#This Row],[sg_amount]],tblLines[remitted_date],tblLines[[#This Row],[remitted_date]]&"",tblLines[fund_received_date],tblLines[[#This Row],[fund_received_date]]&"")>1,1,0) -> 0
A10: EMP002 | B10: 46226 | C10: 540 | D10: 46231 | G10: 46233 | H10: no | I10: no | K10: no | L10: =IF(OR(LOWER(TRIM(tblLines[[#This Row],[defined_benefit]]&""))={"1","t","true","y","yes"}),1,IF(OR(LOWER(TRIM(tblLines[[#This Row],[defined_benefit]]&""))={"","0","f","false","n","no"}),0,"")) -> 0 | M10: =IF(OR(LOWER(TRIM(tblLines[[#This Row],[out_of_cycle]]&""))={"1","t","true","y","yes"}),1,IF(OR(LOWER(TRIM(tblLines[[#This Row],[out_of_cycle]]&""))={"","0","f","false","n","no"}),0,"")) -> 0 | N10: =IF(OR(LOWER(TRIM(tblLines[[#This Row],[first_contribution_to_fund]]&""))={"1","t","true","y","yes"}),1,IF(OR(LOWER(TRIM(tblLines[[#This Row],[first_contribution_to_fund]]&""))={"","0","f","false","n","no"}),0,"")) -> 0 | O10: =TRIM(IF(OR(AND(tblLines[[#This Row],[payment_date]]<>"",NOT(ISNUMBER(tblLines[[#This Row],[payment_date]]))),AND(tblLines[[#This Row],[remitted_date]]<>"",NOT(ISNUMBER(tblLines[[#This Row],[remitted_date]]))),AND(tblLines[[#This Row],[fund_received_date]]<>"",NOT(ISNUMBER(tblLines[[#This Row],[fund_received_date]]))),AND(tblLines[[#This Row],[next_standard_payday]]<>"",NOT(ISNUMBER(tblLines[[#This Row],[next_standard_payday]])))),"date ","")&IF(NOT(ISNUMBER(tblLines[[#This Row],[payment_date]])),"payment_date ","")&IF(AND(ISNUMBER(tblLines[[#This Row],[payment_date]]),tblLines[[#This Row],[payment_date]]<DATE(2026,7,1)),"pre-1-Jul-2026 ","")&IF(OR(AND(tblLines[[#This Row],[sg_amount]]<>"",OR(NOT(ISNUMBER(tblLines[[#This Row],[sg_amount]])),tblLines[[#This Row],[sg_amount]]<0)),AND(tblLines[[#This Row],[remitted_amount]]<>"",OR(NOT(ISNUMBER(tblLines[[#This Row],[remitted_amount]])),tblLines[[#This Row],[remitted_amount]]<0)),AND(tblLines[[#This Row],[matched_amount]]<>"",OR(NOT(ISNUMBER(tblLines[[#This Row],[matched_amount]])),tblLines[[#This Row],[matched_amount]]<0))),"amount ","")&IF(NOT(ISNUMBER(tblLines[[#This Row],[sg_amount]])),"sg_amount ","")&IF(OR(tblLines[[#This Row],[Flag_ftf]]="",tblLines[[#This Row],[Flag_ooc]]="",tblLines[[#This Row],[Flag_db]]=""),"yes/no ","")&IF(AND(ISNUMBER(tblLines[[#This Row],[remitted_amount]]),ISNUMBER(tblLines[[#This Row],[sg_amount]]),tblLines[[#This Row],[remitted_amount]]>tblLines[[#This Row],[sg_amount]]),"remitted_amount>sg ","")&IF(AND(ISNUMBER(tblLines[[#This Row],[remitted_amount]]),NOT(ISNUMBER(tblLines[[#This Row],[remitted_date]]))),"remitted_amount-needs-date ","")&IF(AND(ISNUMBER(tblLines[[#This Row],[matched_amount]]),ISNUMBER(tblLines[[#This Row],[sg_amount]]),tblLines[[#This Row],[matched_amount]]>tblLines[[#This Row],[sg_amount]]),"matched_amount>sg ","")&IF(AND(ISNUMBER(tblLines[[#This Row],[matched_amount]]),ISNUMBER(tblLines[[#This Row],[remitted_amount]]),tblLines[[#This Row],[remitted_amount]]>tblLines[[#This Row],[matched_amount]]),"remitted_amount>matched ","")&IF(AND(ISNUMBER(tblLines[[#This Row],[matched_amount]]),ISNUMBER(tblLines[[#This Row],[sg_amount]]),tblLines[[#This Row],[matched_amount]]<tblLines[[#This Row],[sg_amount]],ISNUMBER(tblLines[[#This Row],[remitted_date]]),NOT(ISNUMBER(tblLines[[#This Row],[remitted_amount]]))),"partial-match-needs-remitted_amount ","")&IF(AND(ISNUMBER(tblLines[[#This Row],[fund_received_date]]),ISNUMBER(tblLines[[#This Row],[remitted_date]]),tblLines[[#This Row],[fund_received_date]]<tblLines[[#This Row],[remitted_date]]),"receipt-before-remittance ","")&IF(AND(tblLines[[#This Row],[Flag_ooc]]=1,NOT(ISNUMBER(tblLines[[#This Row],[next_standard_payday]]))),"out_of_cycle-needs-next_standard_payday ","")&IF(AND(tblLines[[#This Row],[Flag_ooc]]=1,ISNUMBER(tblLines[[#This Row],[next_standard_payday]]),ISNUMBER(tblLines[[#This Row],[payment_date]]),tblLines[[#This Row],[next_standard_payday]]<=tblLines[[#This Row],[payment_date]]),"next_standard_payday-not-after-payday ","")) | P10: =IF(OR(_xlfn.ISFORMULA(tblLines[[#This Row],[employee_id]]),_xlfn.ISFORMULA(tblLines[[#This Row],[payment_date]]),_xlfn.ISFORMULA(tblLines[[#This Row],[sg_amount]]),_xlfn.ISFORMULA(tblLines[[#This Row],[remitted_date]]),_xlfn.ISFORMULA(tblLines[[#This Row],[remitted_amount]]),_xlfn.ISFORMULA(tblLines[[#This Row],[matched_amount]]),_xlfn.ISFORMULA(tblLines[[#This Row],[fund_received_date]]),_xlfn.ISFORMULA(tblLines[[#This Row],[first_contribution_to_fund]]),_xlfn.ISFORMULA(tblLines[[#This Row],[out_of_cycle]]),_xlfn.ISFORMULA(tblLines[[#This Row],[next_standard_payday]]),_xlfn.ISFORMULA(tblLines[[#This Row],[defined_benefit]])),1,0) -> 0 | Q10: =IF(ISNUMBER(tblLines[[#This Row],[matched_amount]]),tblLines[[#This Row],[matched_amount]],IF(ISNUMBER(tblLines[[#This Row],[remitted_amount]]),tblLines[[#This Row],[remitted_amount]],tblLines[[#This Row],[sg_amount]])) -> 540 | R10: =IF(AND(tblLines[[#This Row],[Flag_ooc]]=1,ISNUMBER(tblLines[[#This Row],[next_standard_payday]])),WORKDAY.INTL(tblLines[[#This Row],[next_standard_payday]],7,1,tblHolidays[date]),"") | S10: =IF(tblLines[[#This Row],[Flag_ftf]]=1,WORKDAY.INTL(tblLines[[#This Row],[payment_date]],20,1,tblHolidays[date]),"") | T10: =IF(OR(tblLines[[#This Row],[Flag_db]]=1,NOT(ISNUMBER(tblLines[[#This Row],[payment_date]]))),"",IF(OR(tblLines[[#This Row],[Flag_ooc]]=1,tblLines[[#This Row],[Flag_ftf]]=1),MAX(tblLines[[#This Row],[Due_ooc]],tblLines[[#This Row],[Due_ftf]]),WORKDAY.INTL(tblLines[[#This Row],[payment_date]],7,1,tblHolidays[date]))) -> 46238 | U10: =IF(tblLines[[#This Row],[Flag_db]]=1,"SKIP_DB",IF(tblLines[[#This Row],[Flag_ooc]]=1,IF(AND(tblLines[[#This Row],[Flag_ftf]]=1,tblLines[[#This Row],[Due_ftf]]>tblLines[[#This Row],[Due_ooc]]),"EXTENDED_20BD","OUT_OF_CYCLE"),IF(tblLines[[#This Row],[Flag_ftf]]=1,"EXTENDED_20BD","USUAL_7BD"))) -> USUAL_7BD | V10: =IF(ISNUMBER(tblLines[[#This Row],[payment_date]]),EDATE(tblLines[[#This Row],[payment_date]]-1,-12)+1,"") -> 45861 | W10: =IF(AND(ISNUMBER(tblLines[[#This Row],[fund_received_date]]),tblLines[[#This Row],[fund_received_date]]<=Summary!$B$2),tblLines[[#This Row],[fund_received_date]],"") -> 46233 | X10: =IF(AND(ISNUMBER(tblLines[[#This Row],[remitted_date]]),tblLines[[#This Row],[remitted_date]]<=Summary!$B$2),tblLines[[#This Row],[remitted_date]],"") -> 46231 | Y10: =IF(tblLines[[#This Row],[Settled]]<>"",MIN(ROUND(tblLines[[#This Row],[Cap]],2),ROUND(tblLines[[#This Row],[sg_amount]],2)),0) -> 540 | Z10: =IF(ISNUMBER(tblLines[[#This Row],[remitted_amount]]),IF(tblLines[[#This Row],[Remit]]<>"",MIN(ROUND(tblLines[[#This Row],[remitted_amount]],2),ROUND(tblLines[[#This Row],[sg_amount]],2)),0),IF(tblLines[[#This Row],[Remit]]<>"",ROUND(tblLines[[#This Row],[sg_amount]],2),0)) -> 540 | AA10: =IF(OR(tblLines[[#This Row],[Own_due]]="",tblLines[[#This Row],[sg_amount]]<=0,tblLines[[#This Row],[Flag_db]]=1,tblLines[[#This Row],[Cap]]<=0),"impossible",IF(ISNUMBER(tblLines[[#This Row],[fund_received_date]]),IF(tblLines[[#This Row],[fund_received_date]]<tblLines[[#This Row],[Earliest_prepay]],"impossible",IF(tblLines[[#This Row],[fund_received_date]]<=Summary!$B$2,IF(OR(tblLines[[#This Row],[fund_received_date]]<tblLines[[#This Row],[payment_date]],tblLines[[#This Row],[fund_received_date]]<=tblLines[[#This Row],[Own_due]]),"confirmed",IF(tblLines[[#This Row],[fund_received_date]]>tblLines[[#This Row],[Own_due]],"impossible","possible")),IF(tblLines[[#This Row],[fund_received_date]]<=tblLines[[#This Row],[Own_due]],"possible","impossible"))),IF(AND(ISNUMBER(tblLines[[#This Row],[remitted_date]]),tblLines[[#This Row],[remitted_date]]>tblLines[[#This Row],[Own_due]]),"impossible","possible"))) -> confirmed | AB10: =IF(OR(tblLines[[#This Row],[Flag_db]]=1,tblLines[[#This Row],[Own_due]]=""),"",_xlfn.MAXIFS(tblLines[Own_due],tblLines[employee_id],tblLines[[#This Row],[employee_id]],tblLines[payment_date],"<"&tblLines[[#This Row],[payment_date]],tblLines[Evidence_own],"confirmed")) -> 0 | AC10: =IF(OR(tblLines[[#This Row],[Flag_db]]=1,tblLines[[#This Row],[Own_due]]=""),"",_xlfn.MAXIFS(tblLines[Own_due],tblLines[employee_id],tblLines[[#This Row],[employee_id]],tblLines[payment_date],"<"&tblLines[[#This Row],[payment_date]],tblLines[Evidence_own],"<>impossible")) -> 0 | AD10: =IF(tblLines[[#This Row],[Own_due]]="","",IF(AND(ISNUMBER(tblLines[[#This Row],[Confirmed_latest]]),tblLines[[#This Row],[Confirmed_latest]]>tblLines[[#This Row],[Own_due]]),tblLines[[#This Row],[Confirmed_latest]],tblLines[[#This Row],[Own_due]])) -> 46238 | AE10: =IF(tblLines[[#This Row],[Own_due]]="",tblLines[[#This Row],[Own_pathway]],IF(AND(ISNUMBER(tblLines[[#This Row],[Confirmed_latest]]),tblLines[[#This Row],[Confirmed_latest]]>tblLines[[#This Row],[Own_due]]),"ITEM4_ALIGNED",tblLines[[#This Row],[Own_pathway]])) -> USUAL_7BD | AF10: =IF(tblLines[[#This Row],[Final_due]]="","",IF(AND(ISNUMBER(tblLines[[#This Row],[Possible_latest]]),tblLines[[#This Row],[Possible_latest]]>tblLines[[#This Row],[Final_due]]),tblLines[[#This Row],[Possible_latest]],"")) | AG10: =IF(tblLines[[#This Row],[Final_due]]="","",IF((tblLines[[#This Row],[Final_due]]>Summary!$B$6),1,0)) -> 0 | AH10: =IF(tblLines[[#This Row],[Flag_db]]=1,"DB",IF(tblLines[[#This Row],[Final_due]]="","",IF(tblLines[[#This Row],[sg_amount]]<=0,"NIL",IF(tblLines[[#This Row],[Settled]]<>"",IF(tblLines[[#This Row],[Settled]]<tblLines[[#This Row],[payment_date]],IF(tblLines[[#This Row],[Settled]]>=tblLines[[#This Row],[Earliest_prepay]],IF((tblLines[[#This Row],[Receipt_credit]]>=tblLines[[#This Row],[sg_amount]]),"A1",IF(tblLines[[#This Row],[Final_due]]>=Summary!$B$2,"A2",IF(OR((tblLines[[#This Row],[Final_due]]>Summary!$B$6),AND((tblLines[[#This Row],[Possible_item4]]<>""),Summary!$B$2<=tblLines[[#This Row],[Possible_item4]])),"A3","A4"))),IF(tblLines[[#This Row],[Final_due]]>=Summary!$B$2,"S1",IF(OR((tblLines[[#This Row],[Final_due]]>Summary!$B$6),AND((tblLines[[#This Row],[Possible_item4]]<>""),Summary!$B$2<=tblLines[[#This Row],[Possible_item4]])),"S2","S3"))),IF(AND((tblLines[[#This Row],[Possible_item4]]<>""),tblLines[[#This Row],[Final_due]]<tblLines[[#This Row],[Settled]],tblLines[[#This Row],[Settled]]<=tblLines[[#This Row],[Possible_item4]]),IF((tblLines[[#This Row],[Receipt_credit]]>=tblLines[[#This Row],[sg_amount]]),"B1",IF(Summary!$B$2<=tblLines[[#This Row],[Possible_item4]],"B2","B3")),IF(AND((tblLines[[#This Row],[Final_due]]>Summary!$B$6),tblLines[[#This Row],[Settled]]>tblLines[[#This Row],[Final_due]]),IF((tblLines[[#This Row],[Receipt_credit]]>=tblLines[[#This Row],[sg_amount]]),"C1","C2"),IF(tblLines[[#This Row],[Settled]]<=tblLines[[#This Row],[Final_due]],IF((tblLines[[#This Row],[Receipt_credit]]>=tblLines[[#This Row],[sg_amount]]),"D1",IF(OR((tblLines[[#This Row],[Final_due]]>Summary!$B$6),AND((tblLines[[#This Row],[Possible_item4]]<>""),Summary!$B$2<=tblLines[[#This Row],[Possible_item4]])),"D2",IF(tblLines[[#This Row],[Final_due]]<Summary!$B$2,"D3","D4"))),"E")))),IF(AND(tblLines[[#This Row],[Remit]]<>"",tblLines[[#This Row],[sg_amount]]-tblLines[[#This Row],[Credit]]<=0),IF(AND((tblLines[[#This Row],[Possible_item4]]<>""),tblLines[[#This Row],[Final_due]]<tblLines[[#This Row],[Remit]],tblLines[[#This Row],[Remit]]<=tblLines[[#This Row],[Possible_item4]]),"R1",IF(AND((tblLines[[#This Row],[Final_due]]>Summary!$B$6),tblLines[[#This Row],[Remit]]>tblLines[[#This Row],[Final_due]]),"R2",IF(tblLines[[#This Row],[Remit]]<=tblLines[[#This Row],[Final_due]],"R3","R4"))),IF(tblLines[[#This Row],[Final_due]]<Summary!$B$2,IF(OR((tblLines[[#This Row],[Final_due]]>Summary!$B$6),AND((tblLines[[#This Row],[Possible_item4]]<>""),Summary!$B$2<=tblLines[[#This Row],[Possible_item4]])),"N1","N2"),"N3")))))) -> D1 | AI10: =IF(tblLines[[#This Row],[Branch]]="","",INDEX(tblCodes[verdict],MATCH(tblLines[[#This Row],[Branch]],tblCodes[code],0))) -> ON_TIME | AJ10: =IF(tblLines[[#This Row],[Branch]]="","",T(INDEX(tblCodes[unassessable],MATCH(tblLines[[#This Row],[Branch]],tblCodes[code],0)))) | AK10: =IF(tblLines[[#This Row],[Branch]]="",0,INDEX(tblCodes[exposed],MATCH(tblLines[[#This Row],[Branch]],tblCodes[code],0))) -> 0 | AL10: =IF(tblLines[[#This Row],[Branch]]="",0,INDEX(tblCodes[stale],MATCH(tblLines[[#This Row],[Branch]],tblCodes[code],0))) -> 0 | AM10: =IF(tblLines[[#This Row],[Branch]]="",0,INDEX(tblCodes[otrc],MATCH(tblLines[[#This Row],[Branch]],tblCodes[code],0))*tblLines[[#This Row],[Receipt_credit]]) -> 540 | AN10: =IF((tblLines[[#This Row],[Exposed]]=1),MAX(ROUND(tblLines[[#This Row],[sg_amount]],2)-tblLines[[#This Row],[OTRC]],0),"") | AO10: =IF((tblLines[[#This Row],[Exposed]]=1),IF(AND(tblLines[[#This Row],[Settled]]<>"",tblLines[[#This Row],[Stale_prepay]]=0,tblLines[[#This Row],[Settled]]>tblLines[[#This Row],[Final_due]],OR(Summary!$B$3="",tblLines[[#This Row],[Settled]]<Summary!$B$3)),MIN(tblLines[[#This Row],[Receipt_credit]],tblLines[[#This Row],[Base_shortfall]]),0),"") | AP10: =IF((tblLines[[#This Row],[Exposed]]=1),MAX(tblLines[[#This Row],[Base_shortfall]]-tblLines[[#This Row],[Offset_s18D]],0),"") | AQ10: =IF((tblLines[[#This Row],[Exposed]]=1),IF(AND(tblLines[[#This Row],[Settled]]<>"",tblLines[[#This Row],[Stale_prepay]]=0,(tblLines[[#This Row],[Receipt_credit]]>=tblLines[[#This Row],[sg_amount]])),"fund receipt",IF(AND(tblLines[[#This Row],[Settled]]<>"",tblLines[[#This Row],[Stale_prepay]]=0),"as-at date (shortfall remains after part receipt)",IF(AND(OR(tblLines[[#This Row],[Settled]]<>"",tblLines[[#This Row],[Remit]]<>""),tblLines[[#This Row],[Stale_prepay]]=0),"as-at date (no fund receipt recorded)","as-at date (nothing applied to this payday)"))),"") | AR10: =IF((tblLines[[#This Row],[Exposed]]=1),IF(AND(tblLines[[#This Row],[Settled]]<>"",tblLines[[#This Row],[Stale_prepay]]=0,(tblLines[[#This Row],[Receipt_credit]]>=tblLines[[#This Row],[sg_amount]])),tblLines[[#This Row],[Settled]],Summary!$B$2),"") | AS10: =IF((tblLines[[#This Row],[Exposed]]=1),MIN(IF(Summary!$B$3="",DATE(2030,12,31),Summary!$B$3-1),IF(AND(tblLines[[#This Row],[Settled]]<>"",tblLines[[#This Row],[Stale_prepay]]=0,(tblLines[[#This Row],[Receipt_credit]]>=tblLines[[#This Row],[sg_amount]]),tblLines[[#This Row],[Final_shortfall]]=0),tblLines[[#This Row],[Settled]],Summary!$B$2)),"") | AT10: =IF((tblLines[[#This Row],[Exposed]]=1),IF(tblLines[[#This Row],[Past_horizon]]=1,"",MAX(tblLines[[#This Row],[Outstanding_to]]-tblLines[[#This Row],[Final_due]],0)),"") | AU10: =IF((tblLines[[#This Row],[Exposed]]=1),IF(tblLines[[#This Row],[NEC_end]]>tblLines[[#This Row],[Final_due]],tblLines[[#This Row],[Base_shortfall]]*(EXP(SUMPRODUCT((((((tblLines[[#This Row],[NEC_end]]+tblGic[to]-ABS(tblLines[[#This Row],[NEC_end]]-tblGic[to]))/2)-(((tblLines[[#This Row],[Final_due]]+1)+tblGic[from]+ABS((tblLines[[#This Row],[Final_due]]+1)-tblGic[from]))/2)+1)>0)*(((tblLines[[#This Row],[NEC_end]]+tblGic[to]-ABS(tblLines[[#This Row],[NEC_end]]-tblGic[to]))/2)-(((tblLines[[#This Row],[Final_due]]+1)+tblGic[from]+ABS((tblLines[[#This Row],[Final_due]]+1)-tblGic[from]))/2)+1))*LN(1+tblGic[annual_pct]/100/tblGic[divisor])))-1),0),"") | AV10: =IF((tblLines[[#This Row],[Exposed]]=1),IF(tblLines[[#This Row],[NEC_end]]>Summary!$B$7,1,0),"") | AW10: =IF((tblLines[[#This Row],[Exposed]]=1),ROUND(tblLines[[#This Row],[Final_shortfall]],2),"") | AX10: =IF((tblLines[[#This Row],[Exposed]]=1),ROUND(tblLines[[#This Row],[NEC]],2),"") | AY10: =IF((tblLines[[#This Row],[Exposed]]=1),0,"") | AZ10: =IF((tblLines[[#This Row],[Exposed]]=1),ROUND(0.6*(tblLines[[#This Row],[Final_shortfall]]+tblLines[[#This Row],[NEC]]),2),"") | BA10: =IF((tblLines[[#This Row],[Exposed]]=1),tblLines[[#This Row],[Shortfall_r]]+tblLines[[#This Row],[NEC_r]]+tblLines[[#This Row],[Uplift_best]],"") | BB10: =IF((tblLines[[#This Row],[Exposed]]=1),tblLines[[#This Row],[Shortfall_r]]+tblLines[[#This Row],[NEC_r]]+tblLines[[#This Row],[Uplift_worst]],"") | BC10: =IF(AND(tblLines[[#This Row],[Flag_db]]<>1,ISNUMBER(tblLines[[#This Row],[sg_amount]]),tblLines[[#This Row],[sg_amount]]>0,tblLines[[#This Row],[Cap]]>0,OR(ISNUMBER(tblLines[[#This Row],[fund_received_date]]),ISNUMBER(tblLines[[#This Row],[remitted_date]])),IF(ISNUMBER(tblLines[[#This Row],[fund_received_date]]),tblLines[[#This Row],[fund_received_date]],tblLines[[#This Row],[remitted_date]])<=DATE(2026,7,28)),1,0) -> 0 | BD10: =IF(tblLines[[#This Row],[Settled]]<>"",1,0) -> 1 | BE10: =IF(AND(tblLines[[#This Row],[Verdict]]<>"",tblLines[[#This Row],[Verdict]]<>"SKIPPED",ISNUMBER(tblLines[[#This Row],[sg_amount]]),tblLines[[#This Row],[sg_amount]]>0),1,0) -> 1 | BF10: =IF(COUNTIFS(tblLines[employee_id],tblLines[[#This Row],[employee_id]],tblLines[payment_date],tblLines[[#This Row],[payment_date]],tblLines[sg_amount],tblLines[[#This Row],[sg_amount]],tblLines[remitted_date],tblLines[[#This Row],[remitted_date]]&"",tblLines[fund_received_date],tblLines[[#This Row],[fund_received_date]]&"")>1,1,0) -> 0
A11: EMP005 | B11: 46226 | C11: 450 | D11: 46239 | G11: 46240 | H11: no | I11: no | K11: no | L11: =IF(OR(LOWER(TRIM(tblLines[[#This Row],[defined_benefit]]&""))={"1","t","true","y","yes"}),1,IF(OR(LOWER(TRIM(tblLines[[#This Row],[defined_benefit]]&""))={"","0","f","false","n","no"}),0,"")) -> 0 | M11: =IF(OR(LOWER(TRIM(tblLines[[#This Row],[out_of_cycle]]&""))={"1","t","true","y","yes"}),1,IF(OR(LOWER(TRIM(tblLines[[#This Row],[out_of_cycle]]&""))={"","0","f","false","n","no"}),0,"")) -> 0 | N11: =IF(OR(LOWER(TRIM(tblLines[[#This Row],[first_contribution_to_fund]]&""))={"1","t","true","y","yes"}),1,IF(OR(LOWER(TRIM(tblLines[[#This Row],[first_contribution_to_fund]]&""))={"","0","f","false","n","no"}),0,"")) -> 0 | O11: =TRIM(IF(OR(AND(tblLines[[#This Row],[payment_date]]<>"",NOT(ISNUMBER(tblLines[[#This Row],[payment_date]]))),AND(tblLines[[#This Row],[remitted_date]]<>"",NOT(ISNUMBER(tblLines[[#This Row],[remitted_date]]))),AND(tblLines[[#This Row],[fund_received_date]]<>"",NOT(ISNUMBER(tblLines[[#This Row],[fund_received_date]]))),AND(tblLines[[#This Row],[next_standard_payday]]<>"",NOT(ISNUMBER(tblLines[[#This Row],[next_standard_payday]])))),"date ","")&IF(NOT(ISNUMBER(tblLines[[#This Row],[payment_date]])),"payment_date ","")&IF(AND(ISNUMBER(tblLines[[#This Row],[payment_date]]),tblLines[[#This Row],[payment_date]]<DATE(2026,7,1)),"pre-1-Jul-2026 ","")&IF(OR(AND(tblLines[[#This Row],[sg_amount]]<>"",OR(NOT(ISNUMBER(tblLines[[#This Row],[sg_amount]])),tblLines[[#This Row],[sg_amount]]<0)),AND(tblLines[[#This Row],[remitted_amount]]<>"",OR(NOT(ISNUMBER(tblLines[[#This Row],[remitted_amount]])),tblLines[[#This Row],[remitted_amount]]<0)),AND(tblLines[[#This Row],[matched_amount]]<>"",OR(NOT(ISNUMBER(tblLines[[#This Row],[matched_amount]])),tblLines[[#This Row],[matched_amount]]<0))),"amount ","")&IF(NOT(ISNUMBER(tblLines[[#This Row],[sg_amount]])),"sg_amount ","")&IF(OR(tblLines[[#This Row],[Flag_ftf]]="",tblLines[[#This Row],[Flag_ooc]]="",tblLines[[#This Row],[Flag_db]]=""),"yes/no ","")&IF(AND(ISNUMBER(tblLines[[#This Row],[remitted_amount]]),ISNUMBER(tblLines[[#This Row],[sg_amount]]),tblLines[[#This Row],[remitted_amount]]>tblLines[[#This Row],[sg_amount]]),"remitted_amount>sg ","")&IF(AND(ISNUMBER(tblLines[[#This Row],[remitted_amount]]),NOT(ISNUMBER(tblLines[[#This Row],[remitted_date]]))),"remitted_amount-needs-date ","")&IF(AND(ISNUMBER(tblLines[[#This Row],[matched_amount]]),ISNUMBER(tblLines[[#This Row],[sg_amount]]),tblLines[[#This Row],[matched_amount]]>tblLines[[#This Row],[sg_amount]]),"matched_amount>sg ","")&IF(AND(ISNUMBER(tblLines[[#This Row],[matched_amount]]),ISNUMBER(tblLines[[#This Row],[remitted_amount]]),tblLines[[#This Row],[remitted_amount]]>tblLines[[#This Row],[matched_amount]]),"remitted_amount>matched ","")&IF(AND(ISNUMBER(tblLines[[#This Row],[matched_amount]]),ISNUMBER(tblLines[[#This Row],[sg_amount]]),tblLines[[#This Row],[matched_amount]]<tblLines[[#This Row],[sg_amount]],ISNUMBER(tblLines[[#This Row],[remitted_date]]),NOT(ISNUMBER(tblLines[[#This Row],[remitted_amount]]))),"partial-match-needs-remitted_amount ","")&IF(AND(ISNUMBER(tblLines[[#This Row],[fund_received_date]]),ISNUMBER(tblLines[[#This Row],[remitted_date]]),tblLines[[#This Row],[fund_received_date]]<tblLines[[#This Row],[remitted_date]]),"receipt-before-remittance ","")&IF(AND(tblLines[[#This Row],[Flag_ooc]]=1,NOT(ISNUMBER(tblLines[[#This Row],[next_standard_payday]]))),"out_of_cycle-needs-next_standard_payday ","")&IF(AND(tblLines[[#This Row],[Flag_ooc]]=1,ISNUMBER(tblLines[[#This Row],[next_standard_payday]]),ISNUMBER(tblLines[[#This Row],[payment_date]]),tblLines[[#This Row],[next_standard_payday]]<=tblLines[[#This Row],[payment_date]]),"next_standard_payday-not-after-payday ","")) | P11: =IF(OR(_xlfn.ISFORMULA(tblLines[[#This Row],[employee_id]]),_xlfn.ISFORMULA(tblLines[[#This Row],[payment_date]]),_xlfn.ISFORMULA(tblLines[[#This Row],[sg_amount]]),_xlfn.ISFORMULA(tblLines[[#This Row],[remitted_date]]),_xlfn.ISFORMULA(tblLines[[#This Row],[remitted_amount]]),_xlfn.ISFORMULA(tblLines[[#This Row],[matched_amount]]),_xlfn.ISFORMULA(tblLines[[#This Row],[fund_received_date]]),_xlfn.ISFORMULA(tblLines[[#This Row],[first_contribution_to_fund]]),_xlfn.ISFORMULA(tblLines[[#This Row],[out_of_cycle]]),_xlfn.ISFORMULA(tblLines[[#This Row],[next_standard_payday]]),_xlfn.ISFORMULA(tblLines[[#This Row],[defined_benefit]])),1,0) -> 0 | Q11: =IF(ISNUMBER(tblLines[[#This Row],[matched_amount]]),tblLines[[#This Row],[matched_amount]],IF(ISNUMBER(tblLines[[#This Row],[remitted_amount]]),tblLines[[#This Row],[remitted_amount]],tblLines[[#This Row],[sg_amount]])) -> 450 | R11: =IF(AND(tblLines[[#This Row],[Flag_ooc]]=1,ISNUMBER(tblLines[[#This Row],[next_standard_payday]])),WORKDAY.INTL(tblLines[[#This Row],[next_standard_payday]],7,1,tblHolidays[date]),"") | S11: =IF(tblLines[[#This Row],[Flag_ftf]]=1,WORKDAY.INTL(tblLines[[#This Row],[payment_date]],20,1,tblHolidays[date]),"") | T11: =IF(OR(tblLines[[#This Row],[Flag_db]]=1,NOT(ISNUMBER(tblLines[[#This Row],[payment_date]]))),"",IF(OR(tblLines[[#This Row],[Flag_ooc]]=1,tblLines[[#This Row],[Flag_ftf]]=1),MAX(tblLines[[#This Row],[Due_ooc]],tblLines[[#This Row],[Due_ftf]]),WORKDAY.INTL(tblLines[[#This Row],[payment_date]],7,1,tblHolidays[date]))) -> 46238 | U11: =IF(tblLines[[#This Row],[Flag_db]]=1,"SKIP_DB",IF(tblLines[[#This Row],[Flag_ooc]]=1,IF(AND(tblLines[[#This Row],[Flag_ftf]]=1,tblLines[[#This Row],[Due_ftf]]>tblLines[[#This Row],[Due_ooc]]),"EXTENDED_20BD","OUT_OF_CYCLE"),IF(tblLines[[#This Row],[Flag_ftf]]=1,"EXTENDED_20BD","USUAL_7BD"))) -> USUAL_7BD | V11: =IF(ISNUMBER(tblLines[[#This Row],[payment_date]]),EDATE(tblLines[[#This Row],[payment_date]]-1,-12)+1,"") -> 45861 | W11: =IF(AND(ISNUMBER(tblLines[[#This Row],[fund_received_date]]),tblLines[[#This Row],[fund_received_date]]<=Summary!$B$2),tblLines[[#This Row],[fund_received_date]],"") -> 46240 | X11: =IF(AND(ISNUMBER(tblLines[[#This Row],[remitted_date]]),tblLines[[#This Row],[remitted_date]]<=Summary!$B$2),tblLines[[#This Row],[remitted_date]],"") -> 46239 | Y11: =IF(tblLines[[#This Row],[Settled]]<>"",MIN(ROUND(tblLines[[#This Row],[Cap]],2),ROUND(tblLines[[#This Row],[sg_amount]],2)),0) -> 450 | Z11: =IF(ISNUMBER(tblLines[[#This Row],[remitted_amount]]),IF(tblLines[[#This Row],[Remit]]<>"",MIN(ROUND(tblLines[[#This Row],[remitted_amount]],2),ROUND(tblLines[[#This Row],[sg_amount]],2)),0),IF(tblLines[[#This Row],[Remit]]<>"",ROUND(tblLines[[#This Row],[sg_amount]],2),0)) -> 450 | AA11: =IF(OR(tblLines[[#This Row],[Own_due]]="",tblLines[[#This Row],[sg_amount]]<=0,tblLines[[#This Row],[Flag_db]]=1,tblLines[[#This Row],[Cap]]<=0),"impossible",IF(ISNUMBER(tblLines[[#This Row],[fund_received_date]]),IF(tblLines[[#This Row],[fund_received_date]]<tblLines[[#This Row],[Earliest_prepay]],"impossible",IF(tblLines[[#This Row],[fund_received_date]]<=Summary!$B$2,IF(OR(tblLines[[#This Row],[fund_received_date]]<tblLines[[#This Row],[payment_date]],tblLines[[#This Row],[fund_received_date]]<=tblLines[[#This Row],[Own_due]]),"confirmed",IF(tblLines[[#This Row],[fund_received_date]]>tblLines[[#This Row],[Own_due]],"impossible","possible")),IF(tblLines[[#This Row],[fund_received_date]]<=tblLines[[#This Row],[Own_due]],"possible","impossible"))),IF(AND(ISNUMBER(tblLines[[#This Row],[remitted_date]]),tblLines[[#This Row],[remitted_date]]>tblLines[[#This Row],[Own_due]]),"impossible","possible"))) -> impossible | AB11: =IF(OR(tblLines[[#This Row],[Flag_db]]=1,tblLines[[#This Row],[Own_due]]=""),"",_xlfn.MAXIFS(tblLines[Own_due],tblLines[employee_id],tblLines[[#This Row],[employee_id]],tblLines[payment_date],"<"&tblLines[[#This Row],[payment_date]],tblLines[Evidence_own],"confirmed")) -> 46241 | AC11: =IF(OR(tblLines[[#This Row],[Flag_db]]=1,tblLines[[#This Row],[Own_due]]=""),"",_xlfn.MAXIFS(tblLines[Own_due],tblLines[employee_id],tblLines[[#This Row],[employee_id]],tblLines[payment_date],"<"&tblLines[[#This Row],[payment_date]],tblLines[Evidence_own],"<>impossible")) -> 46241 | AD11: =IF(tblLines[[#This Row],[Own_due]]="","",IF(AND(ISNUMBER(tblLines[[#This Row],[Confirmed_latest]]),tblLines[[#This Row],[Confirmed_latest]]>tblLines[[#This Row],[Own_due]]),tblLines[[#This Row],[Confirmed_latest]],tblLines[[#This Row],[Own_due]])) -> 46241 | AE11: =IF(tblLines[[#This Row],[Own_due]]="",tblLines[[#This Row],[Own_pathway]],IF(AND(ISNUMBER(tblLines[[#This Row],[Confirmed_latest]]),tblLines[[#This Row],[Confirmed_latest]]>tblLines[[#This Row],[Own_due]]),"ITEM4_ALIGNED",tblLines[[#This Row],[Own_pathway]])) -> ITEM4_ALIGNED | AF11: =IF(tblLines[[#This Row],[Final_due]]="","",IF(AND(ISNUMBER(tblLines[[#This Row],[Possible_latest]]),tblLines[[#This Row],[Possible_latest]]>tblLines[[#This Row],[Final_due]]),tblLines[[#This Row],[Possible_latest]],"")) | AG11: =IF(tblLines[[#This Row],[Final_due]]="","",IF((tblLines[[#This Row],[Final_due]]>Summary!$B$6),1,0)) -> 0 | AH11: =IF(tblLines[[#This Row],[Flag_db]]=1,"DB",IF(tblLines[[#This Row],[Final_due]]="","",IF(tblLines[[#This Row],[sg_amount]]<=0,"NIL",IF(tblLines[[#This Row],[Settled]]<>"",IF(tblLines[[#This Row],[Settled]]<tblLines[[#This Row],[payment_date]],IF(tblLines[[#This Row],[Settled]]>=tblLines[[#This Row],[Earliest_prepay]],IF((tblLines[[#This Row],[Receipt_credit]]>=tblLines[[#This Row],[sg_amount]]),"A1",IF(tblLines[[#This Row],[Final_due]]>=Summary!$B$2,"A2",IF(OR((tblLines[[#This Row],[Final_due]]>Summary!$B$6),AND((tblLines[[#This Row],[Possible_item4]]<>""),Summary!$B$2<=tblLines[[#This Row],[Possible_item4]])),"A3","A4"))),IF(tblLines[[#This Row],[Final_due]]>=Summary!$B$2,"S1",IF(OR((tblLines[[#This Row],[Final_due]]>Summary!$B$6),AND((tblLines[[#This Row],[Possible_item4]]<>""),Summary!$B$2<=tblLines[[#This Row],[Possible_item4]])),"S2","S3"))),IF(AND((tblLines[[#This Row],[Possible_item4]]<>""),tblLines[[#This Row],[Final_due]]<tblLines[[#This Row],[Settled]],tblLines[[#This Row],[Settled]]<=tblLines[[#This Row],[Possible_item4]]),IF((tblLines[[#This Row],[Receipt_credit]]>=tblLines[[#This Row],[sg_amount]]),"B1",IF(Summary!$B$2<=tblLines[[#This Row],[Possible_item4]],"B2","B3")),IF(AND((tblLines[[#This Row],[Final_due]]>Summary!$B$6),tblLines[[#This Row],[Settled]]>tblLines[[#This Row],[Final_due]]),IF((tblLines[[#This Row],[Receipt_credit]]>=tblLines[[#This Row],[sg_amount]]),"C1","C2"),IF(tblLines[[#This Row],[Settled]]<=tblLines[[#This Row],[Final_due]],IF((tblLines[[#This Row],[Receipt_credit]]>=tblLines[[#This Row],[sg_amount]]),"D1",IF(OR((tblLines[[#This Row],[Final_due]]>Summary!$B$6),AND((tblLines[[#This Row],[Possible_item4]]<>""),Summary!$B$2<=tblLines[[#This Row],[Possible_item4]])),"D2",IF(tblLines[[#This Row],[Final_due]]<Summary!$B$2,"D3","D4"))),"E")))),IF(AND(tblLines[[#This Row],[Remit]]<>"",tblLines[[#This Row],[sg_amount]]-tblLines[[#This Row],[Credit]]<=0),IF(AND((tblLines[[#This Row],[Possible_item4]]<>""),tblLines[[#This Row],[Final_due]]<tblLines[[#This Row],[Remit]],tblLines[[#This Row],[Remit]]<=tblLines[[#This Row],[Possible_item4]]),"R1",IF(AND((tblLines[[#This Row],[Final_due]]>Summary!$B$6),tblLines[[#This Row],[Remit]]>tblLines[[#This Row],[Final_due]]),"R2",IF(tblLines[[#This Row],[Remit]]<=tblLines[[#This Row],[Final_due]],"R3","R4"))),IF(tblLines[[#This Row],[Final_due]]<Summary!$B$2,IF(OR((tblLines[[#This Row],[Final_due]]>Summary!$B$6),AND((tblLines[[#This Row],[Possible_item4]]<>""),Summary!$B$2<=tblLines[[#This Row],[Possible_item4]])),"N1","N2"),"N3")))))) -> D1 | AI11: =IF(tblLines[[#This Row],[Branch]]="","",INDEX(tblCodes[verdict],MATCH(tblLines[[#This Row],[Branch]],tblCodes[code],0))) -> ON_TIME | AJ11: =IF(tblLines[[#This Row],[Branch]]="","",T(INDEX(tblCodes[unassessable],MATCH(tblLines[[#This Row],[Branch]],tblCodes[code],0)))) | AK11: =IF(tblLines[[#This Row],[Branch]]="",0,INDEX(tblCodes[exposed],MATCH(tblLines[[#This Row],[Branch]],tblCodes[code],0))) -> 0 | AL11: =IF(tblLines[[#This Row],[Branch]]="",0,INDEX(tblCodes[stale],MATCH(tblLines[[#This Row],[Branch]],tblCodes[code],0))) -> 0 | AM11: =IF(tblLines[[#This Row],[Branch]]="",0,INDEX(tblCodes[otrc],MATCH(tblLines[[#This Row],[Branch]],tblCodes[code],0))*tblLines[[#This Row],[Receipt_credit]]) -> 450 | AN11: =IF((tblLines[[#This Row],[Exposed]]=1),MAX(ROUND(tblLines[[#This Row],[sg_amount]],2)-tblLines[[#This Row],[OTRC]],0),"") | AO11: =IF((tblLines[[#This Row],[Exposed]]=1),IF(AND(tblLines[[#This Row],[Settled]]<>"",tblLines[[#This Row],[Stale_prepay]]=0,tblLines[[#This Row],[Settled]]>tblLines[[#This Row],[Final_due]],OR(Summary!$B$3="",tblLines[[#This Row],[Settled]]<Summary!$B$3)),MIN(tblLines[[#This Row],[Receipt_credit]],tblLines[[#This Row],[Base_shortfall]]),0),"") | AP11: =IF((tblLines[[#This Row],[Exposed]]=1),MAX(tblLines[[#This Row],[Base_shortfall]]-tblLines[[#This Row],[Offset_s18D]],0),"") | AQ11: =IF((tblLines[[#This Row],[Exposed]]=1),IF(AND(tblLines[[#This Row],[Settled]]<>"",tblLines[[#This Row],[Stale_prepay]]=0,(tblLines[[#This Row],[Receipt_credit]]>=tblLines[[#This Row],[sg_amount]])),"fund receipt",IF(AND(tblLines[[#This Row],[Settled]]<>"",tblLines[[#This Row],[Stale_prepay]]=0),"as-at date (shortfall remains after part receipt)",IF(AND(OR(tblLines[[#This Row],[Settled]]<>"",tblLines[[#This Row],[Remit]]<>""),tblLines[[#This Row],[Stale_prepay]]=0),"as-at date (no fund receipt recorded)","as-at date (nothing applied to this payday)"))),"") | AR11: =IF((tblLines[[#This Row],[Exposed]]=1),IF(AND(tblLines[[#This Row],[Settled]]<>"",tblLines[[#This Row],[Stale_prepay]]=0,(tblLines[[#This Row],[Receipt_credit]]>=tblLines[[#This Row],[sg_amount]])),tblLines[[#This Row],[Settled]],Summary!$B$2),"") | AS11: =IF((tblLines[[#This Row],[Exposed]]=1),MIN(IF(Summary!$B$3="",DATE(2030,12,31),Summary!$B$3-1),IF(AND(tblLines[[#This Row],[Settled]]<>"",tblLines[[#This Row],[Stale_prepay]]=0,(tblLines[[#This Row],[Receipt_credit]]>=tblLines[[#This Row],[sg_amount]]),tblLines[[#This Row],[Final_shortfall]]=0),tblLines[[#This Row],[Settled]],Summary!$B$2)),"") | AT11: =IF((tblLines[[#This Row],[Exposed]]=1),IF(tblLines[[#This Row],[Past_horizon]]=1,"",MAX(tblLines[[#This Row],[Outstanding_to]]-tblLines[[#This Row],[Final_due]],0)),"") | AU11: =IF((tblLines[[#This Row],[Exposed]]=1),IF(tblLines[[#This Row],[NEC_end]]>tblLines[[#This Row],[Final_due]],tblLines[[#This Row],[Base_shortfall]]*(EXP(SUMPRODUCT((((((tblLines[[#This Row],[NEC_end]]+tblGic[to]-ABS(tblLines[[#This Row],[NEC_end]]-tblGic[to]))/2)-(((tblLines[[#This Row],[Final_due]]+1)+tblGic[from]+ABS((tblLines[[#This Row],[Final_due]]+1)-tblGic[from]))/2)+1)>0)*(((tblLines[[#This Row],[NEC_end]]+tblGic[to]-ABS(tblLines[[#This Row],[NEC_end]]-tblGic[to]))/2)-(((tblLines[[#This Row],[Final_due]]+1)+tblGic[from]+ABS((tblLines[[#This Row],[Final_due]]+1)-tblGic[from]))/2)+1))*LN(1+tblGic[annual_pct]/100/tblGic[divisor])))-1),0),"") | AV11: =IF((tblLines[[#This Row],[Exposed]]=1),IF(tblLines[[#This Row],[NEC_end]]>Summary!$B$7,1,0),"") | AW11: =IF((tblLines[[#This Row],[Exposed]]=1),ROUND(tblLines[[#This Row],[Final_shortfall]],2),"") | AX11: =IF((tblLines[[#This Row],[Exposed]]=1),ROUND(tblLines[[#This Row],[NEC]],2),"") | AY11: =IF((tblLines[[#This Row],[Exposed]]=1),0,"") | AZ11: =IF((tblLines[[#This Row],[Exposed]]=1),ROUND(0.6*(tblLines[[#This Row],[Final_shortfall]]+tblLines[[#This Row],[NEC]]),2),"") | BA11: =IF((tblLines[[#This Row],[Exposed]]=1),tblLines[[#This Row],[Shortfall_r]]+tblLines[[#This Row],[NEC_r]]+tblLines[[#This Row],[Uplift_best]],"") | BB11: =IF((tblLines[[#This Row],[Exposed]]=1),tblLines[[#This Row],[Shortfall_r]]+tblLines[[#This Row],[NEC_r]]+tblLines[[#This Row],[Uplift_worst]],"") | BC11: =IF(AND(tblLines[[#This Row],[Flag_db]]<>1,ISNUMBER(tblLines[[#This Row],[sg_amount]]),tblLines[[#This Row],[sg_amount]]>0,tblLines[[#This Row],[Cap]]>0,OR(ISNUMBER(tblLines[[#This Row],[fund_received_date]]),ISNUMBER(tblLines[[#This Row],[remitted_date]])),IF(ISNUMBER(tblLines[[#This Row],[fund_received_date]]),tblLines[[#This Row],[fund_received_date]],tblLines[[#This Row],[remitted_date]])<=DATE(2026,7,28)),1,0) -> 0 | BD11: =IF(tblLines[[#This Row],[Settled]]<>"",1,0) -> 1 | BE11: =IF(AND(tblLines[[#This Row],[Verdict]]<>"",tblLines[[#This Row],[Verdict]]<>"SKIPPED",ISNUMBER(tblLines[[#This Row],[sg_amount]]),tblLines[[#This Row],[sg_amount]]>0),1,0) -> 1 | BF11: =IF(COUNTIFS(tblLines[employee_id],tblLines[[#This Row],[employee_id]],tblLines[payment_date],tblLines[[#This Row],[payment_date]],tblLines[sg_amount],tblLines[[#This Row],[sg_amount]],tblLines[remitted_date],tblLines[[#This Row],[remitted_date]]&"",tblLines[fund_received_date],tblLines[[#This Row],[fund_received_date]]&"")>1,1,0) -> 0

Sheet Codes
A1: code | B1: verdict | C1: unassessable | D1: otrc | E1: stale | F1: exposed
A2: DB | B2: SKIPPED | D2: 0 | E2: 0 | F2: 0
A3: NIL | B3: UNKNOWN | D3: 0 | E3: 0 | F3: 0
A4: A1 | B4: ON_TIME | D4: 1 | E4: 0 | F4: 0
A5: A2 | B5: UNKNOWN | D5: 1 | E5: 0 | F5: 0
A6: A3 | B6: UNKNOWN | C6: UNPAID or NOT_YET_DUE | D6: 1 | E6: 0 | F6: 0
A7: A4 | B7: UNPAID | D7: 1 | E7: 0 | F7: 1
A8: S1 | B8: UNKNOWN | D8: 0 | E8: 1 | F8: 0
A9: S2 | B9: UNKNOWN | C9: LATE or NOT_YET_DUE | D9: 0 | E9: 1 | F9: 0
A10: S3 | B10: LATE | D10: 0 | E10: 1 | F10: 1
A11: B1 | B11: UNKNOWN | C11: LATE or ON_TIME | D11: 0 | E11: 0 | F11: 0
A12: B2 | B12: UNKNOWN | C12: LATE or NOT_YET_DUE | D12: 0 | E12: 0 | F12: 0
A13: B3 | B13: UNKNOWN | C13: LATE or UNPAID | D13: 0 | E13: 0 | F13: 0
A14: C1 | B14: UNKNOWN | C14: LATE or ON_TIME | D14: 0 | E14: 0 | F14: 0
A15: C2 | B15: UNKNOWN | C15: LATE or NOT_YET_DUE | D15: 0 | E15: 0 | F15: 0
A16: D1 | B16: ON_TIME | D16: 1 | E16: 0 | F16: 0
A17: D2 | B17: UNKNOWN | C17: UNPAID or NOT_YET_DUE | D17: 1 | E17: 0 | F17: 0
A18: D3 | B18: UNPAID | D18: 1 | E18: 0 | F18: 1
A19: D4 | B19: UNKNOWN | D19: 1 | E19: 0 | F19: 0
A20: E | B20: LATE | D20: 0 | E20: 0 | F20: 1
A21: R1 | B21: UNKNOWN | C21: LATE or AT_RISK | D21: 0 | E21: 0 | F21: 0
A22: R2 | B22: UNKNOWN | C22: LATE or AT_RISK | D22: 0 | E22: 0 | F22: 0
A23: R3 | B23: AT_RISK | D23: 0 | E23: 0 | F23: 0
A24: R4 | B24: LATE | D24: 0 | E24: 0 | F24: 1
A25: N1 | B25: UNKNOWN | C25: UNPAID or NOT_YET_DUE | D25: 0 | E25: 0 | F25: 0
A26: N2 | B26: UNPAID | D26: 0 | E26: 0 | F26: 1
A27: N3 | B27: UNKNOWN | D27: 0 | E27: 0 | F27: 0

Sheet Holidays
A1: date | B1: name | C1: jurisdictions
A2: 46023 | B2: New Year's Day | C2: ACT, NSW, NT, QLD, SA, TAS, VIC, WA
A3: 46048 | B3: Australia Day | C3: ACT, NSW, NT, QLD, SA, TAS, VIC, WA
A4: 46083 | B4: Labour Day | C4: WA
A5: 46090 | B5: Adelaide Cup Day; Canberra Day; Eight Hours Day; Labour Day | C5: ACT, SA, TAS, VIC
A6: 46115 | B6: Good Friday | C6: ACT, NSW, NT, QLD, SA, TAS, VIC, WA
A7: 46116 | B7: Easter Saturday | C7: ACT, NSW, NT, QLD, SA, VIC
A8: 46117 | B8: Easter Sunday | C8: ACT, NSW, NT, QLD, SA, VIC, WA
A9: 46118 | B9: Easter Monday | C9: ACT, NSW, NT, QLD, SA, TAS, VIC, WA
A10: 46137 | B10: ANZAC Day | C10: ACT, NSW, NT, QLD, SA, TAS, VIC, WA
A11: 46139 | B11: ANZAC Day (observed) | C11: ACT, NSW, WA
A12: 46146 | B12: Labour Day; May Day | C12: NT, QLD
A13: 46174 | B13: Reconciliation Day; Western Australia Day | C13: ACT, WA
... A40: 46749 | B40: Boxing Day; Boxing Day (observed); Proclamation Day (observed) | C40: ACT, NSW, NT, QLD, SA, TAS, VIC, WA
A43: Whole-of-jurisdiction public holidays under SGAA s 6(1); weekends are computed. Official sources checked through 2027-08-31. To review a later deadline, add the official dates here and move the coverage date on Summary.
A44: Provisional dates not applied (business days until confirmed): 2027-09-24 Friday before the AFL Grand Final; 2028-01-01 New Year's Day; 2028-01-03 New Year's Day; New Year's Day (observed); 2028-01-26 Australia Day; 2028-03-06 Labour Day; 2028-03-13 Adelaide Cup Day; Canberra Day; Eight Hours Day; Labour Day; 2028-04-14 Good Friday; 2028-04-15 Easter Saturday; 2028-04-16 Easter Sunday; 2028-04-17 Easter Monday; 2028-04-25 ANZAC Day; 2028-05-01 Labour Day; May Day; 2028-05-29 Reconciliation Day; 2028-06-05 Western Australia Day; 2028-06-12 King's Birthday; 2028-08-07 Picnic Day; 2028-09-29 Friday before the AFL Grand Final; 2028-10-02 King's Birthday; Labour Day; 2028-12-25 Christmas Day; 2028-12-26 Boxing Day; Proclamation Day

Sheet GIC
A1: from | B1: to | C1: annual_pct | D1: divisor | E1: basis | F1: seen
A2: 46113 | B2: 46203 | C2: 10.96 | D2: 365 | E2: known | F2: 2026-08-14
A3: 46204 | B3: 46295 | C3: 11.43 | D3: 365 | E3: known | F3: 2026-08-14
A4: 46296 | B4: 46387 | C4: 11.43 | D4: 365 | E4: estimate
A5: 46388 | B5: 46752 | C5: 11.43 | D5: 365 | E5: estimate
A6: 46753 | B6: 47118 | C6: 11.43 | D6: 366 | E6: estimate
A7: 47119 | B7: 47483 | C7: 11.43 | D7: 365 | E7: estimate
A8: 47484 | B8: 47848 | C8: 11.43 | D8: 365 | E8: estimate
A11: General interest charge, TAA 1953 s 8AAD: annual rate divided by the days in the calendar year. Rows marked estimate carry the last known rate forward, as the engine does, and the workbook flags any line that uses them. Update each quarter from the ATO GIC rates page and set basis to known.

Sheet Summary
A1: Inputs
A2: As-at date (notional earnings on unpaid lines run to it) | B2: 46244
A3: ATO assessment date (blank if none has issued)
A4: LCR 2026/1 transition allocation reconciled and confirmed (Y/N) | B4: Y
A5: Remittance-only review accepted (Y/N) | B5: N
A6: Holiday coverage verified until | B6: 46630
A7: GIC table last known quarter ends | B7: =_xlfn.MAXIFS(tblGic[to],tblGic[basis],"known") -> 46295
A9: Summary
A10: ON_TIME | B10: =COUNTIF(tblLines[Verdict],"ON_TIME") -> 5
A11: AT_RISK | B11: =COUNTIF(tblLines[Verdict],"AT_RISK") -> 1
A12: LATE | B12: =COUNTIF(tblLines[Verdict],"LATE") -> 2
A13: UNPAID | B13: =COUNTIF(tblLines[Verdict],"UNPAID") -> 1
A14: UNKNOWN | B14: =COUNTIF(tblLines[Verdict],"UNKNOWN") -> 0
A15: SKIPPED | B15: =COUNTIF(tblLines[Verdict],"SKIPPED") -> 1
A16: Lines with exposure | B16: =SUM(tblLines[Exposed]) -> 3
A17: Total final shortfall | B17: =ROUND(SUM(tblLines[Shortfall_r]),2) -> 780
A18: Total notional earnings | B18: =ROUND(SUM(tblLines[NEC_r]),2) -> 8.07
A19: Experimental SG charge estimate, low | B19: =ROUND(SUM(tblLines[SGC_low]),2) -> 788.07
A20: Experimental SG charge estimate, high | B20: =ROUND(SUM(tblLines[SGC_high]),2) -> 1260.92
A21: Attention-driving UNKNOWN lines | B21: =SUMPRODUCT(--(tblLines[Unassessable_between]<>"")) -> 0
A22: Remittance-only file (no assessable line has a fund receipt) | B22: =IF(AND(SUM(tblLines[Assessable])>0,SUMPRODUCT(tblLines[Assessable]*tblLines[Receipt_established])=0),"YES","NO") -> NO
A24: Overall status | B24: ='Review Checks'!B13 -> REVIEW

Sheet Review Checks
A1: Check | B1: Result | C1: Count or value | D1: Example row (employee_id)
A2: Every register value can be read | B2: =IF(C2=0,"PASS","BLOCKED") -> PASS | C2: =SUMPRODUCT(--(tblLines[Row_problem]<>"")) -> 0 | D2: {=IF(C2=0,"",INDEX(tblLines[employee_id],SUMPRODUCT(MAX((tblLines[Row_problem]<>"")*(ROW(tblLines[employee_id])-1)))))}
A3: No formula in an input cell | B3: =IF(C3=0,"PASS","BLOCKED") -> PASS | C3: =SUM(tblLines[Guard]) -> 0 | D3: {=IF(C3=0,"",INDEX(tblLines[employee_id],SUMPRODUCT(MAX((tblLines[Guard]=1)*(ROW(tblLines[employee_id])-1)))))}
A4: Contributions dated on or before 28 July 2026 are reconciled under LCR 2026/1 | B4: =IF(OR(C4=0,Summary!$B$4="Y"),"PASS","BLOCKED") -> PASS | C4: =SUM(tblLines[Transition_row]) -> 2 | D4: {=IF(C4=0,"",INDEX(tblLines[employee_id],SUMPRODUCT(MAX((tblLines[Transition_row]=1)*(ROW(tblLines[employee_id])-1)))))} -> EMP003
A5: No line is LATE or UNPAID | B5: =IF(C5=0,"PASS","REVIEW") -> REVIEW | C5: =SUM(tblLines[Exposed]) -> 3 | D5: {=IF(C5=0,"",INDEX(tblLines[employee_id],SUMPRODUCT(MAX((tblLines[Exposed]=1)*(ROW(tblLines[employee_id])-1)))))} -> EMP001
A6: No line is left undecided by the deadline facts | B6: =IF(C6=0,"PASS","REVIEW") -> PASS | C6: =SUMPRODUCT(--(tblLines[Unassessable_between]<>"")) -> 0 | D6: {=IF(C6=0,"",INDEX(tblLines[employee_id],SUMPRODUCT(MAX((tblLines[Unassessable_between]<>"")*(ROW(tblLines[employee_id])-1)))))}
A7: The file can produce ON_TIME, or remittance-only review is accepted | B7: =IF(OR(Summary!B22="NO",Summary!$B$5="Y"),"PASS","REVIEW") -> PASS | C7: =Summary!B22 -> NO
A8: Deadlines inside the holiday coverage (figures past it are a maximum) | B8: =IF(C8=0,"PASS","NOTE") -> PASS | C8: =SUM(tblLines[Past_horizon]) -> 0 | D8: {=IF(C8=0,"",INDEX(tblLines[employee_id],SUMPRODUCT(MAX((tblLines[Past_horizon]=1)*(ROW(tblLines[employee_id])-1)))))}
A9: Notional earnings use only known GIC quarters | B9: =IF(C9=0,"PASS","NOTE") -> PASS | C9: =SUM(tblLines[GIC_estimated]) -> 0 | D9: {=IF(C9=0,"",INDEX(tblLines[employee_id],SUMPRODUCT(MAX((tblLines[GIC_estimated]=1)*(ROW(tblLines[employee_id])-1)))))}
A10: No identical lines (a doubled export counts a payday twice) | B10: =IF(C10=0,"PASS","NOTE") -> PASS | C10: =SUM(tblLines[Duplicate]) -> 0 | D10: {=IF(C10=0,"",INDEX(tblLines[employee_id],SUMPRODUCT(MAX((tblLines[Duplicate]=1)*(ROW(tblLines[employee_id])-1)))))}
A11: Lines assessed at a nil SG amount (nothing to assess) | B11: =IF(C11=0,"PASS","NOTE") -> PASS | C11: =COUNTIF(tblLines[Branch],"NIL") -> 0 | D11: {=IF(C11=0,"",INDEX(tblLines[employee_id],SUMPRODUCT(MAX((tblLines[Branch]="NIL")*(ROW(tblLines[employee_id])-1)))))}
A13: Overall status | B13: =IF(COUNTIF(B2:B11,"BLOCKED")>0,"BLOCKED",IF(COUNTIF(B2:B11,"REVIEW")>0,"REVIEW","PASS")) -> REVIEW
A15: Assumptions the engine prints with every run
A16: The statutory test is receipt by the fund with enough information to allocate it (SGAA s 18C(1)(c)). A remittance date is operational evidence only; clearing-house transit is the employer's risk.
A17: Item 4 (s 18C(2)) aligns a later payday only to an earlier eligible contribution the register evidences as received on time; a positive amount or a remittance alone gives a possible upper bound and an attention-driving UNKNOWN where it would change the verdict.
A18: Notional earnings compound daily at the general interest charge on the base shortfall from the day after the deadline while the final shortfall remains greater than nil (s 19A, LCR 2026/3). A part receipt does not slow the accrual.
A19: The uplift range runs from 0 per cent (clean history and a voluntary disclosure within 30 days) to 60 per cent (prior history, no disclosure). The ATO, not this workbook, decides which reductions apply.
A20: Each exposure component is rounded to cents half up and the totals are built from the rounded parts. TAA 1953 s 16B applies a five-cent down-round only to the Commissioner's final assessed charge, which is not reproduced.
A21: Not estimated: choice loading, the maximum contributions base, the late payment penalty, interest after assessment, exceptional-circumstances determinations, fund deed and award obligations, and paydays before 1 July 2026.

Sheet Sources & Version
A1: Item | B1: Value
A2: Workbook engine version | B2: 0.1.3
A3: Desktop Excel build used to calculate cached values | B3: Excel 16.0 build 20326
A4: Law | B4: Superannuation Guarantee (Administration) Act 1992 as amended by the Treasury Laws Amendment (Payday Superannuation) Act 2025 (No. 57 of 2025) and the Superannuation Guarantee Charge Amendment Act 2025 (No. 58 of 2025); Payday Superannuation Regulations 2026 (F2026L00133); F2026L00784; LCR 2026/1, 2026/2 and 2026/3
A5: Primary-source review | B5: docs/primary-source-review-2026-08-15.md in the repository
A6: Holiday calendar | B6: Official whole-of-jurisdiction sources checked through 2027-08-31
A7: GIC rates | B7: ATO general interest charge rates, known through 2026-09-30; later days carry the last known rate as an estimate
A8: No-install explainer | B8: https://duguid.com.au/tools/payday-super/
A9: Disclaimer | B9: Experimental review aid. Not a compliance determination, not an ATO assessment, and not tax, legal or financial advice.
